Workbook
Name ListaCategorias: 'Catálogo Productos'!$C$3:$C$52
Name ListaProductos: 'Catálogo Productos'!$B$3:$B$200

Sheet 📋 Instrucciones
A1: ÁVILA MUSIC - CÓMO AGREGAR UN NUEVO MES
A3: PASOS PARA CREAR EL REGISTRO DE UN NUEVO MES:
A5: PASO 1: Haz clic derecho en la pestaña 'Febrero 2026 - Ventas'
A6: → Selecciona 'Mover o copiar'
A7: → Marca la casilla 'Crear una copia'
A8: → Renombra la nueva hoja como: 'Abril 2026 - Ventas'
A10: PASO 2: Haz lo mismo con 'PLANTILLA - Resumen'
A11: → Renombra la nueva hoja como: 'Abril 2026 - Resumen'
A13: PASO 3: En la nueva hoja 'Abril 2026 - Resumen',
A14: cambia todas las referencias de 'Febrero 2026 - Ventas'
A15: por 'Abril 2026 - Ventas'
A17: PASO 4: Ve a 'Configuración' y actualiza el Mes y Año activo
... A48: NOTA: Febrero y Marzo 2026 ya tienen sus precios congelados.

Sheet Configuración
A1: ÁVILA MUSIC - CONFIGURACIÓN FINANCIERA
A3: COMISIONES Y COSTOS MERCADOLIBRE
B4: Días del Mes | C4: 31 | D4: Días del mes activo — ajusta si el mes tiene 28, 29 o 30 días
B5: Comisión MercadoLibre (%) | C5: 0.11 | D5: Porcentaje que cobra ML por cada venta
B6: Costo de Envío por Venta (USD) | C6: 1.3 | D6: Configurable — baja si superas 50 ventas/mes
B7: Tasa de referencia (USD) | C7: 457.5 | D7: Referencia interna — no se usa en cálculos USD
B8: Factor de ajuste (%) | C8: 0.34 | D8: No aplica en modelo 100% USD
B9: Lead Time Proveedor (meses) | C9: 4 | D9: Meses desde pedido hasta recibir (producción + envío)
B10: Colchón de Seguridad (meses) | C10: 1 | D10: Meses de colchón de seguridad (recomendado: 1 mes mínimo con 4 meses lead time)
B11: Días Transcurridos del Mes | C11: 10 | D11: Días ya transcurridos del mes activo (actualiza regularmente)
A12: DISTRIBUCIÓN DE GANANCIA NETA
B14: % Reinversión | C14: 0.7 | D14: Para comprar más inventario y hacer crecer el negocio
B15: % Sueldo / Ganancia Personal | C15: 0.3 | D15: Tu compensación — úsalo para ti o para decisiones
B16: Total (%) | C16: =C14+C15 -> 1 | D16: =IF(C16=1,"✓ Correcto","⚠ Debe sumar 100%") -> ✓ Correcto
A18: MES ACTIVO DE REGISTRO
B20: Mes | C20: Abril | D20: Nombre del mes que estás registrando
B21: Año | C21: 2026 | D21: Año actual
A23: LEYENDA
B25: Celdas amarillas + texto azul | D25: Datos que TU modificas (inputs)
B26: Celdas grises + texto negro | D26: Formulas automaticas (NO tocar)

Sheet Abril 2026 - Ventas
A1: ÁVILA MUSIC - REGISTRO DE VENTAS DETALLADO
A2: ='Configuración'!C17&" "&'Configuración'!C18
A3: Al cerrar el mes: selecciona E5:F54 -> Copiar -> Pegado Especial -> Valores (congela precios historicos)
A4: # | B4: Fecha | C4: Producto | D4: Categoría | E4: Costo USD | F4: Precio Venta USD | G4: Comisión ML | H4: Envío Gratis | I4: Comisión ML | J4: Costo Envío USD | K4: Ingreso Neto USD | L4: Ganancia Bruta USD | M4: Margen % | N4: Descuento USD
A5: 1 | B5: 46113 | C5: Cuerdas de Violin 4/4 | D5: =IFERROR(VLOOKUP(C5,'Catálogo Productos'!$B$3:$E$200,2,0),"") -> Violin | E5: =IFERROR(VLOOKUP(C5,'Catálogo Productos'!$B$3:$E$200,3,0),"") -> 1.06 | F5: =IFERROR(VLOOKUP(C5,'Catálogo Productos'!$B$3:$E$200,4,0),"") -> 4.99 | G5: =IF(F5="","",IF(I5="SÍ",F5*'Configuración'!$C$5,0)) -> 0.5489 | H5: SÍ | I5: SÍ | J5: =IF(F5="","",IF(H5="SÍ",'Configuración'!$C$6,0)) -> 1.3 | K5: =IF(F5="","",F5-G5-J5) -> 3.1411 | L5: =IF(F5="","",K5-E5-IF(N5="",0,N5)) -> 2.0811 | M5: =IF(F5="","",IF(K5=0,0,L5/K5)) -> 0.6625386
A6: 2 | B6: 46113 | C6: Cuerdas Alice Clasica A106 | D6: =IFERROR(VLOOKUP(C6,'Catálogo Productos'!$B$3:$E$200,2,0),"") -> Guitarra Clasica | E6: =IFERROR(VLOOKUP(C6,'Catálogo Productos'!$B$3:$E$200,3,0),"") -> 1.21 | F6: =IFERROR(VLOOKUP(C6,'Catálogo Productos'!$B$3:$E$200,4,0),"") -> 5.49 | G6: =IF(F6="","",IF(I6="SÍ",F6*'Configuración'!$C$5,0)) -> 0.6039 | H6: SÍ | I6: SÍ | J6: =IF(F6="","",IF(H6="SÍ",'Configuración'!$C$6,0)) -> 1.3 | K6: =IF(F6="","",F6-G6-J6) -> 3.5861 | L6: =IF(F6="","",K6-E6-IF(N6="",0,N6)) -> 2.3761 | M6: =IF(F6="","",IF(K6=0,0,L6/K6)) -> 0.6625861
A7: 3 | B7: 46113 | C7: Cuerdas Alice Electrica SL | D7: =IFERROR(VLOOKUP(C7,'Catálogo Productos'!$B$3:$E$200,2,0),"") -> Guitarra Electrica | E7: =IFERROR(VLOOKUP(C7,'Catálogo Productos'!$B$3:$E$200,3,0),"") -> 1.21 | F7: =IFERROR(VLOOKUP(C7,'Catálogo Productos'!$B$3:$E$200,4,0),"") -> 5.49 | G7: =IF(F7="","",IF(I7="SÍ",F7*'Configuración'!$C$5,0)) -> 0.6039 | H7: No | I7: SÍ | J7: =IF(F7="","",IF(H7="SÍ",'Configuración'!$C$6,0)) -> 0 | K7: =IF(F7="","",F7-G7-J7) -> 4.8861 | L7: =IF(F7="","",K7-E7-IF(N7="",0,N7)) -> 3.6761 | M7: =IF(F7="","",IF(K7=0,0,L7/K7)) -> 0.75235873
A8: 4 | B8: 46114 | C8: Cable Hebikuo XA03 | D8: =IFERROR(VLOOKUP(C8,'Catálogo Productos'!$B$3:$E$200,2,0),"") -> Cables | E8: =IFERROR(VLOOKUP(C8,'Catálogo Productos'!$B$3:$E$200,3,0),"") -> 1.91 | F8: =IFERROR(VLOOKUP(C8,'Catálogo Productos'!$B$3:$E$200,4,0),"") -> 10 | G8: =IF(F8="","",IF(I8="SÍ",F8*'Configuración'!$C$5,0)) -> 1.1 | H8: SÍ | I8: SÍ | J8: =IF(F8="","",IF(H8="SÍ",'Configuración'!$C$6,0)) -> 1.3 | K8: =IF(F8="","",F8-G8-J8) -> 7.6 | L8: =IF(F8="","",K8-E8-IF(N8="",0,N8)) -> 5.69 | M8: =IF(F8="","",IF(K8=0,0,L8/K8)) -> 0.74868421
A9: 5 | B9: 46114 | C9: Cuerdas Alice Electrica SL | D9: =IFERROR(VLOOKUP(C9,'Catálogo Productos'!$B$3:$E$200,2,0),"") -> Guitarra Electrica | E9: =IFERROR(VLOOKUP(C9,'Catálogo Productos'!$B$3:$E$200,3,0),"") -> 1.21 | F9: =IFERROR(VLOOKUP(C9,'Catálogo Productos'!$B$3:$E$200,4,0),"") -> 5.49 | G9: =IF(F9="","",IF(I9="SÍ",F9*'Configuración'!$C$5,0)) -> 0.6039 | H9: SÍ | I9: SÍ | J9: =IF(F9="","",IF(H9="SÍ",'Configuración'!$C$6,0)) -> 1.3 | K9: =IF(F9="","",F9-G9-J9) -> 3.5861 | L9: =IF(F9="","",K9-E9-IF(N9="",0,N9)) -> 2.3761 | M9: =IF(F9="","",IF(K9=0,0,L9/K9)) -> 0.6625861
A10: 6 | B10: 46114 | C10: Cuerdas Alice Electrica SL | D10: =IFERROR(VLOOKUP(C10,'Catálogo Productos'!$B$3:$E$200,2,0),"") -> Guitarra Electrica | E10: =IFERROR(VLOOKUP(C10,'Catálogo Productos'!$B$3:$E$200,3,0),"") -> 1.21 | F10: =IFERROR(VLOOKUP(C10,'Catálogo Productos'!$B$3:$E$200,4,0),"") -> 5.49 | G10: =IF(F10="","",IF(I10="SÍ",F10*'Configuración'!$C$5,0)) -> 0.6039 | H10: SÍ | I10: SÍ | J10: =IF(F10="","",IF(H10="SÍ",'Configuración'!$C$6,0)) -> 1.3 | K10: =IF(F10="","",F10-G10-J10) -> 3.5861 | L10: =IF(F10="","",K10-E10-IF(N10="",0,N10)) -> 2.3761 | M10: =IF(F10="","",IF(K10=0,0,L10/K10)) -> 0.6625861
A11: 7 | B11: 46114 | C11: Cuerdas Alice Electrica SL | D11: =IFERROR(VLOOKUP(C11,'Catálogo Productos'!$B$3:$E$200,2,0),"") -> Guitarra Electrica | E11: =IFERROR(VLOOKUP(C11,'Catálogo Productos'!$B$3:$E$200,3,0),"") -> 1.21 | F11: =IFERROR(VLOOKUP(C11,'Catálogo Productos'!$B$3:$E$200,4,0),"") -> 5.49 | G11: =IF(F11="","",IF(I11="SÍ",F11*'Configuración'!$C$5,0)) -> 0.6039 | H11: No | I11: SÍ | J11: =IF(F11="","",IF(H11="SÍ",'Configuración'!$C$6,0)) -> 0 | K11: =IF(F11="","",F11-G11-J11) -> 4.8861 | L11: =IF(F11="","",K11-E11-IF(N11="",0,N11)) -> 3.6761 | M11: =IF(F11="","",IF(K11=0,0,L11/K11)) -> 0.75235873
A12: 8 | B12: 46116 | C12: Base pared Guitarra/Bajo | D12: =IFERROR(VLOOKUP(C12,'Catálogo Productos'!$B$3:$E$200,2,0),"") -> Bases, Stand, Atriles | E12: =IFERROR(VLOOKUP(C12,'Catálogo Productos'!$B$3:$E$200,3,0),"") -> 0.5 | F12: =IFERROR(VLOOKUP(C12,'Catálogo Productos'!$B$3:$E$200,4,0),"") -> 4.99 | G12: =IF(F12="","",IF(I12="SÍ",F12*'Configuración'!$C$5,0)) -> 0.5489 | H12: SÍ | I12: SÍ | J12: =IF(F12="","",IF(H12="SÍ",'Configuración'!$C$6,0)) -> 1.3 | K12: =IF(F12="","",F12-G12-J12) -> 3.1411 | L12: =IF(F12="","",K12-E12-IF(N12="",0,N12)) -> 2.6411 | M12: =IF(F12="","",IF(K12=0,0,L12/K12)) -> 0.84082009
A13: 9 | B13: 46116 | C13: Base pared Guitarra/Bajo | D13: =IFERROR(VLOOKUP(C13,'Catálogo Productos'!$B$3:$E$200,2,0),"") -> Bases, Stand, Atriles | E13: =IFERROR(VLOOKUP(C13,'Catálogo Productos'!$B$3:$E$200,3,0),"") -> 0.5 | F13: =IFERROR(VLOOKUP(C13,'Catálogo Productos'!$B$3:$E$200,4,0),"") -> 4.99 | G13: =IF(F13="","",IF(I13="SÍ",F13*'Configuración'!$C$5,0)) -> 0.5489 | H13: SÍ | I13: SÍ | J13: =IF(F13="","",IF(H13="SÍ",'Configuración'!$C$6,0)) -> 1.3 | K13: =IF(F13="","",F13-G13-J13) -> 3.1411 | L13: =IF(F13="","",K13-E13-IF(N13="",0,N13)) -> 2.6411 | M13: =IF(F13="","",IF(K13=0,0,L13/K13)) -> 0.84082009
A14: 10 | B14: 46117 | C14: Base pared Guitarra/Bajo | D14: =IFERROR(VLOOKUP(C14,'Catálogo Productos'!$B$3:$E$200,2,0),"") -> Bases, Stand, Atriles | E14: =IFERROR(VLOOKUP(C14,'Catálogo Productos'!$B$3:$E$200,3,0),"") -> 0.5 | F14: =IFERROR(VLOOKUP(C14,'Catálogo Productos'!$B$3:$E$200,4,0),"") -> 4.99 | G14: =IF(F14="","",IF(I14="SÍ",F14*'Configuración'!$C$5,0)) -> 0.5489 | H14: No | I14: SÍ | J14: =IF(F14="","",IF(H14="SÍ",'Configuración'!$C$6,0)) -> 0 | K14: =IF(F14="","",F14-G14-J14) -> 4.4411 | L14: =IF(F14="","",K14-E14-IF(N14="",0,N14)) -> 3.9411 | M14: =IF(F14="","",IF(K14=0,0,L14/K14)) -> 0.88741528
A15: 11 | B15: 46118 | C15: Capotraste | D15: =IFERROR(VLOOKUP(C15,'Catálogo Productos'!$B$3:$E$200,2,0),"") -> Capostraste | E15: =IFERROR(VLOOKUP(C15,'Catálogo Productos'!$B$3:$E$200,3,0),"") -> 0.65 | F15: =IFERROR(VLOOKUP(C15,'Catálogo Productos'!$B$3:$E$200,4,0),"") -> 6.99 | G15: =IF(F15="","",IF(I15="SÍ",F15*'Configuración'!$C$5,0)) -> 0.7689 | H15: SÍ | I15: SÍ | J15: =IF(F15="","",IF(H15="SÍ",'Configuración'!$C$6,0)) -> 1.3 | K15: =IF(F15="","",F15-G15-J15) -> 4.9211 | L15: =IF(F15="","",K15-E15-IF(N15="",0,N15)) -> 4.2711 | M15: =IF(F15="","",IF(K15=0,0,L15/K15)) -> 0.86791571
A16: 12 | B16: 46118 | C16: Cuerdas Alice Electrica L | D16: =IFERROR(VLOOKUP(C16,'Catálogo Productos'!$B$3:$E$200,2,0),"") -> Guitarra Electrica | E16: =IFERROR(VLOOKUP(C16,'Catálogo Productos'!$B$3:$E$200,3,0),"") -> 1.21 | F16: =IFERROR(VLOOKUP(C16,'Catálogo Productos'!$B$3:$E$200,4,0),"") -> 5.49 | G16: =IF(F16="","",IF(I16="SÍ",F16*'Configuración'!$C$5,0)) -> 0.6039 | H16: SÍ | I16: SÍ | J16: =IF(F16="","",IF(H16="SÍ",'Configuración'!$C$6,0)) -> 1.3 | K16: =IF(F16="","",F16-G16-J16) -> 3.5861 | L16: =IF(F16="","",K16-E16-IF(N16="",0,N16)) -> 2.3761 | M16: =IF(F16="","",IF(K16=0,0,L16/K16)) -> 0.6625861
... A21: 17 | B21: 46119 | C21: Cuerdas Alice Electrica SL | D21: =IFERROR(VLOOKUP(C21,'Catálogo Productos'!$B$3:$E$200,2,0),"") -> Guitarra Electrica | E21: =IFERROR(VLOOKUP(C21,'Catálogo Productos'!$B$3:$E$200,3,0),"") -> 1.21 | F21: =IFERROR(VLOOKUP(C21,'Catálogo Productos'!$B$3:$E$200,4,0),"") -> 5.49 | G21: =IF(F21="","",IF(I21="SÍ",F21*'Configuración'!$C$5,0)) -> 0.6039 | H21: SÍ | I21: SÍ | J21: =IF(F21="","",IF(H21="SÍ",'Configuración'!$C$6,0)) -> 1.3 | K21: =IF(F21="","",F21-G21-J21) -> 3.5861 | L21: =IF(F21="","",K21-E21-IF(N21="",0,N21)) -> 2.3761 | M21: =IF(F21="","",IF(K21=0,0,L21/K21)) -> 0.6625861
A22: 18 | B22: 46119 | C22: Cuerdas Alice Electrica L | D22: =IFERROR(VLOOKUP(C22,'Catálogo Productos'!$B$3:$E$200,2,0),"") -> Guitarra Electrica | E22: =IFERROR(VLOOKUP(C22,'Catálogo Productos'!$B$3:$E$200,3,0),"") -> 1.21 | F22: =IFERROR(VLOOKUP(C22,'Catálogo Productos'!$B$3:$E$200,4,0),"") -> 5.49 | G22: =IF(F22="","",IF(I22="SÍ",F22*'Configuración'!$C$5,0)) -> 0 | H22: No | I22: NO | J22: =IF(F22="","",IF(H22="SÍ",'Configuración'!$C$6,0)) -> 0 | K22: =IF(F22="","",F22-G22-J22) -> 5.49 | L22: =IF(F22="","",K22-E22-IF(N22="",0,N22)) -> 3.78 | M22: =IF(F22="","",IF(K22=0,0,L22/K22)) -> 0.68852459 | N22: 0.5
A23: 19 | B23: 46119 | C23: Cuerdas Alice Electrica L | D23: =IFERROR(VLOOKUP(C23,'Catálogo Productos'!$B$3:$E$200,2,0),"") -> Guitarra Electrica | E23: =IFERROR(VLOOKUP(C23,'Catálogo Productos'!$B$3:$E$200,3,0),"") -> 1.21 | F23: =IFERROR(VLOOKUP(C23,'Catálogo Productos'!$B$3:$E$200,4,0),"") -> 5.49 | G23: =IF(F23="","",IF(I23="SÍ",F23*'Configuración'!$C$5,0)) -> 0 | H23: No | I23: NO | J23: =IF(F23="","",IF(H23="SÍ",'Configuración'!$C$6,0)) -> 0 | K23: =IF(F23="","",F23-G23-J23) -> 5.49 | L23: =IF(F23="","",K23-E23-IF(N23="",0,N23)) -> 3.78 | M23: =IF(F23="","",IF(K23=0,0,L23/K23)) -> 0.68852459 | N23: 0.5
A24: 20 | B24: 46119 | C24: Cuerdas Alice Electrica SL | D24: =IFERROR(VLOOKUP(C24,'Catálogo Productos'!$B$3:$E$200,2,0),"") -> Guitarra Electrica | E24: =IFERROR(VLOOKUP(C24,'Catálogo Productos'!$B$3:$E$200,3,0),"") -> 1.21 | F24: =IFERROR(VLOOKUP(C24,'Catálogo Productos'!$B$3:$E$200,4,0),"") -> 5.49 | G24: =IF(F24="","",IF(I24="SÍ",F24*'Configuración'!$C$5,0)) -> 0.6039 | H24: SÍ | I24: SÍ | J24: =IF(F24="","",IF(H24="SÍ",'Configuración'!$C$6,0)) -> 1.3 | K24: =IF(F24="","",F24-G24-J24) -> 3.5861 | L24: =IF(F24="","",K24-E24-IF(N24="",0,N24)) -> 2.3761 | M24: =IF(F24="","",IF(K24=0,0,L24/K24)) -> 0.6625861
A25: 21 | B25: 46119 | C25: Hombrera Violin 3/4 4/4 | D25: =IFERROR(VLOOKUP(C25,'Catálogo Productos'!$B$3:$E$200,2,0),"") -> Violin | E25: =IFERROR(VLOOKUP(C25,'Catálogo Productos'!$B$3:$E$200,3,0),"") -> 2.69 | F25: =IFERROR(VLOOKUP(C25,'Catálogo Productos'!$B$3:$E$200,4,0),"") -> 11 | G25: =IF(F25="","",IF(I25="SÍ",F25*'Configuración'!$C$5,0)) -> 1.21 | H25: SÍ | I25: SÍ | J25: =IF(F25="","",IF(H25="SÍ",'Configuración'!$C$6,0)) -> 1.3 | K25: =IF(F25="","",F25-G25-J25) -> 8.49 | L25: =IF(F25="","",K25-E25-IF(N25="",0,N25)) -> 4.8 | M25: =IF(F25="","",IF(K25=0,0,L25/K25)) -> 0.56537102 | N25: 1
A26: 22 | B26: 46119 | C26: Cuerdas Alice Clasica A106 | D26: =IFERROR(VLOOKUP(C26,'Catálogo Productos'!$B$3:$E$200,2,0),"") -> Guitarra Clasica | E26: =IFERROR(VLOOKUP(C26,'Catálogo Productos'!$B$3:$E$200,3,0),"") -> 1.21 | F26: =IFERROR(VLOOKUP(C26,'Catálogo Productos'!$B$3:$E$200,4,0),"") -> 5.49 | G26: =IF(F26="","",IF(I26="SÍ",F26*'Configuración'!$C$5,0)) -> 0.6039 | H26: SÍ | I26: SÍ | J26: =IF(F26="","",IF(H26="SÍ",'Configuración'!$C$6,0)) -> 1.3 | K26: =IF(F26="","",F26-G26-J26) -> 3.5861 | L26: =IF(F26="","",K26-E26-IF(N26="",0,N26)) -> 2.3761 | M26: =IF(F26="","",IF(K26=0,0,L26/K26)) -> 0.6625861
A27: 23 | B27: 46119 | C27: Hombrera Violin 3/4 4/4 | D27: =IFERROR(VLOOKUP(C27,'Catálogo Productos'!$B$3:$E$200,2,0),"") -> Violin | E27: =IFERROR(VLOOKUP(C27,'Catálogo Productos'!$B$3:$E$200,3,0),"") -> 2.69 | F27: =IFERROR(VLOOKUP(C27,'Catálogo Productos'!$B$3:$E$200,4,0),"") -> 11 | G27: =IF(F27="","",IF(I27="SÍ",F27*'Configuración'!$C$5,0)) -> 1.21 | H27: SÍ | I27: SÍ | J27: =IF(F27="","",IF(H27="SÍ",'Configuración'!$C$6,0)) -> 1.3 | K27: =IF(F27="","",F27-G27-J27) -> 8.49 | L27: =IF(F27="","",K27-E27-IF(N27="",0,N27)) -> 4.8 | M27: =IF(F27="","",IF(K27=0,0,L27/K27)) -> 0.56537102 | N27: 1
A28: 24 | B28: 46119 | C28: Cuerdas Alice Clasica A106 | D28: =IFERROR(VLOOKUP(C28,'Catálogo Productos'!$B$3:$E$200,2,0),"") -> Guitarra Clasica | E28: =IFERROR(VLOOKUP(C28,'Catálogo Productos'!$B$3:$E$200,3,0),"") -> 1.21 | F28: =IFERROR(VLOOKUP(C28,'Catálogo Productos'!$B$3:$E$200,4,0),"") -> 5.49 | G28: =IF(F28="","",IF(I28="SÍ",F28*'Configuración'!$C$5,0)) -> 0.6039 | H28: No | I28: SÍ | J28: =IF(F28="","",IF(H28="SÍ",'Configuración'!$C$6,0)) -> 0 | K28: =IF(F28="","",F28-G28-J28) -> 4.8861 | L28: =IF(F28="","",K28-E28-IF(N28="",0,N28)) -> 3.6761 | M28: =IF(F28="","",IF(K28=0,0,L28/K28)) -> 0.75235873
A29: 25 | B29: 46119 | C29: Baqueta Bateria 5B | D29: =IFERROR(VLOOKUP(C29,'Catálogo Productos'!$B$3:$E$200,2,0),"") -> Bateria | E29: =IFERROR(VLOOKUP(C29,'Catálogo Productos'!$B$3:$E$200,3,0),"") -> 0.71 | F29: =IFERROR(VLOOKUP(C29,'Catálogo Productos'!$B$3:$E$200,4,0),"") -> 5 | G29: =IF(F29="","",IF(I29="SÍ",F29*'Configuración'!$C$5,0)) -> 0.55 | H29: No | I29: SÍ | J29: =IF(F29="","",IF(H29="SÍ",'Configuración'!$C$6,0)) -> 0 | K29: =IF(F29="","",F29-G29-J29) -> 4.45 | L29: =IF(F29="","",K29-E29-IF(N29="",0,N29)) -> 3.74 | M29: =IF(F29="","",IF(K29=0,0,L29/K29)) -> 0.84044944
A30: 26 | B30: 46119 | C30: Cable Hebikuo XA03 | D30: =IFERROR(VLOOKUP(C30,'Catálogo Productos'!$B$3:$E$200,2,0),"") -> Cables | E30: =IFERROR(VLOOKUP(C30,'Catálogo Productos'!$B$3:$E$200,3,0),"") -> 1.91 | F30: =IFERROR(VLOOKUP(C30,'Catálogo Productos'!$B$3:$E$200,4,0),"") -> 10 | G30: =IF(F30="","",IF(I30="SÍ",F30*'Configuración'!$C$5,0)) -> 1.1 | H30: SÍ | I30: SÍ | J30: =IF(F30="","",IF(H30="SÍ",'Configuración'!$C$6,0)) -> 1.3 | K30: =IF(F30="","",F30-G30-J30) -> 7.6 | L30: =IF(F30="","",K30-E30-IF(N30="",0,N30)) -> 5.69 | M30: =IF(F30="","",IF(K30=0,0,L30/K30)) -> 0.74868421
A31: 27 | B31: 46119 | C31: Cuerdas Bajo 4C Alice | D31: =IFERROR(VLOOKUP(C31,'Catálogo Productos'!$B$3:$E$200,2,0),"") -> Bajo Electrico | E31: =IFERROR(VLOOKUP(C31,'Catálogo Productos'!$B$3:$E$200,3,0),"") -> 3.03 | F31: =IFERROR(VLOOKUP(C31,'Catálogo Productos'!$B$3:$E$200,4,0),"") -> 12.99 | G31: =IF(F31="","",IF(I31="SÍ",F31*'Configuración'!$C$5,0)) -> 1.4289 | H31: SÍ | I31: SÍ | J31: =IF(F31="","",IF(H31="SÍ",'Configuración'!$C$6,0)) -> 1.3 | K31: =IF(F31="","",F31-G31-J31) -> 10.2611 | L31: =IF(F31="","",K31-E31-IF(N31="",0,N31)) -> 7.2311 | M31: =IF(F31="","",IF(K31=0,0,L31/K31)) -> 0.70471002
A32: 28 | B32: 46119 | C32: Cuerdas Alice Clasica A106 | D32: =IFERROR(VLOOKUP(C32,'Catálogo Productos'!$B$3:$E$200,2,0),"") -> Guitarra Clasica | E32: =IFERROR(VLOOKUP(C32,'Catálogo Productos'!$B$3:$E$200,3,0),"") -> 1.21 | F32: =IFERROR(VLOOKUP(C32,'Catálogo Productos'!$B$3:$E$200,4,0),"") -> 5.49 | G32: =IF(F32="","",IF(I32="SÍ",F32*'Configuración'!$C$5,0)) -> 0.6039 | H32: SÍ | I32: SÍ | J32: =IF(F32="","",IF(H32="SÍ",'Configuración'!$C$6,0)) -> 1.3 | K32: =IF(F32="","",F32-G32-J32) -> 3.5861 | L32: =IF(F32="","",K32-E32-IF(N32="",0,N32)) -> 2.3761 | M32: =IF(F32="","",IF(K32=0,0,L32/K32)) -> 0.6625861
A33: 29 | B33: 46120 | C33: Cuerdas Alice Electrica SL | D33: =IFERROR(VLOOKUP(C33,'Catálogo Productos'!$B$3:$E$200,2,0),"") -> Guitarra Electrica | E33: =IFERROR(VLOOKUP(C33,'Catálogo Productos'!$B$3:$E$200,3,0),"") -> 1.21 | F33: =IFERROR(VLOOKUP(C33,'Catálogo Productos'!$B$3:$E$200,4,0),"") -> 5.49 | G33: =IF(F33="","",IF(I33="SÍ",F33*'Configuración'!$C$5,0)) -> 0.6039 | H33: SÍ | I33: SÍ | J33: =IF(F33="","",IF(H33="SÍ",'Configuración'!$C$6,0)) -> 1.3 | K33: =IF(F33="","",F33-G33-J33) -> 3.5861 | L33: =IF(F33="","",K33-E33-IF(N33="",0,N33)) -> 2.3761 | M33: =IF(F33="","",IF(K33=0,0,L33/K33)) -> 0.6625861
A34: 30 | B34: 46120 | C34: Cuerdas Alice Electrica SL | D34: =IFERROR(VLOOKUP(C34,'Catálogo Productos'!$B$3:$E$200,2,0),"") -> Guitarra Electrica | E34: =IFERROR(VLOOKUP(C34,'Catálogo Productos'!$B$3:$E$200,3,0),"") -> 1.21 | F34: =IFERROR(VLOOKUP(C34,'Catálogo Productos'!$B$3:$E$200,4,0),"") -> 5.49 | G34: =IF(F34="","",IF(I34="SÍ",F34*'Configuración'!$C$5,0)) -> 0 | H34: No | I34: NO | J34: =IF(F34="","",IF(H34="SÍ",'Configuración'!$C$6,0)) -> 0 | K34: =IF(F34="","",F34-G34-J34) -> 5.49 | L34: =IF(F34="","",K34-E34-IF(N34="",0,N34)) -> 4.28 | M34: =IF(F34="","",IF(K34=0,0,L34/K34)) -> 0.77959927
A35: 31 | B35: 46120 | C35: Cuerdas Alice Electrica L | D35: =IFERROR(VLOOKUP(C35,'Catálogo Productos'!$B$3:$E$200,2,0),"") -> Guitarra Electrica | E35: =IFERROR(VLOOKUP(C35,'Catálogo Productos'!$B$3:$E$200,3,0),"") -> 1.21 | F35: =IFERROR(VLOOKUP(C35,'Catálogo Productos'!$B$3:$E$200,4,0),"") -> 5.49 | G35: =IF(F35="","",IF(I35="SÍ",F35*'Configuración'!$C$5,0)) -> 0.6039 | H35: SÍ | I35: SÍ | J35: =IF(F35="","",IF(H35="SÍ",'Configuración'!$C$6,0)) -> 1.3 | K35: =IF(F35="","",F35-G35-J35) -> 3.5861 | L35: =IF(F35="","",K35-E35-IF(N35="",0,N35)) -> 2.3761 | M35: =IF(F35="","",IF(K35=0,0,L35/K35)) -> 0.6625861
A36: 32 | B36: 46120 | C36: Cuerdas Bajo 4C Alice | D36: =IFERROR(VLOOKUP(C36,'Catálogo Productos'!$B$3:$E$200,2,0),"") -> Bajo Electrico | E36: =IFERROR(VLOOKUP(C36,'Catálogo Productos'!$B$3:$E$200,3,0),"") -> 3.03 | F36: =IFERROR(VLOOKUP(C36,'Catálogo Productos'!$B$3:$E$200,4,0),"") -> 12.99 | G36: =IF(F36="","",IF(I36="SÍ",F36*'Configuración'!$C$5,0)) -> 0 | H36: No | I36: NO | J36: =IF(F36="","",IF(H36="SÍ",'Configuración'!$C$6,0)) -> 0 | K36: =IF(F36="","",F36-G36-J36) -> 12.99 | L36: =IF(F36="","",K36-E36-IF(N36="",0,N36)) -> 9.96 | M36: =IF(F36="","",IF(K36=0,0,L36/K36)) -> 0.76674365
A37: 33 | B37: 46120 | C37: Cuerdas Bajo 4C Alice | D37: =IFERROR(VLOOKUP(C37,'Catálogo Productos'!$B$3:$E$200,2,0),"") -> Bajo Electrico | E37: =IFERROR(VLOOKUP(C37,'Catálogo Productos'!$B$3:$E$200,3,0),"") -> 3.03 | F37: =IFERROR(VLOOKUP(C37,'Catálogo Productos'!$B$3:$E$200,4,0),"") -> 12.99 | G37: =IF(F37="","",IF(I37="SÍ",F37*'Configuración'!$C$5,0)) -> 0 | H37: No | I37: NO | J37: =IF(F37="","",IF(H37="SÍ",'Configuración'!$C$6,0)) -> 0 | K37: =IF(F37="","",F37-G37-J37) -> 12.99 | L37: =IF(F37="","",K37-E37-IF(N37="",0,N37)) -> 9.96 | M37: =IF(F37="","",IF(K37=0,0,L37/K37)) -> 0.76674365
A38: 34 | B38: 46120 | C38: Pines de Correa | D38: =IFERROR(VLOOKUP(C38,'Catálogo Productos'!$B$3:$E$200,2,0),"") -> Guitarra Acustica | E38: =IFERROR(VLOOKUP(C38,'Catálogo Productos'!$B$3:$E$200,3,0),"") -> 0.01 | F38: =IFERROR(VLOOKUP(C38,'Catálogo Productos'!$B$3:$E$200,4,0),"") -> 5 | G38: =IF(F38="","",IF(I38="SÍ",F38*'Configuración'!$C$5,0)) -> 0.55 | H38: SÍ | I38: SÍ | J38: =IF(F38="","",IF(H38="SÍ",'Configuración'!$C$6,0)) -> 1.3 | K38: =IF(F38="","",F38-G38-J38) -> 3.15 | L38: =IF(F38="","",K38-E38-IF(N38="",0,N38)) -> 3.14 | M38: =IF(F38="","",IF(K38=0,0,L38/K38)) -> 0.9968254
A39: 35 | B39: 46120 | C39: Cuerdas Alice Clasica A106 | D39: =IFERROR(VLOOKUP(C39,'Catálogo Productos'!$B$3:$E$200,2,0),"") -> Guitarra Clasica | E39: =IFERROR(VLOOKUP(C39,'Catálogo Productos'!$B$3:$E$200,3,0),"") -> 1.21 | F39: =IFERROR(VLOOKUP(C39,'Catálogo Productos'!$B$3:$E$200,4,0),"") -> 5.49 | G39: =IF(F39="","",IF(I39="SÍ",F39*'Configuración'!$C$5,0)) -> 0.6039 | H39: SÍ | I39: SÍ | J39: =IF(F39="","",IF(H39="SÍ",'Configuración'!$C$6,0)) -> 1.3 | K39: =IF(F39="","",F39-G39-J39) -> 3.5861 | L39: =IF(F39="","",K39-E39-IF(N39="",0,N39)) -> 2.3761 | M39: =IF(F39="","",IF(K39=0,0,L39/K39)) -> 0.6625861
... A41: 37 | B41: 46120 | C41: Cuerdas Alice Clasica A106 | D41: =IFERROR(VLOOKUP(C41,'Catálogo Productos'!$B$3:$E$200,2,0),"") -> Guitarra Clasica | E41: =IFERROR(VLOOKUP(C41,'Catálogo Productos'!$B$3:$E$200,3,0),"") -> 1.21 | F41: =IFERROR(VLOOKUP(C41,'Catálogo Productos'!$B$3:$E$200,4,0),"") -> 5.49 | G41: =IF(F41="","",IF(I41="SÍ",F41*'Configuración'!$C$5,0)) -> 0.6039 | H41: SÍ | I41: SÍ | J41: =IF(F41="","",IF(H41="SÍ",'Configuración'!$C$6,0)) -> 1.3 | K41: =IF(F41="","",F41-G41-J41) -> 3.5861 | L41: =IF(F41="","",K41-E41-IF(N41="",0,N41)) -> 2.3761 | M41: =IF(F41="","",IF(K41=0,0,L41/K41)) -> 0.6625861
A42: 38 | B42: 46120 | C42: Hombrera Violin 3/4 4/4 | D42: =IFERROR(VLOOKUP(C42,'Catálogo Productos'!$B$3:$E$200,2,0),"") -> Violin | E42: =IFERROR(VLOOKUP(C42,'Catálogo Productos'!$B$3:$E$200,3,0),"") -> 2.69 | F42: =IFERROR(VLOOKUP(C42,'Catálogo Productos'!$B$3:$E$200,4,0),"") -> 11 | G42: =IF(F42="","",IF(I42="SÍ",F42*'Configuración'!$C$5,0)) -> 1.21 | H42: SÍ | I42: SÍ | J42: =IF(F42="","",IF(H42="SÍ",'Configuración'!$C$6,0)) -> 1.3 | K42: =IF(F42="","",F42-G42-J42) -> 8.49 | L42: =IF(F42="","",K42-E42-IF(N42="",0,N42)) -> 4.8 | M42: =IF(F42="","",IF(K42=0,0,L42/K42)) -> 0.56537102 | N42: 1
A43: 39 | B43: 46121 | C43: Cuerdas Alice Electrica SL | D43: =IFERROR(VLOOKUP(C43,'Catálogo Productos'!$B$3:$E$200,2,0),"") -> Guitarra Electrica | E43: =IFERROR(VLOOKUP(C43,'Catálogo Productos'!$B$3:$E$200,3,0),"") -> 1.21 | F43: =IFERROR(VLOOKUP(C43,'Catálogo Productos'!$B$3:$E$200,4,0),"") -> 5.49 | G43: =IF(F43="","",IF(I43="SÍ",F43*'Configuración'!$C$5,0)) -> 0.6039 | H43: SÍ | I43: SÍ | J43: =IF(F43="","",IF(H43="SÍ",'Configuración'!$C$6,0)) -> 1.3 | K43: =IF(F43="","",F43-G43-J43) -> 3.5861 | L43: =IF(F43="","",K43-E43-IF(N43="",0,N43)) -> 2.3761 | M43: =IF(F43="","",IF(K43=0,0,L43/K43)) -> 0.6625861
A44: 40 | B44: 46121 | C44: Cuerdas Alice Electrica SL | D44: =IFERROR(VLOOKUP(C44,'Catálogo Productos'!$B$3:$E$200,2,0),"") -> Guitarra Electrica | E44: =IFERROR(VLOOKUP(C44,'Catálogo Productos'!$B$3:$E$200,3,0),"") -> 1.21 | F44: =IFERROR(VLOOKUP(C44,'Catálogo Productos'!$B$3:$E$200,4,0),"") -> 5.49 | G44: =IF(F44="","",IF(I44="SÍ",F44*'Configuración'!$C$5,0)) -> 0.6039 | H44: SÍ | I44: SÍ | J44: =IF(F44="","",IF(H44="SÍ",'Configuración'!$C$6,0)) -> 1.3 | K44: =IF(F44="","",F44-G44-J44) -> 3.5861 | L44: =IF(F44="","",K44-E44-IF(N44="",0,N44)) -> 2.3761 | M44: =IF(F44="","",IF(K44=0,0,L44/K44)) -> 0.6625861
A45: 41 | B45: 46121 | C45: Cuerdas Alice Folk 11-52 | D45: =IFERROR(VLOOKUP(C45,'Catálogo Productos'!$B$3:$E$200,2,0),"") -> Guitarra Acustica | E45: =IFERROR(VLOOKUP(C45,'Catálogo Productos'!$B$3:$E$200,3,0),"") -> 1.21 | F45: =IFERROR(VLOOKUP(C45,'Catálogo Productos'!$B$3:$E$200,4,0),"") -> 5.49 | G45: =IF(F45="","",IF(I45="SÍ",F45*'Configuración'!$C$5,0)) -> 0.6039 | H45: SÍ | I45: SÍ | J45: =IF(F45="","",IF(H45="SÍ",'Configuración'!$C$6,0)) -> 1.3 | K45: =IF(F45="","",F45-G45-J45) -> 3.5861 | L45: =IF(F45="","",K45-E45-IF(N45="",0,N45)) -> 2.3761 | M45: =IF(F45="","",IF(K45=0,0,L45/K45)) -> 0.6625861
A46: 42 | B46: 46121 | C46: Cuerdas Bajo 4C Alice | D46: =IFERROR(VLOOKUP(C46,'Catálogo Productos'!$B$3:$E$200,2,0),"") -> Bajo Electrico | E46: =IFERROR(VLOOKUP(C46,'Catálogo Productos'!$B$3:$E$200,3,0),"") -> 3.03 | F46: =IFERROR(VLOOKUP(C46,'Catálogo Productos'!$B$3:$E$200,4,0),"") -> 12.99 | G46: =IF(F46="","",IF(I46="SÍ",F46*'Configuración'!$C$5,0)) -> 1.4289 | H46: SÍ | I46: SÍ | J46: =IF(F46="","",IF(H46="SÍ",'Configuración'!$C$6,0)) -> 1.3 | K46: =IF(F46="","",F46-G46-J46) -> 10.2611 | L46: =IF(F46="","",K46-E46-IF(N46="",0,N46)) -> 7.2311 | M46: =IF(F46="","",IF(K46=0,0,L46/K46)) -> 0.70471002
A47: 43 | B47: 46123 | C47: Cuerdas Alice Electrica SL | D47: =IFERROR(VLOOKUP(C47,'Catálogo Productos'!$B$3:$E$200,2,0),"") -> Guitarra Electrica | E47: =IFERROR(VLOOKUP(C47,'Catálogo Productos'!$B$3:$E$200,3,0),"") -> 1.21 | F47: =IFERROR(VLOOKUP(C47,'Catálogo Productos'!$B$3:$E$200,4,0),"") -> 5.49 | G47: =IF(F47="","",IF(I47="SÍ",F47*'Configuración'!$C$5,0)) -> 0.6039 | H47: No | I47: SÍ | J47: =IF(F47="","",IF(H47="SÍ",'Configuración'!$C$6,0)) -> 0 | K47: =IF(F47="","",F47-G47-J47) -> 4.8861 | L47: =IF(F47="","",K47-E47-IF(N47="",0,N47)) -> 3.6761 | M47: =IF(F47="","",IF(K47=0,0,L47/K47)) -> 0.75235873
A48: 44 | B48: 46124 | C48: Cuerdas Alice Clasica A106 | D48: =IFERROR(VLOOKUP(C48,'Catálogo Productos'!$B$3:$E$200,2,0),"") -> Guitarra Clasica | E48: =IFERROR(VLOOKUP(C48,'Catálogo Productos'!$B$3:$E$200,3,0),"") -> 1.21 | F48: =IFERROR(VLOOKUP(C48,'Catálogo Productos'!$B$3:$E$200,4,0),"") -> 5.49 | G48: =IF(F48="","",IF(I48="SÍ",F48*'Configuración'!$C$5,0)) -> 0.6039 | H48: SÍ | I48: SÍ | J48: =IF(F48="","",IF(H48="SÍ",'Configuración'!$C$6,0)) -> 1.3 | K48: =IF(F48="","",F48-G48-J48) -> 3.5861 | L48: =IF(F48="","",K48-E48-IF(N48="",0,N48)) -> 2.3761 | M48: =IF(F48="","",IF(K48=0,0,L48/K48)) -> 0.6625861
A49: 45 | B49: 46124 | C49: Cuerdas Alice Clasica A106 | D49: =IFERROR(VLOOKUP(C49,'Catálogo Productos'!$B$3:$E$200,2,0),"") -> Guitarra Clasica | E49: =IFERROR(VLOOKUP(C49,'Catálogo Productos'!$B$3:$E$200,3,0),"") -> 1.21 | F49: =IFERROR(VLOOKUP(C49,'Catálogo Productos'!$B$3:$E$200,4,0),"") -> 5.49 | G49: =IF(F49="","",IF(I49="SÍ",F49*'Configuración'!$C$5,0)) -> 0.6039 | H49: SÍ | I49: SÍ | J49: =IF(F49="","",IF(H49="SÍ",'Configuración'!$C$6,0)) -> 1.3 | K49: =IF(F49="","",F49-G49-J49) -> 3.5861 | L49: =IF(F49="","",K49-E49-IF(N49="",0,N49)) -> 2.3761 | M49: =IF(F49="","",IF(K49=0,0,L49/K49)) -> 0.6625861
A50: 46 | B50: 46124 | C50: Base pared Guitarra/Bajo | D50: =IFERROR(VLOOKUP(C50,'Catálogo Productos'!$B$3:$E$200,2,0),"") -> Bases, Stand, Atriles | E50: =IFERROR(VLOOKUP(C50,'Catálogo Productos'!$B$3:$E$200,3,0),"") -> 0.5 | F50: =IFERROR(VLOOKUP(C50,'Catálogo Productos'!$B$3:$E$200,4,0),"") -> 4.99 | G50: =IF(F50="","",IF(I50="SÍ",F50*'Configuración'!$C$5,0)) -> 0.5489 | H50: SÍ | I50: SÍ | J50: =IF(F50="","",IF(H50="SÍ",'Configuración'!$C$6,0)) -> 1.3 | K50: =IF(F50="","",F50-G50-J50) -> 3.1411 | L50: =IF(F50="","",K50-E50-IF(N50="",0,N50)) -> 2.6411 | M50: =IF(F50="","",IF(K50=0,0,L50/K50)) -> 0.84082009
A51: 47 | B51: 46125 | C51: Base pared Guitarra/Bajo | D51: =IFERROR(VLOOKUP(C51,'Catálogo Productos'!$B$3:$E$200,2,0),"") -> Bases, Stand, Atriles | E51: =IFERROR(VLOOKUP(C51,'Catálogo Productos'!$B$3:$E$200,3,0),"") -> 0.5 | F51: =IFERROR(VLOOKUP(C51,'Catálogo Productos'!$B$3:$E$200,4,0),"") -> 4.99 | G51: =IF(F51="","",IF(I51="SÍ",F51*'Configuración'!$C$5,0)) -> 0.5489 | H51: SÍ | I51: SÍ | J51: =IF(F51="","",IF(H51="SÍ",'Configuración'!$C$6,0)) -> 1.3 | K51: =IF(F51="","",F51-G51-J51) -> 3.1411 | L51: =IF(F51="","",K51-E51-IF(N51="",0,N51)) -> 2.6411 | M51: =IF(F51="","",IF(K51=0,0,L51/K51)) -> 0.84082009
A52: 48 | B52: 46125 | C52: Correa Guitarra/Bajo | D52: =IFERROR(VLOOKUP(C52,'Catálogo Productos'!$B$3:$E$200,2,0),"") -> Correas | E52: =IFERROR(VLOOKUP(C52,'Catálogo Productos'!$B$3:$E$200,3,0),"") -> 0.2 | F52: =IFERROR(VLOOKUP(C52,'Catálogo Productos'!$B$3:$E$200,4,0),"") -> 5.49 | G52: =IF(F52="","",IF(I52="SÍ",F52*'Configuración'!$C$5,0)) -> 0.6039 | H52: SÍ | I52: SÍ | J52: =IF(F52="","",IF(H52="SÍ",'Configuración'!$C$6,0)) -> 1.3 | K52: =IF(F52="","",F52-G52-J52) -> 3.5861 | L52: =IF(F52="","",K52-E52-IF(N52="",0,N52)) -> 3.3861 | M52: =IF(F52="","",IF(K52=0,0,L52/K52)) -> 0.94422911
A53: 49 | B53: 46125 | C53: Clavijas Guitarra Clasica Plateadas | D53: =IFERROR(VLOOKUP(C53,'Catálogo Productos'!$B$3:$E$200,2,0),"") -> Guitarra Clasica | E53: =IFERROR(VLOOKUP(C53,'Catálogo Productos'!$B$3:$E$200,3,0),"") -> 2.5 | F53: =IFERROR(VLOOKUP(C53,'Catálogo Productos'!$B$3:$E$200,4,0),"") - 3 -> 9.99 | G53: =IF(F53="","",IF(I53="SÍ",F53*'Configuración'!$C$5,0)) -> 1.0989 | H53: SÍ | I53: SÍ | J53: =IF(F53="","",IF(H53="SÍ",'Configuración'!$C$6,0)) -> 1.3 | K53: =IF(F53="","",F53-G53-J53) -> 7.5911 | L53: =IF(F53="","",K53-E53-IF(N53="",0,N53)) -> 5.0911 | M53: =IF(F53="","",IF(K53=0,0,L53/K53)) -> 0.67066697
A54: 50 | B54: 46125 | C54: Cable Hebikuo XA03 | D54: =IFERROR(VLOOKUP(C54,'Catálogo Productos'!$B$3:$E$200,2,0),"") -> Cables | E54: =IFERROR(VLOOKUP(C54,'Catálogo Productos'!$B$3:$E$200,3,0),"") -> 1.91 | F54: =IFERROR(VLOOKUP(C54,'Catálogo Productos'!$B$3:$E$200,4,0),"") -> 10 | G54: =IF(F54="","",IF(I54="SÍ",F54*'Configuración'!$C$5,0)) -> 1.1 | H54: SÍ | I54: SÍ | J54: =IF(F54="","",IF(H54="SÍ",'Configuración'!$C$6,0)) -> 1.3 | K54: =IF(F54="","",F54-G54-J54) -> 7.6 | L54: =IF(F54="","",K54-E54-IF(N54="",0,N54)) -> 5.69 | M54: =IF(F54="","",IF(K54=0,0,L54/K54)) -> 0.74868421
A55: 51 | B55: 46125 | C55: Cejilla/Cejuela | D55: =IFERROR(VLOOKUP(C55,'Catálogo Productos'!$B$3:$E$200,2,0),"") -> Guitarra Clasica | E55: =IFERROR(VLOOKUP(C55,'Catálogo Productos'!$B$3:$E$200,3,0),"") -> 0.01 | F55: =IFERROR(VLOOKUP(C55,'Catálogo Productos'!$B$3:$E$200,4,0),"") -> 5 | G55: =IF(F55="","",IF(I55="SÍ",F55*'Configuración'!$C$5,0)) -> 0 | H55: No | I55: NO | J55: =IF(F55="","",IF(H55="SÍ",'Configuración'!$C$6,0)) -> 0 | K55: =IF(F55="","",F55-G55-J55) -> 5 | L55: =IF(F55="","",K55-E55-IF(N55="",0,N55)) -> 4.99 | M55: =IF(F55="","",IF(K55=0,0,L55/K55)) -> 0.998
A56: 52 | B56: 46125 | C56: Base pared Guitarra/Bajo | D56: =IFERROR(VLOOKUP(C56,'Catálogo Productos'!$B$3:$E$200,2,0),"") -> Bases, Stand, Atriles | E56: =IFERROR(VLOOKUP(C56,'Catálogo Productos'!$B$3:$E$200,3,0),"") -> 0.5 | F56: =IFERROR(VLOOKUP(C56,'Catálogo Productos'!$B$3:$E$200,4,0),"") -> 4.99 | G56: =IF(F56="","",IF(I56="SÍ",F56*'Configuración'!$C$5,0)) -> 0.5489 | H56: SÍ | I56: SÍ | J56: =IF(F56="","",IF(H56="SÍ",'Configuración'!$C$6,0)) -> 1.3 | K56: =IF(F56="","",F56-G56-J56) -> 3.1411 | L56: =IF(F56="","",K56-E56-IF(N56="",0,N56)) -> 2.6411 | M56: =IF(F56="","",IF(K56=0,0,L56/K56)) -> 0.84082009
A57: 53 | B57: 46125 | C57: Cuerdas Bajo 4C Alice | D57: =IFERROR(VLOOKUP(C57,'Catálogo Productos'!$B$3:$E$200,2,0),"") -> Bajo Electrico | E57: =IFERROR(VLOOKUP(C57,'Catálogo Productos'!$B$3:$E$200,3,0),"") -> 3.03 | F57: =IFERROR(VLOOKUP(C57,'Catálogo Productos'!$B$3:$E$200,4,0),"") -> 12.99 | G57: =IF(F57="","",IF(I57="SÍ",F57*'Configuración'!$C$5,0)) -> 1.4289 | H57: SÍ | I57: SÍ | J57: =IF(F57="","",IF(H57="SÍ",'Configuración'!$C$6,0)) -> 1.3 | K57: =IF(F57="","",F57-G57-J57) -> 10.2611 | L57: =IF(F57="","",K57-E57-IF(N57="",0,N57)) -> 7.2311 | M57: =IF(F57="","",IF(K57=0,0,L57/K57)) -> 0.70471002
A58: 54 | B58: 46126 | C58: Base pared Guitarra/Bajo | D58: =IFERROR(VLOOKUP(C58,'Catálogo Productos'!$B$3:$E$200,2,0),"") -> Bases, Stand, Atriles | E58: =IFERROR(VLOOKUP(C58,'Catálogo Productos'!$B$3:$E$200,3,0),"") -> 0.5 | F58: =IFERROR(VLOOKUP(C58,'Catálogo Productos'!$B$3:$E$200,4,0),"") -> 4.99 | G58: =IF(F58="","",IF(I58="SÍ",F58*'Configuración'!$C$5,0)) -> 0.5489 | H58: SÍ | I58: SÍ | J58: =IF(F58="","",IF(H58="SÍ",'Configuración'!$C$6,0)) -> 1.3 | K58: =IF(F58="","",F58-G58-J58) -> 3.1411 | L58: =IF(F58="","",K58-E58-IF(N58="",0,N58)) -> 2.6411 | M58: =IF(F58="","",IF(K58=0,0,L58/K58)) -> 0.84082009
A59: 55 | B59: 46126 | C59: Base pared Guitarra/Bajo | D59: =IFERROR(VLOOKUP(C59,'Catálogo Productos'!$B$3:$E$200,2,0),"") -> Bases, Stand, Atriles | E59: =IFERROR(VLOOKUP(C59,'Catálogo Productos'!$B$3:$E$200,3,0),"") -> 0.5 | F59: =IFERROR(VLOOKUP(C59,'Catálogo Productos'!$B$3:$E$200,4,0),"") -> 4.99 | G59: =IF(F59="","",IF(I59="SÍ",F59*'Configuración'!$C$5,0)) -> 0 | H59: No | I59: NO | J59: =IF(F59="","",IF(H59="SÍ",'Configuración'!$C$6,0)) -> 0 | K59: =IF(F59="","",F59-G59-J59) -> 4.99 | L59: =IF(F59="","",K59-E59-IF(N59="",0,N59)) -> 4.49 | M59: =IF(F59="","",IF(K59=0,0,L59/K59)) -> 0.8997996
A60: 56 | B60: 46126 | C60: Capotraste | D60: =IFERROR(VLOOKUP(C60,'Catálogo Productos'!$B$3:$E$200,2,0),"") -> Capostraste | E60: =IFERROR(VLOOKUP(C60,'Catálogo Productos'!$B$3:$E$200,3,0),"") -> 0.65 | F60: =IFERROR(VLOOKUP(C60,'Catálogo Productos'!$B$3:$E$200,4,0),"") -> 6.99 | G60: =IF(F60="","",IF(I60="SÍ",F60*'Configuración'!$C$5,0)) -> 0.7689 | H60: SÍ | I60: SÍ | J60: =IF(F60="","",IF(H60="SÍ",'Configuración'!$C$6,0)) -> 1.3 | K60: =IF(F60="","",F60-G60-J60) -> 4.9211 | L60: =IF(F60="","",K60-E60-IF(N60="",0,N60)) -> 4.2711 | M60: =IF(F60="","",IF(K60=0,0,L60/K60)) -> 0.86791571
A61: 57 | B61: 46126 | C61: Capotraste | D61: =IFERROR(VLOOKUP(C61,'Catálogo Productos'!$B$3:$E$200,2,0),"") -> Capostraste | E61: =IFERROR(VLOOKUP(C61,'Catálogo Productos'!$B$3:$E$200,3,0),"") -> 0.65 | F61: =IFERROR(VLOOKUP(C61,'Catálogo Productos'!$B$3:$E$200,4,0),"") -> 6.99 | G61: =IF(F61="","",IF(I61="SÍ",F61*'Configuración'!$C$5,0)) -> 0 | H61: No | I61: NO | J61: =IF(F61="","",IF(H61="SÍ",'Configuración'!$C$6,0)) -> 0 | K61: =IF(F61="","",F61-G61-J61) -> 6.99 | L61: =IF(F61="","",K61-E61-IF(N61="",0,N61)) -> 6.34 | M61: =IF(F61="","",IF(K61=0,0,L61/K61)) -> 0.90701001
A62: 58 | B62: 46126 | C62: Clavijas Guitarra Clasica Plateadas | D62: =IFERROR(VLOOKUP(C62,'Catálogo Productos'!$B$3:$E$200,2,0),"") -> Guitarra Clasica | E62: =IFERROR(VLOOKUP(C62,'Catálogo Productos'!$B$3:$E$200,3,0),"") -> 2.5 | F62: =IFERROR(VLOOKUP(C62,'Catálogo Productos'!$B$3:$E$200,4,0),"") - 3 -> 9.99 | G62: =IF(F62="","",IF(I62="SÍ",F62*'Configuración'!$C$5,0)) -> 0 | H62: No | I62: NO | J62: =IF(F62="","",IF(H62="SÍ",'Configuración'!$C$6,0)) -> 0 | K62: =IF(F62="","",F62-G62-J62) -> 9.99 | L62: =IF(F62="","",K62-E62-IF(N62="",0,N62)) -> 7.49 | M62: =IF(F62="","",IF(K62=0,0,L62/K62)) -> 0.74974975
A63: 59 | B63: 46126 | C63: Cuerdas Alice Clasica A106 | D63: =IFERROR(VLOOKUP(C63,'Catálogo Productos'!$B$3:$E$200,2,0),"") -> Guitarra Clasica | E63: =IFERROR(VLOOKUP(C63,'Catálogo Productos'!$B$3:$E$200,3,0),"") -> 1.21 | F63: =IFERROR(VLOOKUP(C63,'Catálogo Productos'!$B$3:$E$200,4,0),"") -> 5.49 | G63: =IF(F63="","",IF(I63="SÍ",F63*'Configuración'!$C$5,0)) -> 0.6039 | H63: SÍ | I63: SÍ | J63: =IF(F63="","",IF(H63="SÍ",'Configuración'!$C$6,0)) -> 1.3 | K63: =IF(F63="","",F63-G63-J63) -> 3.5861 | L63: =IF(F63="","",K63-E63-IF(N63="",0,N63)) -> 2.3761 | M63: =IF(F63="","",IF(K63=0,0,L63/K63)) -> 0.6625861
A64: 60 | B64: 46126 | C64: Cejilla/Cejuela | D64: =IFERROR(VLOOKUP(C64,'Catálogo Productos'!$B$3:$E$200,2,0),"") -> Guitarra Clasica | E64: =IFERROR(VLOOKUP(C64,'Catálogo Productos'!$B$3:$E$200,3,0),"") -> 0.01 | F64: =IFERROR(VLOOKUP(C64,'Catálogo Productos'!$B$3:$E$200,4,0),"") -> 5 | G64: =IF(F64="","",IF(I64="SÍ",F64*'Configuración'!$C$5,0)) -> 0.55 | H64: SÍ | I64: SÍ | J64: =IF(F64="","",IF(H64="SÍ",'Configuración'!$C$6,0)) -> 1.3 | K64: =IF(F64="","",F64-G64-J64) -> 3.15 | L64: =IF(F64="","",K64-E64-IF(N64="",0,N64)) -> 3.14 | M64: =IF(F64="","",IF(K64=0,0,L64/K64)) -> 0.9968254
A65: 61 | B65: 46126 | C65: Cuerdas Alice Clasica A106 | D65: =IFERROR(VLOOKUP(C65,'Catálogo Productos'!$B$3:$E$200,2,0),"") -> Guitarra Clasica | E65: =IFERROR(VLOOKUP(C65,'Catálogo Productos'!$B$3:$E$200,3,0),"") -> 1.21 | F65: =IFERROR(VLOOKUP(C65,'Catálogo Productos'!$B$3:$E$200,4,0),"") -> 5.49 | G65: =IF(F65="","",IF(I65="SÍ",F65*'Configuración'!$C$5,0)) -> 0.6039 | H65: SÍ | I65: SÍ | J65: =IF(F65="","",IF(H65="SÍ",'Configuración'!$C$6,0)) -> 1.3 | K65: =IF(F65="","",F65-G65-J65) -> 3.5861 | L65: =IF(F65="","",K65-E65-IF(N65="",0,N65)) -> 2.3761 | M65: =IF(F65="","",IF(K65=0,0,L65/K65)) -> 0.6625861
A66: 62 | B66: 46126 | C66: Clavijas Guitarra Clasica Plateadas | D66: =IFERROR(VLOOKUP(C66,'Catálogo Productos'!$B$3:$E$200,2,0),"") -> Guitarra Clasica | E66: =IFERROR(VLOOKUP(C66,'Catálogo Productos'!$B$3:$E$200,3,0),"") -> 2.5 | F66: =IFERROR(VLOOKUP(C66,'Catálogo Productos'!$B$3:$E$200,4,0),"") -> 12.99 | G66: =IF(F66="","",IF(I66="SÍ",F66*'Configuración'!$C$5,0)) -> 0 | H66: No | I66: NO | J66: =IF(F66="","",IF(H66="SÍ",'Configuración'!$C$6,0)) -> 0 | K66: =IF(F66="","",F66-G66-J66) -> 12.99 | L66: =IF(F66="","",K66-E66-IF(N66="",0,N66)) -> 10.49 | M66: =IF(F66="","",IF(K66=0,0,L66/K66)) -> 0.80754426
A67: 63 | B67: 46127 | C67: Cuerdas Alice Electrica L | D67: =IFERROR(VLOOKUP(C67,'Catálogo Productos'!$B$3:$E$200,2,0),"") -> Guitarra Electrica | E67: =IFERROR(VLOOKUP(C67,'Catálogo Productos'!$B$3:$E$200,3,0),"") -> 1.21 | F67: =IFERROR(VLOOKUP(C67,'Catálogo Productos'!$B$3:$E$200,4,0),"") -> 5.49 | G67: =IF(F67="","",IF(I67="SÍ",F67*'Configuración'!$C$5,0)) -> 0.6039 | H67: No | I67: SÍ | J67: =IF(F67="","",IF(H67="SÍ",'Configuración'!$C$6,0)) -> 0 | K67: =IF(F67="","",F67-G67-J67) -> 4.8861 | L67: =IF(F67="","",K67-E67-IF(N67="",0,N67)) -> 3.6761 | M67: =IF(F67="","",IF(K67=0,0,L67/K67)) -> 0.75235873
A68: 64 | B68: 46128 | C68: Cuerdas Bajo 4C Alice | D68: =IFERROR(VLOOKUP(C68,'Catálogo Productos'!$B$3:$E$200,2,0),"") -> Bajo Electrico | E68: =IFERROR(VLOOKUP(C68,'Catálogo Productos'!$B$3:$E$200,3,0),"") -> 3.03 | F68: =IFERROR(VLOOKUP(C68,'Catálogo Productos'!$B$3:$E$200,4,0),"") -> 12.99 | G68: =IF(F68="","",IF(I68="SÍ",F68*'Configuración'!$C$5,0)) -> 1.4289 | H68: SÍ | I68: SÍ | J68: =IF(F68="","",IF(H68="SÍ",'Configuración'!$C$6,0)) -> 1.3 | K68: =IF(F68="","",F68-G68-J68) -> 10.2611 | L68: =IF(F68="","",K68-E68-IF(N68="",0,N68)) -> 7.2311 | M68: =IF(F68="","",IF(K68=0,0,L68/K68)) -> 0.70471002
A69: 65 | B69: 46128 | C69: Cuerdas Alice Clasica A106 | D69: =IFERROR(VLOOKUP(C69,'Catálogo Productos'!$B$3:$E$200,2,0),"") -> Guitarra Clasica | E69: =IFERROR(VLOOKUP(C69,'Catálogo Productos'!$B$3:$E$200,3,0),"") -> 1.21 | F69: =IFERROR(VLOOKUP(C69,'Catálogo Productos'!$B$3:$E$200,4,0),"") + 14.5 -> 19.99 | G69: =IF(F69="","",IF(I69="SÍ",F69*'Configuración'!$C$5,0)) -> 0 | H69: No | I69: NO | J69: =IF(F69="","",IF(H69="SÍ",'Configuración'!$C$6,0)) -> 0 | K69: =IF(F69="","",F69-G69-J69) -> 19.99 | L69: =IF(F69="","",K69-E69-IF(N69="",0,N69)) -> 18.78 | M69: =IF(F69="","",IF(K69=0,0,L69/K69)) -> 0.93946973
A70: 66 | B70: 46128 | C70: Cuerdas Alice Clasica A106 | D70: =IFERROR(VLOOKUP(C70,'Catálogo Productos'!$B$3:$E$200,2,0),"") -> Guitarra Clasica | E70: =IFERROR(VLOOKUP(C70,'Catálogo Productos'!$B$3:$E$200,3,0),"") -> 1.21 | F70: =IFERROR(VLOOKUP(C70,'Catálogo Productos'!$B$3:$E$200,4,0),"") -> 5.49 | G70: =IF(F70="","",IF(I70="SÍ",F70*'Configuración'!$C$5,0)) -> 0.6039 | H70: SÍ | I70: SÍ | J70: =IF(F70="","",IF(H70="SÍ",'Configuración'!$C$6,0)) -> 1.3 | K70: =IF(F70="","",F70-G70-J70) -> 3.5861 | L70: =IF(F70="","",K70-E70-IF(N70="",0,N70)) -> 2.3761 | M70: =IF(F70="","",IF(K70=0,0,L70/K70)) -> 0.6625861
A71: 67 | B71: 46128 | C71: Cuerdas Bajo 4C Alice | D71: =IFERROR(VLOOKUP(C71,'Catálogo Productos'!$B$3:$E$200,2,0),"") -> Bajo Electrico | E71: =IFERROR(VLOOKUP(C71,'Catálogo Productos'!$B$3:$E$200,3,0),"") -> 3.03 | F71: =IFERROR(VLOOKUP(C71,'Catálogo Productos'!$B$3:$E$200,4,0),"") -> 12.99 | G71: =IF(F71="","",IF(I71="SÍ",F71*'Configuración'!$C$5,0)) -> 1.4289 | H71: SÍ | I71: SÍ | J71: =IF(F71="","",IF(H71="SÍ",'Configuración'!$C$6,0)) -> 1.3 | K71: =IF(F71="","",F71-G71-J71) -> 10.2611 | L71: =IF(F71="","",K71-E71-IF(N71="",0,N71)) -> 7.2311 | M71: =IF(F71="","",IF(K71=0,0,L71/K71)) -> 0.70471002
A72: 68 | B72: 46128 | C72: Cuerdas Alice Clasica A106 | D72: =IFERROR(VLOOKUP(C72,'Catálogo Productos'!$B$3:$E$200,2,0),"") -> Guitarra Clasica | E72: =IFERROR(VLOOKUP(C72,'Catálogo Productos'!$B$3:$E$200,3,0),"") -> 1.21 | F72: =IFERROR(VLOOKUP(C72,'Catálogo Productos'!$B$3:$E$200,4,0),"") -> 5.49 | G72: =IF(F72="","",IF(I72="SÍ",F72*'Configuración'!$C$5,0)) -> 0.6039 | H72: SÍ | I72: SÍ | J72: =IF(F72="","",IF(H72="SÍ",'Configuración'!$C$6,0)) -> 1.3 | K72: =IF(F72="","",F72-G72-J72) -> 3.5861 | L72: =IF(F72="","",K72-E72-IF(N72="",0,N72)) -> 2.3761 | M72: =IF(F72="","",IF(K72=0,0,L72/K72)) -> 0.6625861
A73: 69 | B73: 46130 | C73: Hombrera Violin 3/4 4/4 | D73: =IFERROR(VLOOKUP(C73,'Catálogo Productos'!$B$3:$E$200,2,0),"") -> Violin | E73: =IFERROR(VLOOKUP(C73,'Catálogo Productos'!$B$3:$E$200,3,0),"") -> 2.69 | F73: =IFERROR(VLOOKUP(C73,'Catálogo Productos'!$B$3:$E$200,4,0),"") -> 11 | G73: =IF(F73="","",IF(I73="SÍ",F73*'Configuración'!$C$5,0)) -> 1.21 | H73: SÍ | I73: SÍ | J73: =IF(F73="","",IF(H73="SÍ",'Configuración'!$C$6,0)) -> 1.3 | K73: =IF(F73="","",F73-G73-J73) -> 8.49 | L73: =IF(F73="","",K73-E73-IF(N73="",0,N73)) -> 4.8 | M73: =IF(F73="","",IF(K73=0,0,L73/K73)) -> 0.56537102 | N73: 1
A74: 70 | B74: 46130 | C74: Hombrera Violin 3/4 4/4 | D74: =IFERROR(VLOOKUP(C74,'Catálogo Productos'!$B$3:$E$200,2,0),"") -> Violin | E74: =IFERROR(VLOOKUP(C74,'Catálogo Productos'!$B$3:$E$200,3,0),"") -> 2.69 | F74: =IFERROR(VLOOKUP(C74,'Catálogo Productos'!$B$3:$E$200,4,0),"") -> 11 | G74: =IF(F74="","",IF(I74="SÍ",F74*'Configuración'!$C$5,0)) -> 1.21 | H74: SÍ | I74: SÍ | J74: =IF(F74="","",IF(H74="SÍ",'Configuración'!$C$6,0)) -> 1.3 | K74: =IF(F74="","",F74-G74-J74) -> 8.49 | L74: =IF(F74="","",K74-E74-IF(N74="",0,N74)) -> 4.8 | M74: =IF(F74="","",IF(K74=0,0,L74/K74)) -> 0.56537102 | N74: 1
A75: 71 | B75: 46131 | C75: Cuerdas Alice Clasica A106 | D75: =IFERROR(VLOOKUP(C75,'Catálogo Productos'!$B$3:$E$200,2,0),"") -> Guitarra Clasica | E75: =IFERROR(VLOOKUP(C75,'Catálogo Productos'!$B$3:$E$200,3,0),"") -> 1.21 | F75: =IFERROR(VLOOKUP(C75,'Catálogo Productos'!$B$3:$E$200,4,0),"") -> 5.49 | G75: =IF(F75="","",IF(I75="SÍ",F75*'Configuración'!$C$5,0)) -> 0.6039 | H75: SÍ | I75: SÍ | J75: =IF(F75="","",IF(H75="SÍ",'Configuración'!$C$6,0)) -> 1.3 | K75: =IF(F75="","",F75-G75-J75) -> 3.5861 | L75: =IF(F75="","",K75-E75-IF(N75="",0,N75)) -> 2.3761 | M75: =IF(F75="","",IF(K75=0,0,L75/K75)) -> 0.6625861
A76: 72 | B76: 46131 | C76: Cuerdas Alice Electrica L | D76: =IFERROR(VLOOKUP(C76,'Catálogo Productos'!$B$3:$E$200,2,0),"") -> Guitarra Electrica | E76: =IFERROR(VLOOKUP(C76,'Catálogo Productos'!$B$3:$E$200,3,0),"") -> 1.21 | F76: =IFERROR(VLOOKUP(C76,'Catálogo Productos'!$B$3:$E$200,4,0),"") -> 5.49 | G76: =IF(F76="","",IF(I76="SÍ",F76*'Configuración'!$C$5,0)) -> 0.6039 | H76: SÍ | I76: SÍ | J76: =IF(F76="","",IF(H76="SÍ",'Configuración'!$C$6,0)) -> 1.3 | K76: =IF(F76="","",F76-G76-J76) -> 3.5861 | L76: =IF(F76="","",K76-E76-IF(N76="",0,N76)) -> 2.3761 | M76: =IF(F76="","",IF(K76=0,0,L76/K76)) -> 0.6625861
A77: 73 | B77: 46131 | C77: Cuerdas Alice Electrica SL | D77: =IFERROR(VLOOKUP(C77,'Catálogo Productos'!$B$3:$E$200,2,0),"") -> Guitarra Electrica | E77: =IFERROR(VLOOKUP(C77,'Catálogo Productos'!$B$3:$E$200,3,0),"") -> 1.21 | F77: =IFERROR(VLOOKUP(C77,'Catálogo Productos'!$B$3:$E$200,4,0),"") -> 5.49 | G77: =IF(F77="","",IF(I77="SÍ",F77*'Configuración'!$C$5,0)) -> 0 | H77: No | I77: NO | J77: =IF(F77="","",IF(H77="SÍ",'Configuración'!$C$6,0)) -> 0 | K77: =IF(F77="","",F77-G77-J77) -> 5.49 | L77: =IF(F77="","",K77-E77-IF(N77="",0,N77)) -> 4.28 | M77: =IF(F77="","",IF(K77=0,0,L77/K77)) -> 0.77959927
A78: 74 | B78: 46131 | C78: Cuerdas Alice Folk 11-52 | D78: =IFERROR(VLOOKUP(C78,'Catálogo Productos'!$B$3:$E$200,2,0),"") -> Guitarra Acustica | E78: =IFERROR(VLOOKUP(C78,'Catálogo Productos'!$B$3:$E$200,3,0),"") -> 1.21 | F78: =IFERROR(VLOOKUP(C78,'Catálogo Productos'!$B$3:$E$200,4,0),"") -> 5.49 | G78: =IF(F78="","",IF(I78="SÍ",F78*'Configuración'!$C$5,0)) -> 0 | H78: No | I78: NO | J78: =IF(F78="","",IF(H78="SÍ",'Configuración'!$C$6,0)) -> 0 | K78: =IF(F78="","",F78-G78-J78) -> 5.49 | L78: =IF(F78="","",K78-E78-IF(N78="",0,N78)) -> 4.28 | M78: =IF(F78="","",IF(K78=0,0,L78/K78)) -> 0.77959927
A79: 75 | B79: 46132 | C79: Cable Hebikuo XA03 | D79: =IFERROR(VLOOKUP(C79,'Catálogo Productos'!$B$3:$E$200,2,0),"") -> Cables | E79: =IFERROR(VLOOKUP(C79,'Catálogo Productos'!$B$3:$E$200,3,0),"") -> 1.91 | F79: =IFERROR(VLOOKUP(C79,'Catálogo Productos'!$B$3:$E$200,4,0),"") -> 10 | G79: =IF(F79="","",IF(I79="SÍ",F79*'Configuración'!$C$5,0)) -> 1.1 | H79: No | I79: SÍ | J79: =IF(F79="","",IF(H79="SÍ",'Configuración'!$C$6,0)) -> 0 | K79: =IF(F79="","",F79-G79-J79) -> 8.9 | L79: =IF(F79="","",K79-E79-IF(N79="",0,N79)) -> 6.99 | M79: =IF(F79="","",IF(K79=0,0,L79/K79)) -> 0.78539326
A80: 76 | B80: 46132 | C80: Cuerdas de Violin 4/4 | D80: =IFERROR(VLOOKUP(C80,'Catálogo Productos'!$B$3:$E$200,2,0),"") -> Violin | E80: =IFERROR(VLOOKUP(C80,'Catálogo Productos'!$B$3:$E$200,3,0),"") -> 1.06 | F80: =IFERROR(VLOOKUP(C80,'Catálogo Productos'!$B$3:$E$200,4,0),"") -> 4.99 | G80: =IF(F80="","",IF(I80="SÍ",F80*'Configuración'!$C$5,0)) -> 0.5489 | H80: SÍ | I80: SÍ | J80: =IF(F80="","",IF(H80="SÍ",'Configuración'!$C$6,0)) -> 1.3 | K80: =IF(F80="","",F80-G80-J80) -> 3.1411 | L80: =IF(F80="","",K80-E80-IF(N80="",0,N80)) -> 2.0811 | M80: =IF(F80="","",IF(K80=0,0,L80/K80)) -> 0.6625386
A81: 77 | B81: 46132 | C81: Cable Hebikuo XA03 | D81: =IFERROR(VLOOKUP(C81,'Catálogo Productos'!$B$3:$E$200,2,0),"") -> Cables | E81: =IFERROR(VLOOKUP(C81,'Catálogo Productos'!$B$3:$E$200,3,0),"") -> 1.91 | F81: =IFERROR(VLOOKUP(C81,'Catálogo Productos'!$B$3:$E$200,4,0),"") -> 10 | G81: =IF(F81="","",IF(I81="SÍ",F81*'Configuración'!$C$5,0)) -> 1.1 | H81: No | I81: SÍ | J81: =IF(F81="","",IF(H81="SÍ",'Configuración'!$C$6,0)) -> 0 | K81: =IF(F81="","",F81-G81-J81) -> 8.9 | L81: =IF(F81="","",K81-E81-IF(N81="",0,N81)) -> 6.99 | M81: =IF(F81="","",IF(K81=0,0,L81/K81)) -> 0.78539326
A82: 78 | B82: 46132 | C82: Clavijas Guitarra Clasica Doradas | D82: =IFERROR(VLOOKUP(C82,'Catálogo Productos'!$B$3:$E$200,2,0),"") -> Guitarra Clasica | E82: =IFERROR(VLOOKUP(C82,'Catálogo Productos'!$B$3:$E$200,3,0),"") -> 2.5 | F82: =IFERROR(VLOOKUP(C82,'Catálogo Productos'!$B$3:$E$200,4,0),"") -> 9.99 | G82: =IF(F82="","",IF(I82="SÍ",F82*'Configuración'!$C$5,0)) -> 1.0989 | H82: No | I82: SÍ | J82: =IF(F82="","",IF(H82="SÍ",'Configuración'!$C$6,0)) -> 0 | K82: =IF(F82="","",F82-G82-J82) -> 8.8911 | L82: =IF(F82="","",K82-E82-IF(N82="",0,N82)) -> 6.3911 | M82: =IF(F82="","",IF(K82=0,0,L82/K82)) -> 0.71881994
A83: 79 | B83: 46132 | C83: Hombrera Violin 3/4 4/4 | D83: =IFERROR(VLOOKUP(C83,'Catálogo Productos'!$B$3:$E$200,2,0),"") -> Violin | E83: =IFERROR(VLOOKUP(C83,'Catálogo Productos'!$B$3:$E$200,3,0),"") -> 2.69 | F83: =IFERROR(VLOOKUP(C83,'Catálogo Productos'!$B$3:$E$200,4,0),"") -> 11 | G83: =IF(F83="","",IF(I83="SÍ",F83*'Configuración'!$C$5,0)) -> 1.21 | H83: SÍ | I83: SÍ | J83: =IF(F83="","",IF(H83="SÍ",'Configuración'!$C$6,0)) -> 1.3 | K83: =IF(F83="","",F83-G83-J83) -> 8.49 | L83: =IF(F83="","",K83-E83-IF(N83="",0,N83)) -> 4.8 | M83: =IF(F83="","",IF(K83=0,0,L83/K83)) -> 0.56537102 | N83: 1
A84: 80 | B84: 46132 | C84: Cuerdas Alice Electrica L | D84: =IFERROR(VLOOKUP(C84,'Catálogo Productos'!$B$3:$E$200,2,0),"") -> Guitarra Electrica | E84: =IFERROR(VLOOKUP(C84,'Catálogo Productos'!$B$3:$E$200,3,0),"") -> 1.21 | F84: =IFERROR(VLOOKUP(C84,'Catálogo Productos'!$B$3:$E$200,4,0),"") -> 5.49 | G84: =IF(F84="","",IF(I84="SÍ",F84*'Configuración'!$C$5,0)) -> 0.6039 | H84: SÍ | I84: SÍ | J84: =IF(F84="","",IF(H84="SÍ",'Configuración'!$C$6,0)) -> 1.3 | K84: =IF(F84="","",F84-G84-J84) -> 3.5861 | L84: =IF(F84="","",K84-E84-IF(N84="",0,N84)) -> 2.3761 | M84: =IF(F84="","",IF(K84=0,0,L84/K84)) -> 0.6625861
A85: 81 | B85: 46132 | C85: Hombrera Violin 3/4 4/4 | D85: =IFERROR(VLOOKUP(C85,'Catálogo Productos'!$B$3:$E$200,2,0),"") -> Violin | E85: =IFERROR(VLOOKUP(C85,'Catálogo Productos'!$B$3:$E$200,3,0),"") -> 2.69 | F85: =IFERROR(VLOOKUP(C85,'Catálogo Productos'!$B$3:$E$200,4,0),"") -> 11 | G85: =IF(F85="","",IF(I85="SÍ",F85*'Configuración'!$C$5,0)) -> 1.21 | H85: SÍ | I85: SÍ | J85: =IF(F85="","",IF(H85="SÍ",'Configuración'!$C$6,0)) -> 1.3 | K85: =IF(F85="","",F85-G85-J85) -> 8.49 | L85: =IF(F85="","",K85-E85-IF(N85="",0,N85)) -> 4.8 | M85: =IF(F85="","",IF(K85=0,0,L85/K85)) -> 0.56537102 | N85: 1
A86: 82 | B86: 46132 | C86: Clavijas Guitarra Clasica Plateadas | D86: =IFERROR(VLOOKUP(C86,'Catálogo Productos'!$B$3:$E$200,2,0),"") -> Guitarra Clasica | E86: =IFERROR(VLOOKUP(C86,'Catálogo Productos'!$B$3:$E$200,3,0),"") -> 2.5 | F86: =IFERROR(VLOOKUP(C86,'Catálogo Productos'!$B$3:$E$200,4,0),"") -> 12.99 | G86: =IF(F86="","",IF(I86="SÍ",F86*'Configuración'!$C$5,0)) -> 1.4289 | H86: SÍ | I86: SÍ | J86: =IF(F86="","",IF(H86="SÍ",'Configuración'!$C$6,0)) -> 1.3 | K86: =IF(F86="","",F86-G86-J86) -> 10.2611 | L86: =IF(F86="","",K86-E86-IF(N86="",0,N86)) -> 7.7611 | M86: =IF(F86="","",IF(K86=0,0,L86/K86)) -> 0.7563614
A87: 83 | B87: 46132 | C87: Cuerdas Alice Electrica SL | D87: =IFERROR(VLOOKUP(C87,'Catálogo Productos'!$B$3:$E$200,2,0),"") -> Guitarra Electrica | E87: =IFERROR(VLOOKUP(C87,'Catálogo Productos'!$B$3:$E$200,3,0),"") -> 1.21 | F87: =IFERROR(VLOOKUP(C87,'Catálogo Productos'!$B$3:$E$200,4,0),"") -> 5.49 | G87: =IF(F87="","",IF(I87="SÍ",F87*'Configuración'!$C$5,0)) -> 0 | H87: No | I87: NO | J87: =IF(F87="","",IF(H87="SÍ",'Configuración'!$C$6,0)) -> 0 | K87: =IF(F87="","",F87-G87-J87) -> 5.49 | L87: =IF(F87="","",K87-E87-IF(N87="",0,N87)) -> 4.28 | M87: =IF(F87="","",IF(K87=0,0,L87/K87)) -> 0.77959927
A88: 84 | B88: 46132 | C88: Cuerdas Alice Clasica A106 | D88: =IFERROR(VLOOKUP(C88,'Catálogo Productos'!$B$3:$E$200,2,0),"") -> Guitarra Clasica | E88: =IFERROR(VLOOKUP(C88,'Catálogo Productos'!$B$3:$E$200,3,0),"") -> 1.21 | F88: =IFERROR(VLOOKUP(C88,'Catálogo Productos'!$B$3:$E$200,4,0),"") -> 5.49 | G88: =IF(F88="","",IF(I88="SÍ",F88*'Configuración'!$C$5,0)) -> 0.6039 | H88: SÍ | I88: SÍ | J88: =IF(F88="","",IF(H88="SÍ",'Configuración'!$C$6,0)) -> 1.3 | K88: =IF(F88="","",F88-G88-J88) -> 3.5861 | L88: =IF(F88="","",K88-E88-IF(N88="",0,N88)) -> 2.3761 | M88: =IF(F88="","",IF(K88=0,0,L88/K88)) -> 0.6625861
A89: 85 | B89: 46132 | C89: Pines de Correa | D89: =IFERROR(VLOOKUP(C89,'Catálogo Productos'!$B$3:$E$200,2,0),"") -> Guitarra Acustica | E89: =IFERROR(VLOOKUP(C89,'Catálogo Productos'!$B$3:$E$200,3,0),"") -> 0.01 | F89: =IFERROR(VLOOKUP(C89,'Catálogo Productos'!$B$3:$E$200,4,0),"") -> 5 | G89: =IF(F89="","",IF(I89="SÍ",F89*'Configuración'!$C$5,0)) -> 0.55 | H89: SÍ | I89: SÍ | J89: =IF(F89="","",IF(H89="SÍ",'Configuración'!$C$6,0)) -> 1.3 | K89: =IF(F89="","",F89-G89-J89) -> 3.15 | L89: =IF(F89="","",K89-E89-IF(N89="",0,N89)) -> 3.14 | M89: =IF(F89="","",IF(K89=0,0,L89/K89)) -> 0.9968254
A90: 86 | B90: 46133 | C90: Cuerdas Alice Clasica A106 | D90: =IFERROR(VLOOKUP(C90,'Catálogo Productos'!$B$3:$E$200,2,0),"") -> Guitarra Clasica | E90: =IFERROR(VLOOKUP(C90,'Catálogo Productos'!$B$3:$E$200,3,0),"") -> 1.21 | F90: =IFERROR(VLOOKUP(C90,'Catálogo Productos'!$B$3:$E$200,4,0),"") -> 5.49 | G90: =IF(F90="","",IF(I90="SÍ",F90*'Configuración'!$C$5,0)) -> 0.6039 | H90: SÍ | I90: SÍ | J90: =IF(F90="","",IF(H90="SÍ",'Configuración'!$C$6,0)) -> 1.3 | K90: =IF(F90="","",F90-G90-J90) -> 3.5861 | L90: =IF(F90="","",K90-E90-IF(N90="",0,N90)) -> 2.3761 | M90: =IF(F90="","",IF(K90=0,0,L90/K90)) -> 0.6625861
A91: 87 | B91: 46133 | C91: Cuerdas Alice Electrica SL | D91: =IFERROR(VLOOKUP(C91,'Catálogo Productos'!$B$3:$E$200,2,0),"") -> Guitarra Electrica | E91: =IFERROR(VLOOKUP(C91,'Catálogo Productos'!$B$3:$E$200,3,0),"") -> 1.21 | F91: =IFERROR(VLOOKUP(C91,'Catálogo Productos'!$B$3:$E$200,4,0),"") -> 5.49 | G91: =IF(F91="","",IF(I91="SÍ",F91*'Configuración'!$C$5,0)) -> 0.6039 | H91: No | I91: SÍ | J91: =IF(F91="","",IF(H91="SÍ",'Configuración'!$C$6,0)) -> 0 | K91: =IF(F91="","",F91-G91-J91) -> 4.8861 | L91: =IF(F91="","",K91-E91-IF(N91="",0,N91)) -> 3.6761 | M91: =IF(F91="","",IF(K91=0,0,L91/K91)) -> 0.75235873
A92: 88 | B92: 46133 | C92: Base pared Guitarra/Bajo | D92: =IFERROR(VLOOKUP(C92,'Catálogo Productos'!$B$3:$E$200,2,0),"") -> Bases, Stand, Atriles | E92: =IFERROR(VLOOKUP(C92,'Catálogo Productos'!$B$3:$E$200,3,0),"") -> 0.5 | F92: =IFERROR(VLOOKUP(C92,'Catálogo Productos'!$B$3:$E$200,4,0),"") -> 4.99 | G92: =IF(F92="","",IF(I92="SÍ",F92*'Configuración'!$C$5,0)) -> 0.5489 | H92: SÍ | I92: SÍ | J92: =IF(F92="","",IF(H92="SÍ",'Configuración'!$C$6,0)) -> 1.3 | K92: =IF(F92="","",F92-G92-J92) -> 3.1411 | L92: =IF(F92="","",K92-E92-IF(N92="",0,N92)) -> 2.6411 | M92: =IF(F92="","",IF(K92=0,0,L92/K92)) -> 0.84082009
A93: 89 | B93: 46133 | C93: Base pared Guitarra/Bajo | D93: =IFERROR(VLOOKUP(C93,'Catálogo Productos'!$B$3:$E$200,2,0),"") -> Bases, Stand, Atriles | E93: =IFERROR(VLOOKUP(C93,'Catálogo Productos'!$B$3:$E$200,3,0),"") -> 0.5 | F93: =IFERROR(VLOOKUP(C93,'Catálogo Productos'!$B$3:$E$200,4,0),"") -> 4.99 | G93: =IF(F93="","",IF(I93="SÍ",F93*'Configuración'!$C$5,0)) -> 0.5489 | H93: No | I93: SÍ | J93: =IF(F93="","",IF(H93="SÍ",'Configuración'!$C$6,0)) -> 0 | K93: =IF(F93="","",F93-G93-J93) -> 4.4411 | L93: =IF(F93="","",K93-E93-IF(N93="",0,N93)) -> 3.9411 | M93: =IF(F93="","",IF(K93=0,0,L93/K93)) -> 0.88741528
A94: 90 | B94: 46133 | C94: Cuerdas Alice Electrica L | D94: =IFERROR(VLOOKUP(C94,'Catálogo Productos'!$B$3:$E$200,2,0),"") -> Guitarra Electrica | E94: =IFERROR(VLOOKUP(C94,'Catálogo Productos'!$B$3:$E$200,3,0),"") -> 1.21 | F94: =IFERROR(VLOOKUP(C94,'Catálogo Productos'!$B$3:$E$200,4,0),"") +34.5 -> 39.99 | G94: =IF(F94="","",IF(I94="SÍ",F94*'Configuración'!$C$5,0)) -> 0 | H94: No | I94: NO | J94: =IF(F94="","",IF(H94="SÍ",'Configuración'!$C$6,0)) -> 0 | K94: =IF(F94="","",F94-G94-J94) -> 39.99 | L94: =IF(F94="","",K94-E94-IF(N94="",0,N94)) -> 38.78 | M94: =IF(F94="","",IF(K94=0,0,L94/K94)) -> 0.96974244
A95: 91 | B95: 46133 | C95: Cuerdas Alice Clasica A106 | D95: =IFERROR(VLOOKUP(C95,'Catálogo Productos'!$B$3:$E$200,2,0),"") -> Guitarra Clasica | E95: =IFERROR(VLOOKUP(C95,'Catálogo Productos'!$B$3:$E$200,3,0),"") -> 1.21 | F95: =IFERROR(VLOOKUP(C95,'Catálogo Productos'!$B$3:$E$200,4,0),"") -> 5.49 | G95: =IF(F95="","",IF(I95="SÍ",F95*'Configuración'!$C$5,0)) -> 0.6039 | H95: SÍ | I95: SÍ | J95: =IF(F95="","",IF(H95="SÍ",'Configuración'!$C$6,0)) -> 1.3 | K95: =IF(F95="","",F95-G95-J95) -> 3.5861 | L95: =IF(F95="","",K95-E95-IF(N95="",0,N95)) -> 2.3761 | M95: =IF(F95="","",IF(K95=0,0,L95/K95)) -> 0.6625861
A96: 92 | B96: 46133 | C96: Clavijas Guitarra Clasica Doradas | D96: =IFERROR(VLOOKUP(C96,'Catálogo Productos'!$B$3:$E$200,2,0),"") -> Guitarra Clasica | E96: =IFERROR(VLOOKUP(C96,'Catálogo Productos'!$B$3:$E$200,3,0),"") -> 2.5 | F96: =IFERROR(VLOOKUP(C96,'Catálogo Productos'!$B$3:$E$200,4,0),"") -> 9.99 | G96: =IF(F96="","",IF(I96="SÍ",F96*'Configuración'!$C$5,0)) -> 1.0989 | H96: SÍ | I96: SÍ | J96: =IF(F96="","",IF(H96="SÍ",'Configuración'!$C$6,0)) -> 1.3 | K96: =IF(F96="","",F96-G96-J96) -> 7.5911 | L96: =IF(F96="","",K96-E96-IF(N96="",0,N96)) -> 5.0911 | M96: =IF(F96="","",IF(K96=0,0,L96/K96)) -> 0.67066697
A97: 93 | B97: 46133 | C97: Cable Hebikuo XA03 | D97: =IFERROR(VLOOKUP(C97,'Catálogo Productos'!$B$3:$E$200,2,0),"") -> Cables | E97: =IFERROR(VLOOKUP(C97,'Catálogo Productos'!$B$3:$E$200,3,0),"") -> 1.91 | F97: =IFERROR(VLOOKUP(C97,'Catálogo Productos'!$B$3:$E$200,4,0),"") -> 10 | G97: =IF(F97="","",IF(I97="SÍ",F97*'Configuración'!$C$5,0)) -> 1.1 | H97: SÍ | I97: SÍ | J97: =IF(F97="","",IF(H97="SÍ",'Configuración'!$C$6,0)) -> 1.3 | K97: =IF(F97="","",F97-G97-J97) -> 7.6 | L97: =IF(F97="","",K97-E97-IF(N97="",0,N97)) -> 5.69 | M97: =IF(F97="","",IF(K97=0,0,L97/K97)) -> 0.74868421
A98: 94 | B98: 46133 | C98: Pines de Correa | D98: =IFERROR(VLOOKUP(C98,'Catálogo Productos'!$B$3:$E$200,2,0),"") -> Guitarra Acustica | E98: =IFERROR(VLOOKUP(C98,'Catálogo Productos'!$B$3:$E$200,3,0),"") -> 0.01 | F98: =IFERROR(VLOOKUP(C98,'Catálogo Productos'!$B$3:$E$200,4,0),"") -> 5 | G98: =IF(F98="","",IF(I98="SÍ",F98*'Configuración'!$C$5,0)) -> 0.55 | H98: SÍ | I98: SÍ | J98: =IF(F98="","",IF(H98="SÍ",'Configuración'!$C$6,0)) -> 1.3 | K98: =IF(F98="","",F98-G98-J98) -> 3.15 | L98: =IF(F98="","",K98-E98-IF(N98="",0,N98)) -> 3.14 | M98: =IF(F98="","",IF(K98=0,0,L98/K98)) -> 0.9968254
A99: 95 | B99: 46134 | C99: Cable Hebikuo XA03 | D99: =IFERROR(VLOOKUP(C99,'Catálogo Productos'!$B$3:$E$200,2,0),"") -> Cables | E99: =IFERROR(VLOOKUP(C99,'Catálogo Productos'!$B$3:$E$200,3,0),"") -> 1.91 | F99: =IFERROR(VLOOKUP(C99,'Catálogo Productos'!$B$3:$E$200,4,0),"") -> 10 | G99: =IF(F99="","",IF(I99="SÍ",F99*'Configuración'!$C$5,0)) -> 1.1 | H99: SÍ | I99: SÍ | J99: =IF(F99="","",IF(H99="SÍ",'Configuración'!$C$6,0)) -> 1.3 | K99: =IF(F99="","",F99-G99-J99) -> 7.6 | L99: =IF(F99="","",K99-E99-IF(N99="",0,N99)) -> 5.69 | M99: =IF(F99="","",IF(K99=0,0,L99/K99)) -> 0.74868421
A100: 96 | B100: 46134 | C100: Base pared Guitarra/Bajo | D100: =IFERROR(VLOOKUP(C100,'Catálogo Productos'!$B$3:$E$200,2,0),"") -> Bases, Stand, Atriles | E100: =IFERROR(VLOOKUP(C100,'Catálogo Productos'!$B$3:$E$200,3,0),"") -> 0.5 | F100: =IFERROR(VLOOKUP(C100,'Catálogo Productos'!$B$3:$E$200,4,0),"") -> 4.99 | G100: =IF(F100="","",IF(I100="SÍ",F100*'Configuración'!$C$5,0)) -> 0.5489 | H100: SÍ | I100: SÍ | J100: =IF(F100="","",IF(H100="SÍ",'Configuración'!$C$6,0)) -> 1.3 | K100: =IF(F100="","",F100-G100-J100) -> 3.1411 | L100: =IF(F100="","",K100-E100-IF(N100="",0,N100)) -> 2.6411 | M100: =IF(F100="","",IF(K100=0,0,L100/K100)) -> 0.84082009
A101: 97 | B101: 46134 | C101: Base pared Guitarra/Bajo | D101: =IFERROR(VLOOKUP(C101,'Catálogo Productos'!$B$3:$E$200,2,0),"") -> Bases, Stand, Atriles | E101: =IFERROR(VLOOKUP(C101,'Catálogo Productos'!$B$3:$E$200,3,0),"") -> 0.5 | F101: =IFERROR(VLOOKUP(C101,'Catálogo Productos'!$B$3:$E$200,4,0),"") -> 4.99 | G101: =IF(F101="","",IF(I101="SÍ",F101*'Configuración'!$C$5,0)) -> 0.5489 | H101: No | I101: SÍ | J101: =IF(F101="","",IF(H101="SÍ",'Configuración'!$C$6,0)) -> 0 | K101: =IF(F101="","",F101-G101-J101) -> 4.4411 | L101: =IF(F101="","",K101-E101-IF(N101="",0,N101)) -> 3.9411 | M101: =IF(F101="","",IF(K101=0,0,L101/K101)) -> 0.88741528
A102: 98 | B102: 46134 | C102: Cuerdas Alice Electrica L | D102: =IFERROR(VLOOKUP(C102,'Catálogo Productos'!$B$3:$E$200,2,0),"") -> Guitarra Electrica | E102: =IFERROR(VLOOKUP(C102,'Catálogo Productos'!$B$3:$E$200,3,0),"") -> 1.21 | F102: =IFERROR(VLOOKUP(C102,'Catálogo Productos'!$B$3:$E$200,4,0),"") -> 5.49 | G102: =IF(F102="","",IF(I102="SÍ",F102*'Configuración'!$C$5,0)) -> 0 | H102: No | I102: NO | J102: =IF(F102="","",IF(H102="SÍ",'Configuración'!$C$6,0)) -> 0 | K102: =IF(F102="","",F102-G102-J102) -> 5.49 | L102: =IF(F102="","",K102-E102-IF(N102="",0,N102)) -> 4.28 | M102: =IF(F102="","",IF(K102=0,0,L102/K102)) -> 0.77959927
A103: 100 | B103: 46134 | C103: Base pared Guitarra/Bajo | D103: =IFERROR(VLOOKUP(C103,'Catálogo Productos'!$B$3:$E$200,2,0),"") -> Bases, Stand, Atriles | E103: =IFERROR(VLOOKUP(C103,'Catálogo Productos'!$B$3:$E$200,3,0),"") -> 0.5 | F103: =IFERROR(VLOOKUP(C103,'Catálogo Productos'!$B$3:$E$200,4,0),"") -> 4.99 | G103: =IF(F103="","",IF(I103="SÍ",F103*'Configuración'!$C$5,0)) -> 0.5489 | H103: SÍ | I103: SÍ | J103: =IF(F103="","",IF(H103="SÍ",'Configuración'!$C$6,0)) -> 1.3 | K103: =IF(F103="","",F103-G103-J103) -> 3.1411 | L103: =IF(F103="","",K103-E103-IF(N103="",0,N103)) -> 2.6411 | M103: =IF(F103="","",IF(K103=0,0,L103/K103)) -> 0.84082009
A104: 101 | B104: 46134 | C104: Base pared Guitarra/Bajo | D104: =IFERROR(VLOOKUP(C104,'Catálogo Productos'!$B$3:$E$200,2,0),"") -> Bases, Stand, Atriles | E104: =IFERROR(VLOOKUP(C104,'Catálogo Productos'!$B$3:$E$200,3,0),"") -> 0.5 | F104: =IFERROR(VLOOKUP(C104,'Catálogo Productos'!$B$3:$E$200,4,0),"") -> 4.99 | G104: =IF(F104="","",IF(I104="SÍ",F104*'Configuración'!$C$5,0)) -> 0 | H104: No | I104: NO | J104: =IF(F104="","",IF(H104="SÍ",'Configuración'!$C$6,0)) -> 0 | K104: =IF(F104="","",F104-G104-J104) -> 4.99 | L104: =IF(F104="","",K104-E104-IF(N104="",0,N104)) -> 4.49 | M104: =IF(F104="","",IF(K104=0,0,L104/K104)) -> 0.8997996
A105: 102 | B105: 46134 | C105: Base pared Guitarra/Bajo | D105: =IFERROR(VLOOKUP(C105,'Catálogo Productos'!$B$3:$E$200,2,0),"") -> Bases, Stand, Atriles | E105: =IFERROR(VLOOKUP(C105,'Catálogo Productos'!$B$3:$E$200,3,0),"") -> 0.5 | F105: =IFERROR(VLOOKUP(C105,'Catálogo Productos'!$B$3:$E$200,4,0),"") -> 4.99 | G105: =IF(F105="","",IF(I105="SÍ",F105*'Configuración'!$C$5,0)) -> 0 | H105: No | I105: NO | J105: =IF(F105="","",IF(H105="SÍ",'Configuración'!$C$6,0)) -> 0 | K105: =IF(F105="","",F105-G105-J105) -> 4.99 | L105: =IF(F105="","",K105-E105-IF(N105="",0,N105)) -> 4.49 | M105: =IF(F105="","",IF(K105=0,0,L105/K105)) -> 0.8997996
...

Sheet Abril 2026 - Resumen
A1: Cuerdas Bajo 4C Alice
A2: ='Configuración'!C20&" "&'Configuración'!C21 -> Abril 2026
A4: RESUMEN DE INGRESOS
B6: Ventas Totales (USD) | C6: ='Abril 2026 - Ventas'!F158 -> 1120.87
B7: (-) Comisiones MercadoLibre | C7: ='Abril 2026 - Ventas'!G158 -> 101.3738
B8: (-) Costos de Envío | C8: ='Abril 2026 - Ventas'!J158 -> 136.5
B9: Ingreso Neto (lo que recibes) | C9: ='Abril 2026 - Ventas'!K158 -> 882.9962
B10: (-) Costo Total de Mercancía | C10: ='Abril 2026 - Ventas'!E158 -> 206.65
B11: GANANCIA BRUTA | C11: ='Abril 2026 - Ventas'!L158 -> 666.3462
A13: ANÁLISIS DE GANANCIA
B15: Ingreso Neto (USD) | C15: =C9 -> 882.9962 | E15: Lo que recibes después de comisiones y envíos
B16: Ganancia Bruta (USD) | C16: =C11 -> 666.3462 | E16: Ventas netas menos costo de mercancía
B17: (-) Costo de Mercancía (USD) | C17: =C10 -> 206.65
B18: GANANCIA NETA (USD) | C18: =C15-C10 -> 676.3462
A21: DISTRIBUCIÓN DE GANANCIA REAL
B23: Ganancia Neta del Mes | C23: =C18 -> 676.3462
B24: → Para Reinversión | C24: =IF(C23>0,C23*'Configuración'!$C$14,0) -> 473.44234 | D24: ='Configuración'!$C$14 -> 0.7 | E24: Para comprar más inventario
B25: → Tu Sueldo / Ganancia Personal | C25: =IF(C23>0,C23*'Configuración'!$C$15,0) -> 202.90386 | D25: ='Configuración'!$C$15 -> 0.3 | E25: Disponible para ti o para decisiones
A27: INDICADORES CLAVE (KPIs)
B29: Total de ventas del mes | C29: ='Abril 2026 - Ventas'!C160 -> 155 | E29: Cantidad de transacciones
B30: Ticket promedio (USD) | C30: =IF(C29>0,C6/C29,0) -> 7.2314194 | E30: Venta promedio por transacción
B31: Ganancia neta promedio por venta | C31: =IF(C29>0,C18/C29,0) -> 4.3635239 | E31: Cuánto ganas en promedio por venta
B32: Margen neto real (%) | C32: =IF(C9=0,0,C18/C9) -> 0.76596728 | E32: % ganancia real sobre ingreso neto
B33: Total pagado a ML (comisiones + envíos) | C33: ='Abril 2026 - Ventas'!G158+'Febrero 2026 - Ventas'!J55 -> #REF! | E33: Lo que le pagas a MercadoLibre
B34: ROI del mes (%) | C34: =IF(C10=0,0,C18/C10) -> 3.2729068 | E34: Retorno sobre inversión en inventario
A36: SEMÁFORO DE SALUD DEL NEGOCIO
B38: ¿Recuperaste la inversión? | C38: =IF(C29=0,"—",IF(C18>0,"✅ SÍ","❌ NO")) -> ✅ SÍ | E38: Ganancia real positiva
B39: ¿El negocio se autosostiene? | C39: =IF(C29=0,"—",IF(C24>0,"✅ SÍ","❌ NO")) -> ✅ SÍ | E39: Hay fondos para reinversión
B40: ¿Genera sueldo para ti? | C40: =IF(C29=0,"—",IF(C25>0,"✅ SÍ","❌ NO")) -> ✅ SÍ | E40: Hay ganancia personal disponible
B41: ¿Superaste 50 ventas? | C41: =IF(C29>=50,"✅ SÍ — ¡Baja tu tarifa de envío!","❌ NO — Aún no") -> ✅ SÍ — ¡Baja tu tarifa de envío! | E41: Meta para reducir costo de envío

Sheet Marzo 2026 - Ventas
A1: ÁVILA MUSIC - REGISTRO DE VENTAS DETALLADO
A2: ='Configuración'!C17&" "&'Configuración'!C18
A4: # | B4: Fecha | C4: Producto | D4: Categoría | E4: Costo USD | F4: Precio Venta USD | G4: Comisión ML | H4: Envío Gratis | I4: Comisión ML | J4: Costo Envío USD | K4: Ingreso Neto USD | L4: Ganancia Bruta USD | M4: Margen % | N4: Descuento USD
A5: 1 | B5: 46104 | C5: Base pared Guitarra/Bajo | D5: =IFERROR(VLOOKUP(C5,'Catálogo Productos'!$B$3:$E$53,2,0),"") -> Bases, Stand, Atriles | E5: =IFERROR(VLOOKUP(C5,'Catálogo Productos'!$B$3:$E$53,3,0),"") -> 0.5 | F5: =IFERROR(VLOOKUP(C5,'Catálogo Productos'!$B$3:$E$53,4,0),"") -> 4.99 | G5: =IF(F5="","",IF(I5="SÍ",F5*'Configuración'!$C$5,0)) -> 0.5489 | H5: SÍ | I5: SÍ | J5: =IF(F5="","",IF(H5="SÍ",'Configuración'!$C$6,0)) -> 1.3 | K5: =IF(F5="","",F5-G5-J5) -> 3.1411 | L5: =IF(F5="","",K5-E5-IF(N5="",0,N5)) -> 2.6411 | M5: =IF(F5="","",IF(K5=0,0,L5/K5)) -> 0.84082009
A6: 2 | B6: 46104 | C6: Capotraste | D6: =IFERROR(VLOOKUP(C6,'Catálogo Productos'!$B$3:$E$53,2,0),"") -> Capostraste | E6: =IFERROR(VLOOKUP(C6,'Catálogo Productos'!$B$3:$E$53,3,0),"") -> 0.65 | F6: =IFERROR(VLOOKUP(C6,'Catálogo Productos'!$B$3:$E$53,4,0),"") -> 6.99 | G6: =IF(F6="","",IF(I6="SÍ",F6*'Configuración'!$C$5,0)) -> 0.7689 | H6: SÍ | I6: SÍ | J6: =IF(F6="","",IF(H6="SÍ",'Configuración'!$C$6,0)) -> 1.3 | K6: =IF(F6="","",F6-G6-J6) -> 4.9211 | L6: =IF(F6="","",K6-E6-IF(N6="",0,N6)) -> 4.2711 | M6: =IF(F6="","",IF(K6=0,0,L6/K6)) -> 0.86791571
A7: 3 | B7: 46104 | C7: Correa Guitarra/Bajo | D7: =IFERROR(VLOOKUP(C7,'Catálogo Productos'!$B$3:$E$53,2,0),"") -> Correas | E7: =IFERROR(VLOOKUP(C7,'Catálogo Productos'!$B$3:$E$53,3,0),"") -> 0.2 | F7: =IFERROR(VLOOKUP(C7,'Catálogo Productos'!$B$3:$E$53,4,0),"") -> 5.49 | G7: =IF(F7="","",IF(I7="SÍ",F7*'Configuración'!$C$5,0)) -> 0.6039 | H7: SÍ | I7: SÍ | J7: =IF(F7="","",IF(H7="SÍ",'Configuración'!$C$6,0)) -> 1.3 | K7: =IF(F7="","",F7-G7-J7) -> 3.5861 | L7: =IF(F7="","",K7-E7-IF(N7="",0,N7)) -> 3.3861 | M7: =IF(F7="","",IF(K7=0,0,L7/K7)) -> 0.94422911
A8: 4 | B8: 46104 | C8: Correa Guitarra/Bajo | D8: =IFERROR(VLOOKUP(C8,'Catálogo Productos'!$B$3:$E$53,2,0),"") -> Correas | E8: =IFERROR(VLOOKUP(C8,'Catálogo Productos'!$B$3:$E$53,3,0),"") -> 0.2 | F8: =IFERROR(VLOOKUP(C8,'Catálogo Productos'!$B$3:$E$53,4,0),"") -> 5.49 | G8: =IF(F8="","",IF(I8="SÍ",F8*'Configuración'!$C$5,0)) -> 0.6039 | H8: SÍ | I8: SÍ | J8: =IF(F8="","",IF(H8="SÍ",'Configuración'!$C$6,0)) -> 1.3 | K8: =IF(F8="","",F8-G8-J8) -> 3.5861 | L8: =IF(F8="","",K8-E8-IF(N8="",0,N8)) -> 3.3861 | M8: =IF(F8="","",IF(K8=0,0,L8/K8)) -> 0.94422911
A9: 5 | B9: 46104 | C9: Cuerdas de Violin 4/4 | D9: =IFERROR(VLOOKUP(C9,'Catálogo Productos'!$B$3:$E$53,2,0),"") -> Violin | E9: =IFERROR(VLOOKUP(C9,'Catálogo Productos'!$B$3:$E$53,3,0),"") -> 1.06 | F9: =IFERROR(VLOOKUP(C9,'Catálogo Productos'!$B$3:$E$53,4,0),"") -> 4.99 | G9: =IF(F9="","",IF(I9="SÍ",F9*'Configuración'!$C$5,0)) -> 0.5489 | H9: SÍ | I9: SÍ | J9: =IF(F9="","",IF(H9="SÍ",'Configuración'!$C$6,0)) -> 1.3 | K9: =IF(F9="","",F9-G9-J9) -> 3.1411 | L9: =IF(F9="","",K9-E9-IF(N9="",0,N9)) -> 2.0811 | M9: =IF(F9="","",IF(K9=0,0,L9/K9)) -> 0.6625386
A10: 6 | B10: 46104 | C10: Cable Hebikuo XA03 | D10: =IFERROR(VLOOKUP(C10,'Catálogo Productos'!$B$3:$E$53,2,0),"") -> Cables | E10: =IFERROR(VLOOKUP(C10,'Catálogo Productos'!$B$3:$E$53,3,0),"") -> 1.91 | F10: =IFERROR(VLOOKUP(C10,'Catálogo Productos'!$B$3:$E$53,4,0),"") -> 10 | G10: =IF(F10="","",IF(I10="SÍ",F10*'Configuración'!$C$5,0)) -> 1.1 | H10: SÍ | I10: SÍ | J10: =IF(F10="","",IF(H10="SÍ",'Configuración'!$C$6,0)) -> 1.3 | K10: =IF(F10="","",F10-G10-J10) -> 7.6 | L10: =IF(F10="","",K10-E10-IF(N10="",0,N10)) -> 5.69 | M10: =IF(F10="","",IF(K10=0,0,L10/K10)) -> 0.74868421
A11: 7 | B11: 24/03/0206 | C11: Cuerdas Alice Clasica A106 | D11: =IFERROR(VLOOKUP(C11,'Catálogo Productos'!$B$3:$E$53,2,0),"") -> Guitarra Clasica | E11: =IFERROR(VLOOKUP(C11,'Catálogo Productos'!$B$3:$E$53,3,0),"") -> 1.21 | F11: =IFERROR(VLOOKUP(C11,'Catálogo Productos'!$B$3:$E$53,4,0),"") -> 5.49 | G11: =IF(F11="","",IF(I11="SÍ",F11*'Configuración'!$C$5,0)) -> 0.6039 | H11: SÍ | I11: SÍ | J11: =IF(F11="","",IF(H11="SÍ",'Configuración'!$C$6,0)) -> 1.3 | K11: =IF(F11="","",F11-G11-J11) -> 3.5861 | L11: =IF(F11="","",K11-E11-IF(N11="",0,N11)) -> 2.3761 | M11: =IF(F11="","",IF(K11=0,0,L11/K11)) -> 0.6625861
A12: 8 | B12: 02/03/0206 | C12: Correa Guitarra/Bajo | D12: =IFERROR(VLOOKUP(C12,'Catálogo Productos'!$B$3:$E$53,2,0),"") -> Correas | E12: =IFERROR(VLOOKUP(C12,'Catálogo Productos'!$B$3:$E$53,3,0),"") -> 0.2 | F12: =IFERROR(VLOOKUP(C12,'Catálogo Productos'!$B$3:$E$53,4,0),"") -> 5.49 | G12: =IF(F12="","",IF(I12="SÍ",F12*'Configuración'!$C$5,0)) -> 0.6039 | H12: SÍ | I12: SÍ | J12: =IF(F12="","",IF(H12="SÍ",'Configuración'!$C$6,0)) -> 1.3 | K12: =IF(F12="","",F12-G12-J12) -> 3.5861 | L12: =IF(F12="","",K12-E12-IF(N12="",0,N12)) -> 3.3861 | M12: =IF(F12="","",IF(K12=0,0,L12/K12)) -> 0.94422911
A13: 9 | B13: 02/03/0206 | C13: Cable Hebikuo XA03 | D13: =IFERROR(VLOOKUP(C13,'Catálogo Productos'!$B$3:$E$53,2,0),"") -> Cables | E13: =IFERROR(VLOOKUP(C13,'Catálogo Productos'!$B$3:$E$53,3,0),"") -> 1.91 | F13: =IFERROR(VLOOKUP(C13,'Catálogo Productos'!$B$3:$E$53,4,0),"") -> 10 | G13: =IF(F13="","",IF(I13="SÍ",F13*'Configuración'!$C$5,0)) -> 1.1 | H13: SÍ | I13: SÍ | J13: =IF(F13="","",IF(H13="SÍ",'Configuración'!$C$6,0)) -> 1.3 | K13: =IF(F13="","",F13-G13-J13) -> 7.6 | L13: =IF(F13="","",K13-E13-IF(N13="",0,N13)) -> 5.69 | M13: =IF(F13="","",IF(K13=0,0,L13/K13)) -> 0.74868421
A14: 10 | B14: 02/03/0206 | C14: Cable Hebikuo XA03 | D14: =IFERROR(VLOOKUP(C14,'Catálogo Productos'!$B$3:$E$53,2,0),"") -> Cables | E14: =IFERROR(VLOOKUP(C14,'Catálogo Productos'!$B$3:$E$53,3,0),"") -> 1.91 | F14: =IFERROR(VLOOKUP(C14,'Catálogo Productos'!$B$3:$E$53,4,0),"") -> 10 | G14: =IF(F14="","",IF(I14="SÍ",F14*'Configuración'!$C$5,0)) -> 1.1 | H14: SÍ | I14: SÍ | J14: =IF(F14="","",IF(H14="SÍ",'Configuración'!$C$6,0)) -> 1.3 | K14: =IF(F14="","",F14-G14-J14) -> 7.6 | L14: =IF(F14="","",K14-E14-IF(N14="",0,N14)) -> 5.69 | M14: =IF(F14="","",IF(K14=0,0,L14/K14)) -> 0.74868421
A15: 11 | B15: 02/03/0206 | C15: Cuerdas Alice Clasica A106 | D15: =IFERROR(VLOOKUP(C15,'Catálogo Productos'!$B$3:$E$53,2,0),"") -> Guitarra Clasica | E15: =IFERROR(VLOOKUP(C15,'Catálogo Productos'!$B$3:$E$53,3,0),"") -> 1.21 | F15: =IFERROR(VLOOKUP(C15,'Catálogo Productos'!$B$3:$E$53,4,0),"") -> 5.49 | G15: =IF(F15="","",IF(I15="SÍ",F15*'Configuración'!$C$5,0)) -> 0.6039 | H15: SÍ | I15: SÍ | J15: =IF(F15="","",IF(H15="SÍ",'Configuración'!$C$6,0)) -> 1.3 | K15: =IF(F15="","",F15-G15-J15) -> 3.5861 | L15: =IF(F15="","",K15-E15-IF(N15="",0,N15)) -> 2.3761 | M15: =IF(F15="","",IF(K15=0,0,L15/K15)) -> 0.6625861
A16: 12 | B16: 02/03/0206 | C16: Cuerdas de Violin 4/4 | D16: =IFERROR(VLOOKUP(C16,'Catálogo Productos'!$B$3:$E$53,2,0),"") -> Violin | E16: =IFERROR(VLOOKUP(C16,'Catálogo Productos'!$B$3:$E$53,3,0),"") -> 1.06 | F16: =IFERROR(VLOOKUP(C16,'Catálogo Productos'!$B$3:$E$53,4,0),"") -> 4.99 | G16: =IF(F16="","",IF(I16="SÍ",F16*'Configuración'!$C$5,0)) -> 0.5489 | H16: SÍ | I16: SÍ | J16: =IF(F16="","",IF(H16="SÍ",'Configuración'!$C$6,0)) -> 1.3 | K16: =IF(F16="","",F16-G16-J16) -> 3.1411 | L16: =IF(F16="","",K16-E16-IF(N16="",0,N16)) -> 2.0811 | M16: =IF(F16="","",IF(K16=0,0,L16/K16)) -> 0.6625386
A17: 13 | B17: 02/03/0206 | C17: Hombrera Violin 3/4 4/4 | D17: =IFERROR(VLOOKUP(C17,'Catálogo Productos'!$B$3:$E$53,2,0),"") -> Violin | E17: =IFERROR(VLOOKUP(C17,'Catálogo Productos'!$B$3:$E$53,3,0),"") -> 2.69 | F17: =IFERROR(VLOOKUP(C17,'Catálogo Productos'!$B$3:$E$53,4,0),"") -> 11 | G17: =IF(F17="","",IF(I17="SÍ",F17*'Configuración'!$C$5,0)) -> 1.21 | H17: SÍ | I17: SÍ | J17: =IF(F17="","",IF(H17="SÍ",'Configuración'!$C$6,0)) -> 1.3 | K17: =IF(F17="","",F17-G17-J17) -> 8.49 | L17: =IF(F17="","",K17-E17-IF(N17="",0,N17)) -> 5.8 | M17: =IF(F17="","",IF(K17=0,0,L17/K17)) -> 0.68315665
A18: 14 | B18: 02/03/0206 | C18: Cable Hebikuo XA03 | D18: =IFERROR(VLOOKUP(C18,'Catálogo Productos'!$B$3:$E$53,2,0),"") -> Cables | E18: =IFERROR(VLOOKUP(C18,'Catálogo Productos'!$B$3:$E$53,3,0),"") -> 1.91 | F18: =IFERROR(VLOOKUP(C18,'Catálogo Productos'!$B$3:$E$53,4,0),"") -> 10 | G18: =IF(F18="","",IF(I18="SÍ",F18*'Configuración'!$C$5,0)) -> 1.1 | H18: SÍ | I18: SÍ | J18: =IF(F18="","",IF(H18="SÍ",'Configuración'!$C$6,0)) -> 1.3 | K18: =IF(F18="","",F18-G18-J18) -> 7.6 | L18: =IF(F18="","",K18-E18-IF(N18="",0,N18)) -> 5.69 | M18: =IF(F18="","",IF(K18=0,0,L18/K18)) -> 0.74868421
A19: 15 | B19: 02/03/0206 | C19: Cable Hebikuo XA03 | D19: =IFERROR(VLOOKUP(C19,'Catálogo Productos'!$B$3:$E$53,2,0),"") -> Cables | E19: =IFERROR(VLOOKUP(C19,'Catálogo Productos'!$B$3:$E$53,3,0),"") -> 1.91 | F19: =IFERROR(VLOOKUP(C19,'Catálogo Productos'!$B$3:$E$53,4,0),"") -> 10 | G19: =IF(F19="","",IF(I19="SÍ",F19*'Configuración'!$C$5,0)) -> 1.1 | H19: SÍ | I19: SÍ | J19: =IF(F19="","",IF(H19="SÍ",'Configuración'!$C$6,0)) -> 1.3 | K19: =IF(F19="","",F19-G19-J19) -> 7.6 | L19: =IF(F19="","",K19-E19-IF(N19="",0,N19)) -> 5.69 | M19: =IF(F19="","",IF(K19=0,0,L19/K19)) -> 0.74868421
A20: 16 | B20: 02/03/0206 | C20: Cable Hebikuo XA03 | D20: =IFERROR(VLOOKUP(C20,'Catálogo Productos'!$B$3:$E$53,2,0),"") -> Cables | E20: =IFERROR(VLOOKUP(C20,'Catálogo Productos'!$B$3:$E$53,3,0),"") -> 1.91 | F20: =IFERROR(VLOOKUP(C20,'Catálogo Productos'!$B$3:$E$53,4,0),"") -> 10 | G20: =IF(F20="","",IF(I20="SÍ",F20*'Configuración'!$C$5,0)) -> 1.1 | H20: SÍ | I20: SÍ | J20: =IF(F20="","",IF(H20="SÍ",'Configuración'!$C$6,0)) -> 1.3 | K20: =IF(F20="","",F20-G20-J20) -> 7.6 | L20: =IF(F20="","",K20-E20-IF(N20="",0,N20)) -> 5.69 | M20: =IF(F20="","",IF(K20=0,0,L20/K20)) -> 0.74868421
A21: 17 | B21: 02/03/0206 | C21: Cuerdas Alice Electrica SL | D21: =IFERROR(VLOOKUP(C21,'Catálogo Productos'!$B$3:$E$53,2,0),"") -> Guitarra Electrica | E21: =IFERROR(VLOOKUP(C21,'Catálogo Productos'!$B$3:$E$53,3,0),"") -> 1.21 | F21: =IFERROR(VLOOKUP(C21,'Catálogo Productos'!$B$3:$E$53,4,0),"") -> 5.49 | G21: =IF(F21="","",IF(I21="SÍ",F21*'Configuración'!$C$5,0)) -> 0.6039 | H21: SÍ | I21: SÍ | J21: =IF(F21="","",IF(H21="SÍ",'Configuración'!$C$6,0)) -> 1.3 | K21: =IF(F21="","",F21-G21-J21) -> 3.5861 | L21: =IF(F21="","",K21-E21-IF(N21="",0,N21)) -> 2.3761 | M21: =IF(F21="","",IF(K21=0,0,L21/K21)) -> 0.6625861
A22: 18 | B22: 02/03/0206 | C22: Cuerdas Alice Electrica L | D22: =IFERROR(VLOOKUP(C22,'Catálogo Productos'!$B$3:$E$53,2,0),"") -> Guitarra Electrica | E22: =IFERROR(VLOOKUP(C22,'Catálogo Productos'!$B$3:$E$53,3,0),"") -> 1.21 | F22: =IFERROR(VLOOKUP(C22,'Catálogo Productos'!$B$3:$E$53,4,0),"") -> 5.49 | G22: =IF(F22="","",IF(I22="SÍ",F22*'Configuración'!$C$5,0)) -> 0.6039 | H22: SÍ | I22: SÍ | J22: =IF(F22="","",IF(H22="SÍ",'Configuración'!$C$6,0)) -> 1.3 | K22: =IF(F22="","",F22-G22-J22) -> 3.5861 | L22: =IF(F22="","",K22-E22-IF(N22="",0,N22)) -> 2.3761 | M22: =IF(F22="","",IF(K22=0,0,L22/K22)) -> 0.6625861
... A43: 39 | B43: 02/03/0206 | C43: Pines de Correa | D43: =IFERROR(VLOOKUP(C43,'Catálogo Productos'!$B$3:$E$53,2,0),"") -> Guitarra Acustica | E43: =IFERROR(VLOOKUP(C43,'Catálogo Productos'!$B$3:$E$53,3,0),"") -> 0.01 | F43: =IFERROR(VLOOKUP(C43,'Catálogo Productos'!$B$3:$E$53,4,0),"") -> 5 | G43: =IF(F43="","",IF(I43="SÍ",F43*'Configuración'!$C$5,0)) -> 0.55 | H43: SÍ | I43: SÍ | J43: =IF(F43="","",IF(H43="SÍ",'Configuración'!$C$6,0)) -> 1.3 | K43: =IF(F43="","",F43-G43-J43) -> 3.15 | L43: =IF(F43="","",K43-E43-IF(N43="",0,N43)) -> 3.14 | M43: =IF(F43="","",IF(K43=0,0,L43/K43)) -> 0.9968254
A44: 40 | B44: 46105 | C44: Cable Pedales | D44: =IFERROR(VLOOKUP(C44,'Catálogo Productos'!$B$3:$E$53,2,0),"") -> Guitarra Electrica | E44: =IFERROR(VLOOKUP(C44,'Catálogo Productos'!$B$3:$E$53,3,0),"") -> 2.3 | F44: =IFERROR(VLOOKUP(C44,'Catálogo Productos'!$B$3:$E$53,4,0),"") -> 14 | G44: =IF(F44="","",IF(I44="SÍ",F44*'Configuración'!$C$5,0)) -> 1.54 | H44: SÍ | I44: SÍ | J44: =IF(F44="","",IF(H44="SÍ",'Configuración'!$C$6,0)) -> 1.3 | K44: =IF(F44="","",F44-G44-J44) -> 11.16 | L44: =IF(F44="","",K44-E44-IF(N44="",0,N44)) -> 8.86 | M44: =IF(F44="","",IF(K44=0,0,L44/K44)) -> 0.79390681
A45: 41 | B45: 46105 | C45: Clavijas Guitarra Clasica Doradas | D45: =IFERROR(VLOOKUP(C45,'Catálogo Productos'!$B$3:$E$53,2,0),"") -> Guitarra Clasica | E45: =IFERROR(VLOOKUP(C45,'Catálogo Productos'!$B$3:$E$53,3,0),"") -> 2.5 | F45: =IFERROR(VLOOKUP(C45,'Catálogo Productos'!$B$3:$E$53,4,0),"") -> 9.99 | G45: =IF(F45="","",IF(I45="SÍ",F45*'Configuración'!$C$5,0)) -> 1.0989 | H45: SÍ | I45: SÍ | J45: =IF(F45="","",IF(H45="SÍ",'Configuración'!$C$6,0)) -> 1.3 | K45: =IF(F45="","",F45-G45-J45) -> 7.5911 | L45: =IF(F45="","",K45-E45-IF(N45="",0,N45)) -> 5.0911 | M45: =IF(F45="","",IF(K45=0,0,L45/K45)) -> 0.67066697
A46: 42 | B46: 46105 | C46: Clavijas Guitarra Clasica Doradas | D46: =IFERROR(VLOOKUP(C46,'Catálogo Productos'!$B$3:$E$53,2,0),"") -> Guitarra Clasica | E46: =IFERROR(VLOOKUP(C46,'Catálogo Productos'!$B$3:$E$53,3,0),"") -> 2.5 | F46: =IFERROR(VLOOKUP(C46,'Catálogo Productos'!$B$3:$E$53,4,0),"") -> 9.99 | G46: =IF(F46="","",IF(I46="SÍ",F46*'Configuración'!$C$5,0)) -> 1.0989 | H46: SÍ | I46: SÍ | J46: =IF(F46="","",IF(H46="SÍ",'Configuración'!$C$6,0)) -> 1.3 | K46: =IF(F46="","",F46-G46-J46) -> 7.5911 | L46: =IF(F46="","",K46-E46-IF(N46="",0,N46)) -> 5.0911 | M46: =IF(F46="","",IF(K46=0,0,L46/K46)) -> 0.67066697
A47: 43 | B47: 46106 | C47: Cuerdas Alice Folk 11-52 | D47: =IFERROR(VLOOKUP(C47,'Catálogo Productos'!$B$3:$E$53,2,0),"") -> Guitarra Acustica | E47: =IFERROR(VLOOKUP(C47,'Catálogo Productos'!$B$3:$E$53,3,0),"") -> 1.21 | F47: =IFERROR(VLOOKUP(C47,'Catálogo Productos'!$B$3:$E$53,4,0),"") -> 5.49 | G47: =IF(F47="","",IF(I47="SÍ",F47*'Configuración'!$C$5,0)) -> 0.6039 | H47: SÍ | I47: SÍ | J47: =IF(F47="","",IF(H47="SÍ",'Configuración'!$C$6,0)) -> 1.3 | K47: =IF(F47="","",F47-G47-J47) -> 3.5861 | L47: =IF(F47="","",K47-E47-IF(N47="",0,N47)) -> 2.3761 | M47: =IF(F47="","",IF(K47=0,0,L47/K47)) -> 0.6625861
A48: 44 | B48: 46106 | C48: Cuerdas Alice Electrica SL | D48: =IFERROR(VLOOKUP(C48,'Catálogo Productos'!$B$3:$E$53,2,0),"") -> Guitarra Electrica | E48: =IFERROR(VLOOKUP(C48,'Catálogo Productos'!$B$3:$E$53,3,0),"") -> 1.21 | F48: =IFERROR(VLOOKUP(C48,'Catálogo Productos'!$B$3:$E$53,4,0),"") -> 5.49 | G48: =IF(F48="","",IF(I48="SÍ",F48*'Configuración'!$C$5,0)) -> 0 | H48: No | I48: NO | J48: =IF(F48="","",IF(H48="SÍ",'Configuración'!$C$6,0)) -> 0 | K48: =IF(F48="","",F48-G48-J48) -> 5.49 | L48: =IF(F48="","",K48-E48-IF(N48="",0,N48)) -> 3.78 | M48: =IF(F48="","",IF(K48=0,0,L48/K48)) -> 0.68852459 | N48: 0.5
A49: 45 | B49: 46106 | C49: Cuerdas Alice Electrica SL | D49: =IFERROR(VLOOKUP(C49,'Catálogo Productos'!$B$3:$E$53,2,0),"") -> Guitarra Electrica | E49: =IFERROR(VLOOKUP(C49,'Catálogo Productos'!$B$3:$E$53,3,0),"") -> 1.21 | F49: =IFERROR(VLOOKUP(C49,'Catálogo Productos'!$B$3:$E$53,4,0),"") -> 5.49 | G49: =IF(F49="","",IF(I49="SÍ",F49*'Configuración'!$C$5,0)) -> 0 | H49: No | I49: NO | J49: =IF(F49="","",IF(H49="SÍ",'Configuración'!$C$6,0)) -> 0 | K49: =IF(F49="","",F49-G49-J49) -> 5.49 | L49: =IF(F49="","",K49-E49-IF(N49="",0,N49)) -> 3.78 | M49: =IF(F49="","",IF(K49=0,0,L49/K49)) -> 0.68852459 | N49: 0.5
A50: 46 | B50: 46106 | C50: Cuerdas Bajo 4C Alice | D50: =IFERROR(VLOOKUP(C50,'Catálogo Productos'!$B$3:$E$53,2,0),"") -> Bajo Electrico | E50: =IFERROR(VLOOKUP(C50,'Catálogo Productos'!$B$3:$E$53,3,0),"") -> 3.03 | F50: =IFERROR(VLOOKUP(C50,'Catálogo Productos'!$B$3:$E$53,4,0),"") -> 12.99 | G50: =IF(F50="","",IF(I50="SÍ",F50*'Configuración'!$C$5,0)) -> 0 | H50: No | I50: NO | J50: =IF(F50="","",IF(H50="SÍ",'Configuración'!$C$6,0)) -> 0 | K50: =IF(F50="","",F50-G50-J50) -> 12.99 | L50: =IF(F50="","",K50-E50-IF(N50="",0,N50)) -> 7.96 | M50: =IF(F50="","",IF(K50=0,0,L50/K50)) -> 0.61277906 | N50: 2
A51: 47 | B51: 46106 | C51: Capotraste | D51: =IFERROR(VLOOKUP(C51,'Catálogo Productos'!$B$3:$E$53,2,0),"") -> Capostraste | E51: =IFERROR(VLOOKUP(C51,'Catálogo Productos'!$B$3:$E$53,3,0),"") -> 0.65 | F51: =IFERROR(VLOOKUP(C51,'Catálogo Productos'!$B$3:$E$53,4,0),"") -> 6.99 | G51: =IF(F51="","",IF(I51="SÍ",F51*'Configuración'!$C$5,0)) -> 0.7689 | H51: SÍ | I51: SÍ | J51: =IF(F51="","",IF(H51="SÍ",'Configuración'!$C$6,0)) -> 1.3 | K51: =IF(F51="","",F51-G51-J51) -> 4.9211 | L51: =IF(F51="","",K51-E51-IF(N51="",0,N51)) -> 4.2711 | M51: =IF(F51="","",IF(K51=0,0,L51/K51)) -> 0.86791571
A52: 48 | B52: 46108 | C52: Cuerdas Alice Electrica L | D52: =IFERROR(VLOOKUP(C52,'Catálogo Productos'!$B$3:$E$53,2,0),"") -> Guitarra Electrica | E52: =IFERROR(VLOOKUP(C52,'Catálogo Productos'!$B$3:$E$53,3,0),"") -> 1.21 | F52: =IFERROR(VLOOKUP(C52,'Catálogo Productos'!$B$3:$E$53,4,0),"") -> 5.49 | G52: =IF(F52="","",IF(I52="SÍ",F52*'Configuración'!$C$5,0)) -> 0.6039 | H52: SÍ | I52: SÍ | J52: =IF(F52="","",IF(H52="SÍ",'Configuración'!$C$6,0)) -> 1.3 | K52: =IF(F52="","",F52-G52-J52) -> 3.5861 | L52: =IF(F52="","",K52-E52-IF(N52="",0,N52)) -> 2.3761 | M52: =IF(F52="","",IF(K52=0,0,L52/K52)) -> 0.6625861
A53: 49 | B53: 46108 | C53: Cuerdas Alice Folk 11-52 | D53: =IFERROR(VLOOKUP(C53,'Catálogo Productos'!$B$3:$E$53,2,0),"") -> Guitarra Acustica | E53: =IFERROR(VLOOKUP(C53,'Catálogo Productos'!$B$3:$E$53,3,0),"") -> 1.21 | F53: =IFERROR(VLOOKUP(C53,'Catálogo Productos'!$B$3:$E$53,4,0),"") -> 5.49 | G53: =IF(F53="","",IF(I53="SÍ",F53*'Configuración'!$C$5,0)) -> 0.6039 | H53: SÍ | I53: SÍ | J53: =IF(F53="","",IF(H53="SÍ",'Configuración'!$C$6,0)) -> 1.3 | K53: =IF(F53="","",F53-G53-J53) -> 3.5861 | L53: =IF(F53="","",K53-E53-IF(N53="",0,N53)) -> 2.3761 | M53: =IF(F53="","",IF(K53=0,0,L53/K53)) -> 0.6625861
A54: 50 | B54: 46110 | C54: Cuerdas Bajo 4C Alice | D54: =IFERROR(VLOOKUP(C54,'Catálogo Productos'!$B$3:$E$53,2,0),"") -> Bajo Electrico | E54: =IFERROR(VLOOKUP(C54,'Catálogo Productos'!$B$3:$E$53,3,0),"") -> 3.03 | F54: =IFERROR(VLOOKUP(C54,'Catálogo Productos'!$B$3:$E$53,4,0),"") -> 12.99 | G54: =IF(F54="","",IF(I54="SÍ",F54*'Configuración'!$C$5,0)) -> 1.4289 | H54: SÍ | I54: SÍ | J54: =IF(F54="","",IF(H54="SÍ",'Configuración'!$C$6,0)) -> 1.3 | K54: =IF(F54="","",F54-G54-J54) -> 10.2611 | L54: =IF(F54="","",K54-E54-IF(N54="",0,N54)) -> 6.2311 | M54: =IF(F54="","",IF(K54=0,0,L54/K54)) -> 0.60725458 | N54: 1
A55: 51 | B55: 46110 | C55: Cuerdas Alice Electrica L | D55: =IFERROR(VLOOKUP(C55,'Catálogo Productos'!$B$3:$E$53,2,0),"") -> Guitarra Electrica | E55: =IFERROR(VLOOKUP(C55,'Catálogo Productos'!$B$3:$E$53,3,0),"") -> 1.21 | F55: =IFERROR(VLOOKUP(C55,'Catálogo Productos'!$B$3:$E$53,4,0),"") -> 5.49 | G55: =IF(F55="","",IF(I55="SÍ",F55*'Configuración'!$C$5,0)) -> 0.6039 | H55: SÍ | I55: SÍ | J55: =IF(F55="","",IF(H55="SÍ",'Configuración'!$C$6,0)) -> 1.3 | K55: =IF(F55="","",F55-G55-J55) -> 3.5861 | L55: =IF(F55="","",K55-E55-IF(N55="",0,N55)) -> 0.8761 | M55: =IF(F55="","",IF(K55=0,0,L55/K55)) -> 0.2443044 | N55: 1.5
A56: 52 | B56: 46111 | C56: Cuerdas Alice Clasica A106 | D56: =IFERROR(VLOOKUP(C56,'Catálogo Productos'!$B$3:$E$53,2,0),"") -> Guitarra Clasica | E56: =IFERROR(VLOOKUP(C56,'Catálogo Productos'!$B$3:$E$53,3,0),"") -> 1.21 | F56: =IFERROR(VLOOKUP(C56,'Catálogo Productos'!$B$3:$E$53,4,0),"") -> 5.49 | G56: =IF(F56="","",IF(I56="SÍ",F56*'Configuración'!$C$5,0)) -> 0.6039 | H56: SÍ | I56: SÍ | J56: =IF(F56="","",IF(H56="SÍ",'Configuración'!$C$6,0)) -> 1.3 | K56: =IF(F56="","",F56-G56-J56) -> 3.5861 | L56: =IF(F56="","",K56-E56-IF(N56="",0,N56)) -> 0.3761 | M56: =IF(F56="","",IF(K56=0,0,L56/K56)) -> 0.10487716 | N56: 2
A57: 53 | B57: 46111 | C57: Cuerdas Alice Clasica A106 | D57: =IFERROR(VLOOKUP(C57,'Catálogo Productos'!$B$3:$E$53,2,0),"") -> Guitarra Clasica | E57: =IFERROR(VLOOKUP(C57,'Catálogo Productos'!$B$3:$E$53,3,0),"") -> 1.21 | F57: =IFERROR(VLOOKUP(C57,'Catálogo Productos'!$B$3:$E$53,4,0),"") -> 5.49 | G57: =IF(F57="","",IF(I57="SÍ",F57*'Configuración'!$C$5,0)) -> 0 | H57: No | I57: NO | J57: =IF(F57="","",IF(H57="SÍ",'Configuración'!$C$6,0)) -> 0 | K57: =IF(F57="","",F57-G57-J57) -> 5.49 | L57: =IF(F57="","",K57-E57-IF(N57="",0,N57)) -> 2.28 | M57: =IF(F57="","",IF(K57=0,0,L57/K57)) -> 0.41530055 | N57: 2
A58: 54 | B58: 46111 | C58: Cuerdas Alice Folk 11-52 | D58: =IFERROR(VLOOKUP(C58,'Catálogo Productos'!$B$3:$E$53,2,0),"") -> Guitarra Acustica | E58: =IFERROR(VLOOKUP(C58,'Catálogo Productos'!$B$3:$E$53,3,0),"") -> 1.21 | F58: =IFERROR(VLOOKUP(C58,'Catálogo Productos'!$B$3:$E$53,4,0),"") -> 5.49 | G58: =IF(F58="","",IF(I58="SÍ",F58*'Configuración'!$C$5,0)) -> 0.6039 | H58: SÍ | I58: SÍ | J58: =IF(F58="","",IF(H58="SÍ",'Configuración'!$C$6,0)) -> 1.3 | K58: =IF(F58="","",F58-G58-J58) -> 3.5861 | L58: =IF(F58="","",K58-E58-IF(N58="",0,N58)) -> 0.8861 | M58: =IF(F58="","",IF(K58=0,0,L58/K58)) -> 0.24709294 | N58: 1.49
A59: 55 | B59: 46111 | C59: Pickguard Negro Guitarra Acustica | D59: =IFERROR(VLOOKUP(C59,'Catálogo Productos'!$B$3:$E$53,2,0),"") -> Guitarra Acustica | E59: =IFERROR(VLOOKUP(C59,'Catálogo Productos'!$B$3:$E$53,3,0),"") -> 0.5 | F59: =IFERROR(VLOOKUP(C59,'Catálogo Productos'!$B$3:$E$53,4,0),"") -> 5 | G59: =IF(F59="","",IF(I59="SÍ",F59*'Configuración'!$C$5,0)) -> 0.55 | H59: SÍ | I59: SÍ | J59: =IF(F59="","",IF(H59="SÍ",'Configuración'!$C$6,0)) -> 1.3 | K59: =IF(F59="","",F59-G59-J59) -> 3.15 | L59: =IF(F59="","",K59-E59-IF(N59="",0,N59)) -> 2.65 | M59: =IF(F59="","",IF(K59=0,0,L59/K59)) -> 0.84126984
A60: 56 | B60: 46112 | C60: Clavijas Guitarra Clasica Doradas | D60: =IFERROR(VLOOKUP(C60,'Catálogo Productos'!$B$3:$E$53,2,0),"") -> Guitarra Clasica | E60: =IFERROR(VLOOKUP(C60,'Catálogo Productos'!$B$3:$E$53,3,0),"") -> 2.5 | F60: =IFERROR(VLOOKUP(C60,'Catálogo Productos'!$B$3:$E$53,4,0),"") -> 9.99 | G60: =IF(F60="","",IF(I60="SÍ",F60*'Configuración'!$C$5,0)) -> 1.0989 | H60: No | I60: SÍ | J60: =IF(F60="","",IF(H60="SÍ",'Configuración'!$C$6,0)) -> 0 | K60: =IF(F60="","",F60-G60-J60) -> 8.8911 | L60: =IF(F60="","",K60-E60-IF(N60="",0,N60)) -> 6.3911 | M60: =IF(F60="","",IF(K60=0,0,L60/K60)) -> 0.71881994
A61: 57 | B61: 46112 | C61: Cuerdas Bajo 4C Alice | D61: =IFERROR(VLOOKUP(C61,'Catálogo Productos'!$B$3:$E$53,2,0),"") -> Bajo Electrico | E61: =IFERROR(VLOOKUP(C61,'Catálogo Productos'!$B$3:$E$53,3,0),"") -> 3.03 | F61: =IFERROR(VLOOKUP(C61,'Catálogo Productos'!$B$3:$E$53,4,0),"") -> 12.99 | G61: =IF(F61="","",IF(I61="SÍ",F61*'Configuración'!$C$5,0)) -> 1.4289 | H61: SÍ | I61: SÍ | J61: =IF(F61="","",IF(H61="SÍ",'Configuración'!$C$6,0)) -> 1.3 | K61: =IF(F61="","",F61-G61-J61) -> 10.2611 | L61: =IF(F61="","",K61-E61-IF(N61="",0,N61)) -> 6.2311 | M61: =IF(F61="","",IF(K61=0,0,L61/K61)) -> 0.60725458 | N61: 1
A62: 58 | B62: 46112 | C62: Cuerdas Alice Electrica SL | D62: =IFERROR(VLOOKUP(C62,'Catálogo Productos'!$B$3:$E$53,2,0),"") -> Guitarra Electrica | E62: =IFERROR(VLOOKUP(C62,'Catálogo Productos'!$B$3:$E$53,3,0),"") -> 1.21 | F62: =IFERROR(VLOOKUP(C62,'Catálogo Productos'!$B$3:$E$53,4,0),"") -> 5.49 | G62: =IF(F62="","",IF(I62="SÍ",F62*'Configuración'!$C$5,0)) -> 0.6039 | H62: SÍ | I62: SÍ | J62: =IF(F62="","",IF(H62="SÍ",'Configuración'!$C$6,0)) -> 1.3 | K62: =IF(F62="","",F62-G62-J62) -> 3.5861 | L62: =IF(F62="","",K62-E62-IF(N62="",0,N62)) -> 0.3761 | M62: =IF(F62="","",IF(K62=0,0,L62/K62)) -> 0.10487716 | N62: 2
A63: 59 | B63: 46111 | C63: Capotraste | D63: =IFERROR(VLOOKUP(C63,'Catálogo Productos'!$B$3:$E$53,2,0),"") -> Capostraste | E63: =IFERROR(VLOOKUP(C63,'Catálogo Productos'!$B$3:$E$53,3,0),"") -> 0.65 | F63: =IFERROR(VLOOKUP(C63,'Catálogo Productos'!$B$3:$E$53,4,0),"") -> 6.99 | G63: =IF(F63="","",IF(I63="SÍ",F63*'Configuración'!$C$5,0)) -> 0.7689 | H63: SÍ | I63: SÍ | J63: =IF(F63="","",IF(H63="SÍ",'Configuración'!$C$6,0)) -> 1.3 | K63: =IF(F63="","",F63-G63-J63) -> 4.9211 | L63: =IF(F63="","",K63-E63-IF(N63="",0,N63)) -> 4.2711 | M63: =IF(F63="","",IF(K63=0,0,L63/K63)) -> 0.86791571
A64: TOTALES DEL MES | E64: =SUM(E5:E63) -> 76.72 | F64: =SUM(F5:F63) -> 436.09 | G64: =SUM(G5:G63) -> 44.7293 | J64: =SUM(J5:J63) -> 70.2 | K64: =SUM(K5:K63) -> 321.1607 | L64: =SUM(L5:L63) -> 230.4507 | M64: =IF(K64=0,0,L64/K64) -> 0.71755573 | N64: =SUM(N5:N63) -> 13.99
B66: Total ventas registradas: | C66: =COUNTA(B5:B204) -> 60
A68: 64 | D68: =IFERROR(VLOOKUP(C68,'Catálogo Productos'!$B$3:$E$53,2,0),"") | E68: =IFERROR(VLOOKUP(C68,'Catálogo Productos'!$B$3:$E$53,3,0),"") | F68: =IFERROR(VLOOKUP(C68,'Catálogo Productos'!$B$3:$E$53,4,0),"") | G68: =IF(F68="","",IF(I68="SÍ",F68*'Configuración'!$C$5,0)) | J68: =IF(F68="","",IF(H68="SÍ",'Configuración'!$C$6,0)) | K68: =IF(F68="","",F68-G68-J68) | L68: =IF(F68="","",K68-E68-IF(N68="",0,N68)) | M68: =IF(F68="","",IF(K68=0,0,L68/K68))
A69: 65 | D69: =IFERROR(VLOOKUP(C69,'Catálogo Productos'!$B$3:$E$53,2,0),"") | E69: =IFERROR(VLOOKUP(C69,'Catálogo Productos'!$B$3:$E$53,3,0),"") | F69: =IFERROR(VLOOKUP(C69,'Catálogo Productos'!$B$3:$E$53,4,0),"") | G69: =IF(F69="","",IF(I69="SÍ",F69*'Configuración'!$C$5,0)) | J69: =IF(F69="","",IF(H69="SÍ",'Configuración'!$C$6,0)) | K69: =IF(F69="","",F69-G69-J69) | L69: =IF(F69="","",K69-E69-IF(N69="",0,N69)) | M69: =IF(F69="","",IF(K69=0,0,L69/K69))
A70: 66 | D70: =IFERROR(VLOOKUP(C70,'Catálogo Productos'!$B$3:$E$53,2,0),"") | E70: =IFERROR(VLOOKUP(C70,'Catálogo Productos'!$B$3:$E$53,3,0),"") | F70: =IFERROR(VLOOKUP(C70,'Catálogo Productos'!$B$3:$E$53,4,0),"") | G70: =IF(F70="","",IF(I70="SÍ",F70*'Configuración'!$C$5,0)) | J70: =IF(F70="","",IF(H70="SÍ",'Configuración'!$C$6,0)) | K70: =IF(F70="","",F70-G70-J70) | L70: =IF(F70="","",K70-E70-IF(N70="",0,N70)) | M70: =IF(F70="","",IF(K70=0,0,L70/K70))
A71: 67 | D71: =IFERROR(VLOOKUP(C71,'Catálogo Productos'!$B$3:$E$53,2,0),"") | E71: =IFERROR(VLOOKUP(C71,'Catálogo Productos'!$B$3:$E$53,3,0),"") | F71: =IFERROR(VLOOKUP(C71,'Catálogo Productos'!$B$3:$E$53,4,0),"") | G71: =IF(F71="","",IF(I71="SÍ",F71*'Configuración'!$C$5,0)) | J71: =IF(F71="","",IF(H71="SÍ",'Configuración'!$C$6,0)) | K71: =IF(F71="","",F71-G71-J71) | L71: =IF(F71="","",K71-E71-IF(N71="",0,N71)) | M71: =IF(F71="","",IF(K71=0,0,L71/K71))
A72: 68 | D72: =IFERROR(VLOOKUP(C72,'Catálogo Productos'!$B$3:$E$53,2,0),"") | E72: =IFERROR(VLOOKUP(C72,'Catálogo Productos'!$B$3:$E$53,3,0),"") | F72: =IFERROR(VLOOKUP(C72,'Catálogo Productos'!$B$3:$E$53,4,0),"") | G72: =IF(F72="","",IF(I72="SÍ",F72*'Configuración'!$C$5,0)) | J72: =IF(F72="","",IF(H72="SÍ",'Configuración'!$C$6,0)) | K72: =IF(F72="","",F72-G72-J72) | L72: =IF(F72="","",K72-E72-IF(N72="",0,N72)) | M72: =IF(F72="","",IF(K72=0,0,L72/K72))
A73: 69 | D73: =IFERROR(VLOOKUP(C73,'Catálogo Productos'!$B$3:$E$53,2,0),"") | E73: =IFERROR(VLOOKUP(C73,'Catálogo Productos'!$B$3:$E$53,3,0),"") | F73: =IFERROR(VLOOKUP(C73,'Catálogo Productos'!$B$3:$E$53,4,0),"") | G73: =IF(F73="","",IF(I73="SÍ",F73*'Configuración'!$C$5,0)) | J73: =IF(F73="","",IF(H73="SÍ",'Configuración'!$C$6,0)) | K73: =IF(F73="","",F73-G73-J73) | L73: =IF(F73="","",K73-E73-IF(N73="",0,N73)) | M73: =IF(F73="","",IF(K73=0,0,L73/K73))
A74: 70 | D74: =IFERROR(VLOOKUP(C74,'Catálogo Productos'!$B$3:$E$53,2,0),"") | E74: =IFERROR(VLOOKUP(C74,'Catálogo Productos'!$B$3:$E$53,3,0),"") | F74: =IFERROR(VLOOKUP(C74,'Catálogo Productos'!$B$3:$E$53,4,0),"") | G74: =IF(F74="","",IF(I74="SÍ",F74*'Configuración'!$C$5,0)) | J74: =IF(F74="","",IF(H74="SÍ",'Configuración'!$C$6,0)) | K74: =IF(F74="","",F74-G74-J74) | L74: =IF(F74="","",K74-E74-IF(N74="",0,N74)) | M74: =IF(F74="","",IF(K74=0,0,L74/K74))
A75: 71 | D75: =IFERROR(VLOOKUP(C75,'Catálogo Productos'!$B$3:$E$53,2,0),"") | E75: =IFERROR(VLOOKUP(C75,'Catálogo Productos'!$B$3:$E$53,3,0),"") | F75: =IFERROR(VLOOKUP(C75,'Catálogo Productos'!$B$3:$E$53,4,0),"") | G75: =IF(F75="","",IF(I75="SÍ",F75*'Configuración'!$C$5,0)) | J75: =IF(F75="","",IF(H75="SÍ",'Configuración'!$C$6,0)) | K75: =IF(F75="","",F75-G75-J75) | L75: =IF(F75="","",K75-E75-IF(N75="",0,N75)) | M75: =IF(F75="","",IF(K75=0,0,L75/K75))
A76: 72 | D76: =IFERROR(VLOOKUP(C76,'Catálogo Productos'!$B$3:$E$53,2,0),"") | E76: =IFERROR(VLOOKUP(C76,'Catálogo Productos'!$B$3:$E$53,3,0),"") | F76: =IFERROR(VLOOKUP(C76,'Catálogo Productos'!$B$3:$E$53,4,0),"") | G76: =IF(F76="","",IF(I76="SÍ",F76*'Configuración'!$C$5,0)) | J76: =IF(F76="","",IF(H76="SÍ",'Configuración'!$C$6,0)) | K76: =IF(F76="","",F76-G76-J76) | L76: =IF(F76="","",K76-E76-IF(N76="",0,N76)) | M76: =IF(F76="","",IF(K76=0,0,L76/K76))
A77: 73 | D77: =IFERROR(VLOOKUP(C77,'Catálogo Productos'!$B$3:$E$53,2,0),"") | E77: =IFERROR(VLOOKUP(C77,'Catálogo Productos'!$B$3:$E$53,3,0),"") | F77: =IFERROR(VLOOKUP(C77,'Catálogo Productos'!$B$3:$E$53,4,0),"") | G77: =IF(F77="","",IF(I77="SÍ",F77*'Configuración'!$C$5,0)) | J77: =IF(F77="","",IF(H77="SÍ",'Configuración'!$C$6,0)) | K77: =IF(F77="","",F77-G77-J77) | L77: =IF(F77="","",K77-E77-IF(N77="",0,N77)) | M77: =IF(F77="","",IF(K77=0,0,L77/K77))
A78: 74 | D78: =IFERROR(VLOOKUP(C78,'Catálogo Productos'!$B$3:$E$53,2,0),"") | E78: =IFERROR(VLOOKUP(C78,'Catálogo Productos'!$B$3:$E$53,3,0),"") | F78: =IFERROR(VLOOKUP(C78,'Catálogo Productos'!$B$3:$E$53,4,0),"") | G78: =IF(F78="","",IF(I78="SÍ",F78*'Configuración'!$C$5,0)) | J78: =IF(F78="","",IF(H78="SÍ",'Configuración'!$C$6,0)) | K78: =IF(F78="","",F78-G78-J78) | L78: =IF(F78="","",K78-E78-IF(N78="",0,N78)) | M78: =IF(F78="","",IF(K78=0,0,L78/K78))
A79: 75 | D79: =IFERROR(VLOOKUP(C79,'Catálogo Productos'!$B$3:$E$53,2,0),"") | E79: =IFERROR(VLOOKUP(C79,'Catálogo Productos'!$B$3:$E$53,3,0),"") | F79: =IFERROR(VLOOKUP(C79,'Catálogo Productos'!$B$3:$E$53,4,0),"") | G79: =IF(F79="","",IF(I79="SÍ",F79*'Configuración'!$C$5,0)) | J79: =IF(F79="","",IF(H79="SÍ",'Configuración'!$C$6,0)) | K79: =IF(F79="","",F79-G79-J79) | L79: =IF(F79="","",K79-E79-IF(N79="",0,N79)) | M79: =IF(F79="","",IF(K79=0,0,L79/K79))
... A204: 200 | D204: =IFERROR(VLOOKUP(C204,'Catálogo Productos'!$B$3:$E$53,2,0),"") | E204: =IFERROR(VLOOKUP(C204,'Catálogo Productos'!$B$3:$E$53,3,0),"") | F204: =IFERROR(VLOOKUP(C204,'Catálogo Productos'!$B$3:$E$53,4,0),"") | G204: =IF(F204="","",IF(I204="SÍ",F204*'Configuración'!$C$5,0)) | J204: =IF(F204="","",IF(H204="SÍ",'Configuración'!$C$6,0)) | K204: =IF(F204="","",F204-G204-J204) | L204: =IF(F204="","",K204-E204-IF(N204="",0,N204)) | M204: =IF(F204="","",IF(K204=0,0,L204/K204))

Sheet Marzo 2026 - Resumen
A1: ÁVILA MUSIC - RESUMEN FINANCIERO MENSUAL
A2: ='Configuración'!C20&" "&'Configuración'!C21 -> Abril 2026
A4: RESUMEN DE INGRESOS
B6: Ventas Totales (USD) | C6: ='Marzo 2026 - Ventas'!F64 -> 436.09
B7: (-) Comisiones MercadoLibre | C7: ='Marzo 2026 - Ventas'!G64 -> 44.7293
B8: (-) Costos de Envío | C8: ='Marzo 2026 - Ventas'!J64 -> 70.2
B9: Ingreso Neto (lo que recibes) | C9: ='Marzo 2026 - Ventas'!K64 -> 321.1607
B10: (-) Costo Total de Mercancía | C10: ='Marzo 2026 - Ventas'!E64 -> 76.72
B11: GANANCIA BRUTA | C11: ='Marzo 2026 - Ventas'!L64 -> 230.4507
A13: ANÁLISIS DE GANANCIA
B15: Ingreso Neto (USD) | C15: =C9 -> 321.1607 | E15: Lo que recibes después de comisiones y envíos
B16: Ganancia Bruta (USD) | C16: =C11 -> 230.4507 | E16: Ventas netas menos costo de mercancía
B17: (-) Costo de Mercancía (USD) | C17: =C10 -> 76.72
B18: GANANCIA NETA (USD) | C18: =C15-C10 -> 244.4407
A21: DISTRIBUCIÓN DE GANANCIA REAL
B23: Ganancia Neta del Mes | C23: =C18 -> 244.4407
B24: → Para Reinversión | C24: =IF(C23>0,C23*'Configuración'!$C$14,0) -> 171.10849 | D24: ='Configuración'!$C$14 -> 0.7 | E24: Para comprar más inventario
B25: → Tu Sueldo / Ganancia Personal | C25: =IF(C23>0,C23*'Configuración'!$C$15,0) -> 73.33221 | D25: ='Configuración'!$C$15 -> 0.3 | E25: Disponible para ti o para decisiones
A27: INDICADORES CLAVE (KPIs)
B29: Total de ventas del mes | C29: ='Marzo 2026 - Ventas'!C66 -> 60 | E29: Cantidad de transacciones
B30: Ticket promedio (USD) | C30: =IF(C29>0,C6/C29,0) -> 7.2681667 | E30: Venta promedio por transacción
B31: Ganancia neta promedio por venta | C31: =IF(C29>0,C18/C29,0) -> 4.0740117 | E31: Cuánto ganas en promedio por venta
B32: Margen neto real (%) | C32: =IF(C9=0,0,C18/C9) -> 0.76111648 | E32: % ganancia real sobre ingreso neto
B33: Total pagado a ML (comisiones + envíos) | C33: ='Marzo 2026 - Ventas'!G64+'Marzo 2026 - Ventas'!J64 -> 114.9293 | E33: Lo que le pagas a MercadoLibre
B34: ROI del mes (%) | C34: =IF(C10=0,0,C18/C10) -> 3.1861405 | E34: Retorno sobre inversión en inventario
A36: SEMÁFORO DE SALUD DEL NEGOCIO
B38: ¿Recuperaste la inversión? | C38: =IF(C29=0,"—",IF(C18>0,"✅ SÍ","❌ NO")) -> ✅ SÍ | E38: Ganancia real positiva
B39: ¿El negocio se autosostiene? | C39: =IF(C29=0,"—",IF(C24>0,"✅ SÍ","❌ NO")) -> ✅ SÍ | E39: Hay fondos para reinversión
B40: ¿Genera sueldo para ti? | C40: =IF(C29=0,"—",IF(C25>0,"✅ SÍ","❌ NO")) -> ✅ SÍ | E40: Hay ganancia personal disponible
B41: ¿Superaste 50 ventas? | C41: =IF(C29>=50,"✅ SÍ — ¡Baja tu tarifa de envío!","❌ NO — Aún no") -> ✅ SÍ — ¡Baja tu tarifa de envío! | E41: Meta para reducir costo de envío

Sheet Febrero 2026 - Ventas
A1: ÁVILA MUSIC - REGISTRO DE VENTAS DETALLADO
A2: ='Configuración'!C17&" "&'Configuración'!C18
A4: # | B4: Fecha | C4: Producto | D4: Categoría | E4: Costo USD | F4: Precio Venta USD | G4: Comisión ML | H4: Envío Gratis | I4: Comisión ML | J4: Costo Envío USD | K4: Ingreso Neto USD | L4: Ganancia Bruta USD | M4: Margen % | N4: Descuento USD
A5: 1 | B5: 46056 | C5: Cuerdas Alice Electrica SL | D5: =IFERROR(VLOOKUP(C5,'Catálogo Productos'!$B$3:$E$53,2,0),"") -> Guitarra Electrica | E5: =IFERROR(VLOOKUP(C5,'Catálogo Productos'!$B$3:$E$53,3,0),"") -> 1.21 | F5: =IFERROR(VLOOKUP(C5,'Catálogo Productos'!$B$3:$E$53,4,0),"") -> 5.49 | G5: =IF(F5="","",IF(I5="SÍ",F5*'Configuración'!$C$5,0)) -> 0.6039 | H5: SÍ | I5: SÍ | J5: =IF(F5="","",IF(H5="SÍ",'Configuración'!$C$6,0)) -> 1.3 | K5: =IF(F5="","",F5-G5-J5) -> 3.5861 | L5: =IF(F5="","",K5-E5-IF(N5="",0,N5)) -> 2.3761 | M5: =IF(F5="","",IF(K5=0,0,L5/K5)) -> 0.6625861
A6: 2 | B6: 46056 | C6: Clavijas Guitarra Clasica Doradas | D6: =IFERROR(VLOOKUP(C6,'Catálogo Productos'!$B$3:$E$53,2,0),"") -> Guitarra Clasica | E6: =IFERROR(VLOOKUP(C6,'Catálogo Productos'!$B$3:$E$53,3,0),"") -> 2.5 | F6: =IFERROR(VLOOKUP(C6,'Catálogo Productos'!$B$3:$E$53,4,0),"") -> 9.99 | G6: =IF(F6="","",IF(I6="SÍ",F6*'Configuración'!$C$5,0)) -> 1.0989 | H6: SÍ | I6: SÍ | J6: =IF(F6="","",IF(H6="SÍ",'Configuración'!$C$6,0)) -> 1.3 | K6: =IF(F6="","",F6-G6-J6) -> 7.5911 | L6: =IF(F6="","",K6-E6-IF(N6="",0,N6)) -> 5.0911 | M6: =IF(F6="","",IF(K6=0,0,L6/K6)) -> 0.67066697
A7: 3 | B7: 46057 | C7: Cuerdas Alice Electrica L | D7: =IFERROR(VLOOKUP(C7,'Catálogo Productos'!$B$3:$E$53,2,0),"") -> Guitarra Electrica | E7: =IFERROR(VLOOKUP(C7,'Catálogo Productos'!$B$3:$E$53,3,0),"") -> 1.21 | F7: =IFERROR(VLOOKUP(C7,'Catálogo Productos'!$B$3:$E$53,4,0),"") -> 5.49 | G7: =IF(F7="","",IF(I7="SÍ",F7*'Configuración'!$C$5,0)) -> 0.6039 | H7: SÍ | I7: SÍ | J7: =IF(F7="","",IF(H7="SÍ",'Configuración'!$C$6,0)) -> 1.3 | K7: =IF(F7="","",F7-G7-J7) -> 3.5861 | L7: =IF(F7="","",K7-E7-IF(N7="",0,N7)) -> 2.3761 | M7: =IF(F7="","",IF(K7=0,0,L7/K7)) -> 0.6625861
A8: 4 | B8: 46057 | C8: Cuerdas Alice Electrica SL | D8: =IFERROR(VLOOKUP(C8,'Catálogo Productos'!$B$3:$E$53,2,0),"") -> Guitarra Electrica | E8: =IFERROR(VLOOKUP(C8,'Catálogo Productos'!$B$3:$E$53,3,0),"") -> 1.21 | F8: =IFERROR(VLOOKUP(C8,'Catálogo Productos'!$B$3:$E$53,4,0),"") -> 5.49 | G8: =IF(F8="","",IF(I8="SÍ",F8*'Configuración'!$C$5,0)) -> 0.6039 | H8: SÍ | I8: SÍ | J8: =IF(F8="","",IF(H8="SÍ",'Configuración'!$C$6,0)) -> 1.3 | K8: =IF(F8="","",F8-G8-J8) -> 3.5861 | L8: =IF(F8="","",K8-E8-IF(N8="",0,N8)) -> 2.3761 | M8: =IF(F8="","",IF(K8=0,0,L8/K8)) -> 0.6625861
A9: 5 | B9: 46057 | C9: Cuerdas Alice Electrica L | D9: =IFERROR(VLOOKUP(C9,'Catálogo Productos'!$B$3:$E$53,2,0),"") -> Guitarra Electrica | E9: =IFERROR(VLOOKUP(C9,'Catálogo Productos'!$B$3:$E$53,3,0),"") -> 1.21 | F9: =IFERROR(VLOOKUP(C9,'Catálogo Productos'!$B$3:$E$53,4,0),"") -> 5.49 | G9: =IF(F9="","",IF(I9="SÍ",F9*'Configuración'!$C$5,0)) -> 0.6039 | H9: SÍ | I9: SÍ | J9: =IF(F9="","",IF(H9="SÍ",'Configuración'!$C$6,0)) -> 1.3 | K9: =IF(F9="","",F9-G9-J9) -> 3.5861 | L9: =IF(F9="","",K9-E9-IF(N9="",0,N9)) -> 2.3761 | M9: =IF(F9="","",IF(K9=0,0,L9/K9)) -> 0.6625861
A10: 6 | B10: 46057 | C10: Hombrera Violin 3/4 4/4 | D10: =IFERROR(VLOOKUP(C10,'Catálogo Productos'!$B$3:$E$53,2,0),"") -> Violin | E10: =IFERROR(VLOOKUP(C10,'Catálogo Productos'!$B$3:$E$53,3,0),"") -> 2.69 | F10: =IFERROR(VLOOKUP(C10,'Catálogo Productos'!$B$3:$E$53,4,0),"") -> 11 | G10: =IF(F10="","",IF(I10="SÍ",F10*'Configuración'!$C$5,0)) -> 1.21 | H10: SÍ | I10: SÍ | J10: =IF(F10="","",IF(H10="SÍ",'Configuración'!$C$6,0)) -> 1.3 | K10: =IF(F10="","",F10-G10-J10) -> 8.49 | L10: =IF(F10="","",K10-E10-IF(N10="",0,N10)) -> 5.8 | M10: =IF(F10="","",IF(K10=0,0,L10/K10)) -> 0.68315665
A11: 7 | B11: 46057 | C11: Cuerdas Alice Electrica SL | D11: =IFERROR(VLOOKUP(C11,'Catálogo Productos'!$B$3:$E$53,2,0),"") -> Guitarra Electrica | E11: =IFERROR(VLOOKUP(C11,'Catálogo Productos'!$B$3:$E$53,3,0),"") -> 1.21 | F11: =IFERROR(VLOOKUP(C11,'Catálogo Productos'!$B$3:$E$53,4,0),"") -> 5.49 | G11: =IF(F11="","",IF(I11="SÍ",F11*'Configuración'!$C$5,0)) -> 0.6039 | H11: SÍ | I11: SÍ | J11: =IF(F11="","",IF(H11="SÍ",'Configuración'!$C$6,0)) -> 1.3 | K11: =IF(F11="","",F11-G11-J11) -> 3.5861 | L11: =IF(F11="","",K11-E11-IF(N11="",0,N11)) -> 2.3761 | M11: =IF(F11="","",IF(K11=0,0,L11/K11)) -> 0.6625861
A12: 8 | B12: 46057 | C12: Clavijas Guitarra Clasica Doradas | D12: =IFERROR(VLOOKUP(C12,'Catálogo Productos'!$B$3:$E$53,2,0),"") -> Guitarra Clasica | E12: =IFERROR(VLOOKUP(C12,'Catálogo Productos'!$B$3:$E$53,3,0),"") -> 2.5 | F12: =IFERROR(VLOOKUP(C12,'Catálogo Productos'!$B$3:$E$53,4,0),"") -> 9.99 | G12: =IF(F12="","",IF(I12="SÍ",F12*'Configuración'!$C$5,0)) -> 1.0989 | H12: SÍ | I12: SÍ | J12: =IF(F12="","",IF(H12="SÍ",'Configuración'!$C$6,0)) -> 1.3 | K12: =IF(F12="","",F12-G12-J12) -> 7.5911 | L12: =IF(F12="","",K12-E12-IF(N12="",0,N12)) -> 5.0911 | M12: =IF(F12="","",IF(K12=0,0,L12/K12)) -> 0.67066697
A13: 9 | B13: 46057 | C13: Cuerdas Alice Clasica A106 | D13: =IFERROR(VLOOKUP(C13,'Catálogo Productos'!$B$3:$E$53,2,0),"") -> Guitarra Clasica | E13: =IFERROR(VLOOKUP(C13,'Catálogo Productos'!$B$3:$E$53,3,0),"") -> 1.21 | F13: =IFERROR(VLOOKUP(C13,'Catálogo Productos'!$B$3:$E$53,4,0),"") -> 5.49 | G13: =IF(F13="","",IF(I13="SÍ",F13*'Configuración'!$C$5,0)) -> 0.6039 | H13: SÍ | I13: SÍ | J13: =IF(F13="","",IF(H13="SÍ",'Configuración'!$C$6,0)) -> 1.3 | K13: =IF(F13="","",F13-G13-J13) -> 3.5861 | L13: =IF(F13="","",K13-E13-IF(N13="",0,N13)) -> 2.3761 | M13: =IF(F13="","",IF(K13=0,0,L13/K13)) -> 0.6625861
A14: 10 | B14: 46057 | C14: Correa Guitarra/Bajo | D14: =IFERROR(VLOOKUP(C14,'Catálogo Productos'!$B$3:$E$53,2,0),"") -> Correas | E14: =IFERROR(VLOOKUP(C14,'Catálogo Productos'!$B$3:$E$53,3,0),"") -> 0.2 | F14: =IFERROR(VLOOKUP(C14,'Catálogo Productos'!$B$3:$E$53,4,0),"") -> 5.49 | G14: =IF(F14="","",IF(I14="SÍ",F14*'Configuración'!$C$5,0)) -> 0.6039 | H14: SÍ | I14: SÍ | J14: =IF(F14="","",IF(H14="SÍ",'Configuración'!$C$6,0)) -> 1.3 | K14: =IF(F14="","",F14-G14-J14) -> 3.5861 | L14: =IF(F14="","",K14-E14-IF(N14="",0,N14)) -> 3.3861 | M14: =IF(F14="","",IF(K14=0,0,L14/K14)) -> 0.94422911
A15: 11 | B15: 46057 | C15: Hombrera Violin 3/4 4/4 | D15: =IFERROR(VLOOKUP(C15,'Catálogo Productos'!$B$3:$E$53,2,0),"") -> Violin | E15: =IFERROR(VLOOKUP(C15,'Catálogo Productos'!$B$3:$E$53,3,0),"") -> 2.69 | F15: =IFERROR(VLOOKUP(C15,'Catálogo Productos'!$B$3:$E$53,4,0),"") -> 11 | G15: =IF(F15="","",IF(I15="SÍ",F15*'Configuración'!$C$5,0)) -> 1.21 | H15: SÍ | I15: SÍ | J15: =IF(F15="","",IF(H15="SÍ",'Configuración'!$C$6,0)) -> 1.3 | K15: =IF(F15="","",F15-G15-J15) -> 8.49 | L15: =IF(F15="","",K15-E15-IF(N15="",0,N15)) -> 5.8 | M15: =IF(F15="","",IF(K15=0,0,L15/K15)) -> 0.68315665
A16: 12 | B16: 46057 | C16: Correa Guitarra/Bajo | D16: =IFERROR(VLOOKUP(C16,'Catálogo Productos'!$B$3:$E$53,2,0),"") -> Correas | E16: =IFERROR(VLOOKUP(C16,'Catálogo Productos'!$B$3:$E$53,3,0),"") -> 0.2 | F16: =IFERROR(VLOOKUP(C16,'Catálogo Productos'!$B$3:$E$53,4,0),"") -> 5.49 | G16: =IF(F16="","",IF(I16="SÍ",F16*'Configuración'!$C$5,0)) -> 0.6039 | H16: SÍ | I16: SÍ | J16: =IF(F16="","",IF(H16="SÍ",'Configuración'!$C$6,0)) -> 1.3 | K16: =IF(F16="","",F16-G16-J16) -> 3.5861 | L16: =IF(F16="","",K16-E16-IF(N16="",0,N16)) -> 3.3861 | M16: =IF(F16="","",IF(K16=0,0,L16/K16)) -> 0.94422911
... A41: 37 | B41: 46057 | C41: Clavijas de Bajo Mariposa Detallado | D41: =IFERROR(VLOOKUP(C41,'Catálogo Productos'!$B$3:$E$53,2,0),"") -> Bajo | E41: =IFERROR(VLOOKUP(C41,'Catálogo Productos'!$B$3:$E$53,3,0),"") -> 2 | F41: =IFERROR(VLOOKUP(C41,'Catálogo Productos'!$B$3:$E$53,4,0),"") -> 10 | G41: =IF(F41="","",IF(I41="SÍ",F41*'Configuración'!$C$5,0)) -> 1.1 | H41: SÍ | I41: SÍ | J41: =IF(F41="","",IF(H41="SÍ",'Configuración'!$C$6,0)) -> 1.3 | K41: =IF(F41="","",F41-G41-J41) -> 7.6 | L41: =IF(F41="","",K41-E41-IF(N41="",0,N41)) -> 5.6 | M41: =IF(F41="","",IF(K41=0,0,L41/K41)) -> 0.73684211
A42: 38 | D42: =IFERROR(VLOOKUP(C42,'Catálogo Productos'!$B$3:$E$53,2,0),"") | E42: =IFERROR(VLOOKUP(C42,'Catálogo Productos'!$B$3:$E$53,3,0),"") | F42: =IFERROR(VLOOKUP(C42,'Catálogo Productos'!$B$3:$E$53,4,0),"") | G42: =IF(F42="","",IF(I42="SÍ",F42*'Configuración'!$C$5,0)) | J42: =IF(F42="","",IF(H42="SÍ",'Configuración'!$C$6,0)) | K42: =IF(F42="","",F42-G42-J42) | L42: =IF(F42="","",K42-E42-IF(N42="",0,N42)) | M42: =IF(F42="","",IF(K42=0,0,L42/K42))
A43: 39 | D43: =IFERROR(VLOOKUP(C43,'Catálogo Productos'!$B$3:$E$53,2,0),"") | E43: =IFERROR(VLOOKUP(C43,'Catálogo Productos'!$B$3:$E$53,3,0),"") | F43: =IFERROR(VLOOKUP(C43,'Catálogo Productos'!$B$3:$E$53,4,0),"") | G43: =IF(F43="","",IF(I43="SÍ",F43*'Configuración'!$C$5,0)) | J43: =IF(F43="","",IF(H43="SÍ",'Configuración'!$C$6,0)) | K43: =IF(F43="","",F43-G43-J43) | L43: =IF(F43="","",K43-E43-IF(N43="",0,N43)) | M43: =IF(F43="","",IF(K43=0,0,L43/K43))
A44: 40 | D44: =IFERROR(VLOOKUP(C44,'Catálogo Productos'!$B$3:$E$53,2,0),"") | E44: =IFERROR(VLOOKUP(C44,'Catálogo Productos'!$B$3:$E$53,3,0),"") | F44: =IFERROR(VLOOKUP(C44,'Catálogo Productos'!$B$3:$E$53,4,0),"") | G44: =IF(F44="","",IF(I44="SÍ",F44*'Configuración'!$C$5,0)) | J44: =IF(F44="","",IF(H44="SÍ",'Configuración'!$C$6,0)) | K44: =IF(F44="","",F44-G44-J44) | L44: =IF(F44="","",K44-E44-IF(N44="",0,N44)) | M44: =IF(F44="","",IF(K44=0,0,L44/K44))
A45: 41 | D45: =IFERROR(VLOOKUP(C45,'Catálogo Productos'!$B$3:$E$53,2,0),"") | E45: =IFERROR(VLOOKUP(C45,'Catálogo Productos'!$B$3:$E$53,3,0),"") | F45: =IFERROR(VLOOKUP(C45,'Catálogo Productos'!$B$3:$E$53,4,0),"") | G45: =IF(F45="","",IF(I45="SÍ",F45*'Configuración'!$C$5,0)) | J45: =IF(F45="","",IF(H45="SÍ",'Configuración'!$C$6,0)) | K45: =IF(F45="","",F45-G45-J45) | L45: =IF(F45="","",K45-E45-IF(N45="",0,N45)) | M45: =IF(F45="","",IF(K45=0,0,L45/K45))
A46: 42 | D46: =IFERROR(VLOOKUP(C46,'Catálogo Productos'!$B$3:$E$53,2,0),"") | E46: =IFERROR(VLOOKUP(C46,'Catálogo Productos'!$B$3:$E$53,3,0),"") | F46: =IFERROR(VLOOKUP(C46,'Catálogo Productos'!$B$3:$E$53,4,0),"") | G46: =IF(F46="","",IF(I46="SÍ",F46*'Configuración'!$C$5,0)) | J46: =IF(F46="","",IF(H46="SÍ",'Configuración'!$C$6,0)) | K46: =IF(F46="","",F46-G46-J46) | L46: =IF(F46="","",K46-E46-IF(N46="",0,N46)) | M46: =IF(F46="","",IF(K46=0,0,L46/K46))
A47: 43 | D47: =IFERROR(VLOOKUP(C47,'Catálogo Productos'!$B$3:$E$53,2,0),"") | E47: =IFERROR(VLOOKUP(C47,'Catálogo Productos'!$B$3:$E$53,3,0),"") | F47: =IFERROR(VLOOKUP(C47,'Catálogo Productos'!$B$3:$E$53,4,0),"") | G47: =IF(F47="","",IF(I47="SÍ",F47*'Configuración'!$C$5,0)) | J47: =IF(F47="","",IF(H47="SÍ",'Configuración'!$C$6,0)) | K47: =IF(F47="","",F47-G47-J47) | L47: =IF(F47="","",K47-E47-IF(N47="",0,N47)) | M47: =IF(F47="","",IF(K47=0,0,L47/K47))
A48: 44 | D48: =IFERROR(VLOOKUP(C48,'Catálogo Productos'!$B$3:$E$53,2,0),"") | E48: =IFERROR(VLOOKUP(C48,'Catálogo Productos'!$B$3:$E$53,3,0),"") | F48: =IFERROR(VLOOKUP(C48,'Catálogo Productos'!$B$3:$E$53,4,0),"") | G48: =IF(F48="","",IF(I48="SÍ",F48*'Configuración'!$C$5,0)) | J48: =IF(F48="","",IF(H48="SÍ",'Configuración'!$C$6,0)) | K48: =IF(F48="","",F48-G48-J48) | L48: =IF(F48="","",K48-E48-IF(N48="",0,N48)) | M48: =IF(F48="","",IF(K48=0,0,L48/K48))
A49: 45 | D49: =IFERROR(VLOOKUP(C49,'Catálogo Productos'!$B$3:$E$53,2,0),"") | E49: =IFERROR(VLOOKUP(C49,'Catálogo Productos'!$B$3:$E$53,3,0),"") | F49: =IFERROR(VLOOKUP(C49,'Catálogo Productos'!$B$3:$E$53,4,0),"") | G49: =IF(F49="","",IF(I49="SÍ",F49*'Configuración'!$C$5,0)) | J49: =IF(F49="","",IF(H49="SÍ",'Configuración'!$C$6,0)) | K49: =IF(F49="","",F49-G49-J49) | L49: =IF(F49="","",K49-E49-IF(N49="",0,N49)) | M49: =IF(F49="","",IF(K49=0,0,L49/K49))
A50: 46 | D50: =IFERROR(VLOOKUP(C50,'Catálogo Productos'!$B$3:$E$53,2,0),"") | E50: =IFERROR(VLOOKUP(C50,'Catálogo Productos'!$B$3:$E$53,3,0),"") | F50: =IFERROR(VLOOKUP(C50,'Catálogo Productos'!$B$3:$E$53,4,0),"") | G50: =IF(F50="","",IF(I50="SÍ",F50*'Configuración'!$C$5,0)) | J50: =IF(F50="","",IF(H50="SÍ",'Configuración'!$C$6,0)) | K50: =IF(F50="","",F50-G50-J50) | L50: =IF(F50="","",K50-E50-IF(N50="",0,N50)) | M50: =IF(F50="","",IF(K50=0,0,L50/K50))
A51: 47 | D51: =IFERROR(VLOOKUP(C51,'Catálogo Productos'!$B$3:$E$53,2,0),"") | E51: =IFERROR(VLOOKUP(C51,'Catálogo Productos'!$B$3:$E$53,3,0),"") | F51: =IFERROR(VLOOKUP(C51,'Catálogo Productos'!$B$3:$E$53,4,0),"") | G51: =IF(F51="","",IF(I51="SÍ",F51*'Configuración'!$C$5,0)) | J51: =IF(F51="","",IF(H51="SÍ",'Configuración'!$C$6,0)) | K51: =IF(F51="","",F51-G51-J51) | L51: =IF(F51="","",K51-E51-IF(N51="",0,N51)) | M51: =IF(F51="","",IF(K51=0,0,L51/K51))
A52: 48 | D52: =IFERROR(VLOOKUP(C52,'Catálogo Productos'!$B$3:$E$53,2,0),"") | E52: =IFERROR(VLOOKUP(C52,'Catálogo Productos'!$B$3:$E$53,3,0),"") | F52: =IFERROR(VLOOKUP(C52,'Catálogo Productos'!$B$3:$E$53,4,0),"") | G52: =IF(F52="","",IF(I52="SÍ",F52*'Configuración'!$C$5,0)) | H52: SÍ | I52: SÍ | J52: =IF(F52="","",IF(H52="SÍ",'Configuración'!$C$6,0)) | K52: =IF(F52="","",F52-G52-J52) | L52: =IF(F52="","",K52-E52-IF(N52="",0,N52)) | M52: =IF(F52="","",IF(K52=0,0,L52/K52))
A53: 49 | D53: =IFERROR(VLOOKUP(C53,'Catálogo Productos'!$B$3:$E$53,2,0),"") | E53: =IFERROR(VLOOKUP(C53,'Catálogo Productos'!$B$3:$E$53,3,0),"") | F53: =IFERROR(VLOOKUP(C53,'Catálogo Productos'!$B$3:$E$53,4,0),"") | G53: =IF(F53="","",IF(I53="SÍ",F53*'Configuración'!$C$5,0)) | H53: SÍ | I53: SÍ | J53: =IF(F53="","",IF(H53="SÍ",'Configuración'!$C$6,0)) | K53: =IF(F53="","",F53-G53-J53) | L53: =IF(F53="","",K53-E53-IF(N53="",0,N53)) | M53: =IF(F53="","",IF(K53=0,0,L53/K53))
A54: 50 | D54: =IFERROR(VLOOKUP(C54,'Catálogo Productos'!$B$3:$E$53,2,0),"") | E54: =IFERROR(VLOOKUP(C54,'Catálogo Productos'!$B$3:$E$53,3,0),"") | F54: =IFERROR(VLOOKUP(C54,'Catálogo Productos'!$B$3:$E$53,4,0),"") | G54: =IF(F54="","",IF(I54="SÍ",F54*'Configuración'!$C$5,0)) | H54: SÍ | I54: SÍ | J54: =IF(F54="","",IF(H54="SÍ",'Configuración'!$C$6,0)) | K54: =IF(F54="","",F54-G54-J54) | L54: =IF(F54="","",K54-E54-IF(N54="",0,N54)) | M54: =IF(F54="","",IF(K54=0,0,L54/K54))
A55: TOTALES DEL MES | E55: =SUM(E5:E204) -> #REF! | F55: =SUM(F5:F204) -> #REF! | G55: =SUM(G5:G204) -> #REF! | J55: =SUM(J5:J204) -> #REF! | K55: =SUM(K5:K204) -> #REF! | L55: =SUM(L5:L204) -> #REF! | M55: =IF(K55=0,0,L55/K55) -> #REF! | N55: =SUM(N5:N204) -> #REF!
C57: =COUNTA(B5:B204) -> 37
A59: 55 | D59: =IFERROR(VLOOKUP(C59,'Catálogo Productos'!$B$3:$E$53,2,0),"") | E59: =IFERROR(VLOOKUP(C59,'Catálogo Productos'!$B$3:$E$53,3,0),"") | F59: =IFERROR(VLOOKUP(C59,'Catálogo Productos'!$B$3:$E$53,4,0),"") | G59: =IF(F59="","",IF(I59="SÍ",F59*'Configuración'!$C$5,0)) | J59: =IF(F59="","",IF(H59="SÍ",'Configuración'!$C$6,0)) | K59: =IF(F59="","",F59-G59-J59) | L59: =IF(F59="","",K59-E59-IF(N59="",0,N59)) | M59: =IF(F59="","",IF(K59=0,0,L59/K59))
A60: 56 | D60: =IFERROR(VLOOKUP(C60,'Catálogo Productos'!$B$3:$E$53,2,0),"") | E60: =IFERROR(VLOOKUP(C60,'Catálogo Productos'!$B$3:$E$53,3,0),"") | F60: =IFERROR(VLOOKUP(C60,'Catálogo Productos'!$B$3:$E$53,4,0),"") | G60: =IF(F60="","",IF(I60="SÍ",F60*'Configuración'!$C$5,0)) | J60: =IF(F60="","",IF(H60="SÍ",'Configuración'!$C$6,0)) | K60: =IF(F60="","",F60-G60-J60) | L60: =IF(F60="","",K60-E60-IF(N60="",0,N60)) | M60: =IF(F60="","",IF(K60=0,0,L60/K60))
A61: 57 | D61: =IFERROR(VLOOKUP(C61,'Catálogo Productos'!$B$3:$E$53,2,0),"") | E61: =IFERROR(VLOOKUP(C61,'Catálogo Productos'!$B$3:$E$53,3,0),"") | F61: =IFERROR(VLOOKUP(C61,'Catálogo Productos'!$B$3:$E$53,4,0),"") | G61: =IF(F61="","",IF(I61="SÍ",F61*'Configuración'!$C$5,0)) | J61: =IF(F61="","",IF(H61="SÍ",'Configuración'!$C$6,0)) | K61: =IF(F61="","",F61-G61-J61) | L61: =IF(F61="","",K61-E61-IF(N61="",0,N61)) | M61: =IF(F61="","",IF(K61=0,0,L61/K61))
A62: 58 | D62: =IFERROR(VLOOKUP(C62,'Catálogo Productos'!$B$3:$E$53,2,0),"") | E62: =IFERROR(VLOOKUP(C62,'Catálogo Productos'!$B$3:$E$53,3,0),"") | F62: =IFERROR(VLOOKUP(C62,'Catálogo Productos'!$B$3:$E$53,4,0),"") | G62: =IF(F62="","",IF(I62="SÍ",F62*'Configuración'!$C$5,0)) | J62: =IF(F62="","",IF(H62="SÍ",'Configuración'!$C$6,0)) | K62: =IF(F62="","",F62-G62-J62) | L62: =IF(F62="","",K62-E62-IF(N62="",0,N62)) | M62: =IF(F62="","",IF(K62=0,0,L62/K62))
A63: 59 | D63: =IFERROR(VLOOKUP(C63,'Catálogo Productos'!$B$3:$E$53,2,0),"") | E63: =IFERROR(VLOOKUP(C63,'Catálogo Productos'!$B$3:$E$53,3,0),"") | F63: =IFERROR(VLOOKUP(C63,'Catálogo Productos'!$B$3:$E$53,4,0),"") | G63: =IF(F63="","",IF(I63="SÍ",F63*'Configuración'!$C$5,0)) | J63: =IF(F63="","",IF(H63="SÍ",'Configuración'!$C$6,0)) | K63: =IF(F63="","",F63-G63-J63) | L63: =IF(F63="","",K63-E63-IF(N63="",0,N63)) | M63: =IF(F63="","",IF(K63=0,0,L63/K63))
A64: 60 | D64: =IFERROR(VLOOKUP(C64,'Catálogo Productos'!$B$3:$E$53,2,0),"") | E64: =IFERROR(VLOOKUP(C64,'Catálogo Productos'!$B$3:$E$53,3,0),"") | F64: =IFERROR(VLOOKUP(C64,'Catálogo Productos'!$B$3:$E$53,4,0),"") | G64: =IF(F64="","",IF(I64="SÍ",F64*'Configuración'!$C$5,0)) | J64: =IF(F64="","",IF(H64="SÍ",'Configuración'!$C$6,0)) | K64: =IF(F64="","",F64-G64-J64) | L64: =IF(F64="","",K64-E64-IF(N64="",0,N64)) | M64: =IF(F64="","",IF(K64=0,0,L64/K64))
A65: 61 | D65: =IFERROR(VLOOKUP(C65,'Catálogo Productos'!$B$3:$E$53,2,0),"") | E65: =IFERROR(VLOOKUP(C65,'Catálogo Productos'!$B$3:$E$53,3,0),"") | F65: =IFERROR(VLOOKUP(C65,'Catálogo Productos'!$B$3:$E$53,4,0),"") | G65: =IF(F65="","",IF(I65="SÍ",F65*'Configuración'!$C$5,0)) | J65: =IF(F65="","",IF(H65="SÍ",'Configuración'!$C$6,0)) | K65: =IF(F65="","",F65-G65-J65) | L65: =IF(F65="","",K65-E65-IF(N65="",0,N65)) | M65: =IF(F65="","",IF(K65=0,0,L65/K65))
A66: 62 | D66: =IFERROR(VLOOKUP(C66,'Catálogo Productos'!$B$3:$E$53,2,0),"") | E66: =IFERROR(VLOOKUP(C66,'Catálogo Productos'!$B$3:$E$53,3,0),"") | F66: =IFERROR(VLOOKUP(C66,'Catálogo Productos'!$B$3:$E$53,4,0),"") | G66: =IF(F66="","",IF(I66="SÍ",F66*'Configuración'!$C$5,0)) | J66: =IF(F66="","",IF(H66="SÍ",'Configuración'!$C$6,0)) | K66: =IF(F66="","",F66-G66-J66) | L66: =IF(F66="","",K66-E66-IF(N66="",0,N66)) | M66: =IF(F66="","",IF(K66=0,0,L66/K66))
A67: 63 | D67: =IFERROR(VLOOKUP(C67,'Catálogo Productos'!$B$3:$E$53,2,0),"") | E67: =IFERROR(VLOOKUP(C67,'Catálogo Productos'!$B$3:$E$53,3,0),"") | F67: =IFERROR(VLOOKUP(C67,'Catálogo Productos'!$B$3:$E$53,4,0),"") | G67: =IF(F67="","",IF(I67="SÍ",F67*'Configuración'!$C$5,0)) | J67: =IF(F67="","",IF(H67="SÍ",'Configuración'!$C$6,0)) | K67: =IF(F67="","",F67-G67-J67) | L67: =IF(F67="","",K67-E67-IF(N67="",0,N67)) | M67: =IF(F67="","",IF(K67=0,0,L67/K67))
A68: 64 | D68: =IFERROR(VLOOKUP(C68,'Catálogo Productos'!$B$3:$E$53,2,0),"") | E68: =IFERROR(VLOOKUP(C68,'Catálogo Productos'!$B$3:$E$53,3,0),"") | F68: =IFERROR(VLOOKUP(C68,'Catálogo Productos'!$B$3:$E$53,4,0),"") | G68: =IF(F68="","",IF(I68="SÍ",F68*'Configuración'!$C$5,0)) | J68: =IF(F68="","",IF(H68="SÍ",'Configuración'!$C$6,0)) | K68: =IF(F68="","",F68-G68-J68) | L68: =IF(F68="","",K68-E68-IF(N68="",0,N68)) | M68: =IF(F68="","",IF(K68=0,0,L68/K68))
A69: 65 | D69: =IFERROR(VLOOKUP(C69,'Catálogo Productos'!$B$3:$E$53,2,0),"") | E69: =IFERROR(VLOOKUP(C69,'Catálogo Productos'!$B$3:$E$53,3,0),"") | F69: =IFERROR(VLOOKUP(C69,'Catálogo Productos'!$B$3:$E$53,4,0),"") | G69: =IF(F69="","",IF(I69="SÍ",F69*'Configuración'!$C$5,0)) | J69: =IF(F69="","",IF(H69="SÍ",'Configuración'!$C$6,0)) | K69: =IF(F69="","",F69-G69-J69) | L69: =IF(F69="","",K69-E69-IF(N69="",0,N69)) | M69: =IF(F69="","",IF(K69=0,0,L69/K69))
A70: 66 | D70: =IFERROR(VLOOKUP(C70,'Catálogo Productos'!$B$3:$E$53,2,0),"") | E70: =IFERROR(VLOOKUP(C70,'Catálogo Productos'!$B$3:$E$53,3,0),"") | F70: =IFERROR(VLOOKUP(C70,'Catálogo Productos'!$B$3:$E$53,4,0),"") | G70: =IF(F70="","",IF(I70="SÍ",F70*'Configuración'!$C$5,0)) | J70: =IF(F70="","",IF(H70="SÍ",'Configuración'!$C$6,0)) | K70: =IF(F70="","",F70-G70-J70) | L70: =IF(F70="","",K70-E70-IF(N70="",0,N70)) | M70: =IF(F70="","",IF(K70=0,0,L70/K70))
... A204: 200 | D204: =IFERROR(VLOOKUP(C204,'Catálogo Productos'!$B$3:$E$53,2,0),"") | E204: =IFERROR(VLOOKUP(C204,'Catálogo Productos'!$B$3:$E$53,3,0),"") | F204: =IFERROR(VLOOKUP(C204,'Catálogo Productos'!$B$3:$E$53,4,0),"") | G204: =IF(F204="","",IF(I204="SÍ",F204*'Configuración'!$C$5,0)) | J204: =IF(F204="","",IF(H204="SÍ",'Configuración'!$C$6,0)) | K204: =IF(F204="","",F204-G204-J204) | L204: =IF(F204="","",K204-E204-IF(N204="",0,N204)) | M204: =IF(F204="","",IF(K204=0,0,L204/K204))

Sheet Febrero 2026 - Resumen
A1: ÁVILA MUSIC - RESUMEN FINANCIERO MENSUAL
A2: ='Configuración'!C20&" "&'Configuración'!C21 -> Abril 2026
A4: RESUMEN DE INGRESOS
B6: Ventas Totales (USD) | C6: ='Febrero 2026 - Ventas'!F55 -> #REF!
B7: (-) Comisiones MercadoLibre | C7: ='Febrero 2026 - Ventas'!G55 -> #REF!
B8: (-) Costos de Envío | C8: ='Febrero 2026 - Ventas'!J55 -> #REF!
B9: Ingreso Neto (lo que recibes) | C9: ='Febrero 2026 - Ventas'!K55 -> #REF!
B10: (-) Costo Total de Mercancía | C10: ='Febrero 2026 - Ventas'!E55 -> #REF!
B11: GANANCIA BRUTA | C11: ='Febrero 2026 - Ventas'!L55 -> #REF!
A13: ANÁLISIS DE GANANCIA
B15: Ingreso Neto (USD) | C15: =C9 -> #REF! | E15: Lo que recibes después de comisiones y envíos
B16: Ganancia Bruta (USD) | C16: =C11 -> #REF! | E16: Ventas netas menos costo de mercancía
B17: (-) Costo de Mercancía (USD) | C17: =C10 -> #REF!
B18: GANANCIA NETA (USD) | C18: =C15-C10 -> #REF!
A21: DISTRIBUCIÓN DE GANANCIA REAL
B23: Ganancia Neta del Mes | C23: =C18 -> #REF!
B24: → Para Reinversión | C24: =IF(C23>0,C23*'Configuración'!$C$14,0) -> #REF! | D24: ='Configuración'!$C$14 -> 0.7 | E24: Para comprar más inventario
B25: → Tu Sueldo / Ganancia Personal | C25: =IF(C23>0,C23*'Configuración'!$C$15,0) -> #REF! | D25: ='Configuración'!$C$15 -> 0.3 | E25: Disponible para ti o para decisiones
A27: INDICADORES CLAVE (KPIs)
B29: Total de ventas del mes | C29: ='Febrero 2026 - Ventas'!C57 -> 37 | E29: Cantidad de transacciones
B30: Ticket promedio (USD) | C30: =IF(C29>0,C6/C29,0) -> #REF! | E30: Venta promedio por transacción
B31: Ganancia neta promedio por venta | C31: =IF(C29>0,C18/C29,0) -> #REF! | E31: Cuánto ganas en promedio por venta
B32: Margen neto real (%) | C32: =IF(C9=0,0,C18/C9) -> #REF! | E32: % ganancia real sobre ingreso neto
B33: Total pagado a ML (comisiones + envíos) | C33: ='Febrero 2026 - Ventas'!G55+'Febrero 2026 - Ventas'!J55 -> #REF! | E33: Lo que le pagas a MercadoLibre
B34: ROI del mes (%) | C34: =IF(C10=0,0,C18/C10) -> #REF! | E34: Retorno sobre inversión en inventario
A36: SEMÁFORO DE SALUD DEL NEGOCIO
B38: ¿Recuperaste la inversión? | C38: =IF(C29=0,"—",IF(C18>0,"✅ SÍ","❌ NO")) -> #REF! | E38: Ganancia real positiva
B39: ¿El negocio se autosostiene? | C39: =IF(C29=0,"—",IF(C24>0,"✅ SÍ","❌ NO")) -> #REF! | E39: Hay fondos para reinversión
B40: ¿Genera sueldo para ti? | C40: =IF(C29=0,"—",IF(C25>0,"✅ SÍ","❌ NO")) -> #REF! | E40: Hay ganancia personal disponible
B41: ¿Superaste 50 ventas? | C41: =IF(C29>=50,"✅ SÍ — ¡Baja tu tarifa de envío!","❌ NO — Aún no") -> ❌ NO — Aún no | E41: Meta para reducir costo de envío

Sheet 📊 Ranking Productos
A1: ÁVILA MUSIC — RANKING DE PRODUCTOS
A2: ="Mes: "&'Configuración'!C19&" "&'Configuración'!C20 -> Mes: Abril
A3: ℹ️ Los datos se toman de "Marzo 2026 - Ventas". Al crear un mes nuevo, actualiza las referencias COUNTIF/SUMIF al nuevo nombre de hoja.
A5: 🏆 RANKING POR PRODUCTO — Ventas del Mes
A6: # | B6: Producto | C6: Categoría | D6: Uds Vendidas | E6: Ingreso Neto USD | F6: Ganancia USD | G6: Margen % | H6: Stock Total | I6: 🚦 Estado
A7: =IF('Catálogo Productos'!B4<>"",COUNTA('Catálogo Productos'!$B$4:$B4),"") -> 1 | B7: =IF('Catálogo Productos'!B4<>"",'Catálogo Productos'!B4,"") -> Cuerdas Alice Clasica A106 | C7: =IF('Catálogo Productos'!B4<>"",'Catálogo Productos'!C4,"") -> Guitarra Clasica | D7: =IF('Catálogo Productos'!B4<>"",COUNTIF('Febrero 2026 - Ventas'!$C$5:$C$63,'Catálogo Productos'!B4)+COUNTIF('Marzo 2026 - Ventas'!$C$5:$C$63,'Catálogo Productos'!B4)+COUNTIF('Abril 2026 - Ventas'!$C$5:$C$166,'Catálogo Productos'!B4),"") -> 32 | E7: =IF('Catálogo Productos'!B4<>"",SUMIF('Febrero 2026 - Ventas'!$C$5:$C$63,'Catálogo Productos'!B4,'Febrero 2026 - Ventas'!$J$5:$J$63)+SUMIF('Marzo 2026 - Ventas'!$C$5:$C$63,'Catálogo Productos'!B4,'Marzo 2026 - Ventas'!$J$5:$J$63)+SUMIF('Abril 2026 - Ventas'!$C$5:$C$166,'Catálogo Productos'!B4,'Abril 2026 - Ventas'!$J$5:$J$166),"") -> 36.4 | F7: =IF('Catálogo Productos'!B4<>"",SUMIF('Febrero 2026 - Ventas'!$C$5:$C$63,'Catálogo Productos'!B4,'Febrero 2026 - Ventas'!$K$5:$K$63)+SUMIF('Marzo 2026 - Ventas'!$C$5:$C$63,'Catálogo Productos'!B4,'Marzo 2026 - Ventas'!$K$5:$K$63)+SUMIF('Abril 2026 - Ventas'!$C$5:$C$166,'Catálogo Productos'!B4,'Abril 2026 - Ventas'!$K$5:$K$166),"") -> 135.663 | G7: =IF(OR(NOT('Catálogo Productos'!B4<>""),E7="",E7=0),"",F7/E7) -> 3.7270055 | H7: =IF('Catálogo Productos'!B4<>"",'Catálogo Productos'!H59,"") -> 125 | I7: =IF('Catálogo Productos'!B4<>"",'Catálogo Productos'!L59,"") -> 🟢 OK
A8: =IF('Catálogo Productos'!B5<>"",COUNTA('Catálogo Productos'!$B$4:$B5),"") -> 2 | B8: =IF('Catálogo Productos'!B5<>"",'Catálogo Productos'!B5,"") -> Cuerdas Alice Electrica SL | C8: =IF('Catálogo Productos'!B5<>"",'Catálogo Productos'!C5,"") -> Guitarra Electrica | D8: =IF('Catálogo Productos'!B5<>"",COUNTIF('Febrero 2026 - Ventas'!$C$5:$C$63,'Catálogo Productos'!B5)+COUNTIF('Marzo 2026 - Ventas'!$C$5:$C$63,'Catálogo Productos'!B5)+COUNTIF('Abril 2026 - Ventas'!$C$5:$C$166,'Catálogo Productos'!B5),"") -> 29 | E8: =IF('Catálogo Productos'!B5<>"",SUMIF('Febrero 2026 - Ventas'!$C$5:$C$63,'Catálogo Productos'!B5,'Febrero 2026 - Ventas'!$J$5:$J$63)+SUMIF('Marzo 2026 - Ventas'!$C$5:$C$63,'Catálogo Productos'!B5,'Marzo 2026 - Ventas'!$J$5:$J$63)+SUMIF('Abril 2026 - Ventas'!$C$5:$C$166,'Catálogo Productos'!B5,'Abril 2026 - Ventas'!$J$5:$J$166),"") -> 26 | F8: =IF('Catálogo Productos'!B5<>"",SUMIF('Febrero 2026 - Ventas'!$C$5:$C$63,'Catálogo Productos'!B5,'Febrero 2026 - Ventas'!$K$5:$K$63)+SUMIF('Marzo 2026 - Ventas'!$C$5:$C$63,'Catálogo Productos'!B5,'Marzo 2026 - Ventas'!$K$5:$K$63)+SUMIF('Abril 2026 - Ventas'!$C$5:$C$166,'Catálogo Productos'!B5,'Abril 2026 - Ventas'!$K$5:$K$166),"") -> 118.7164 | G8: =IF(OR(NOT('Catálogo Productos'!B5<>""),E8="",E8=0),"",F8/E8) -> 4.5660154 | H8: =IF('Catálogo Productos'!B5<>"",'Catálogo Productos'!H60,"") -> 73 | I8: =IF('Catálogo Productos'!B5<>"",'Catálogo Productos'!L60,"") -> 🟢 OK
A9: =IF('Catálogo Productos'!B6<>"",COUNTA('Catálogo Productos'!$B$4:$B6),"") -> 3 | B9: =IF('Catálogo Productos'!B6<>"",'Catálogo Productos'!B6,"") -> Cuerdas Alice Electrica L | C9: =IF('Catálogo Productos'!B6<>"",'Catálogo Productos'!C6,"") -> Guitarra Electrica | D9: =IF('Catálogo Productos'!B6<>"",COUNTIF('Febrero 2026 - Ventas'!$C$5:$C$63,'Catálogo Productos'!B6)+COUNTIF('Marzo 2026 - Ventas'!$C$5:$C$63,'Catálogo Productos'!B6)+COUNTIF('Abril 2026 - Ventas'!$C$5:$C$166,'Catálogo Productos'!B6),"") -> 19 | E9: =IF('Catálogo Productos'!B6<>"",SUMIF('Febrero 2026 - Ventas'!$C$5:$C$63,'Catálogo Productos'!B6,'Febrero 2026 - Ventas'!$J$5:$J$63)+SUMIF('Marzo 2026 - Ventas'!$C$5:$C$63,'Catálogo Productos'!B6,'Marzo 2026 - Ventas'!$J$5:$J$63)+SUMIF('Abril 2026 - Ventas'!$C$5:$C$166,'Catálogo Productos'!B6,'Abril 2026 - Ventas'!$J$5:$J$166),"") -> 18.2 | F9: =IF('Catálogo Productos'!B6<>"",SUMIF('Febrero 2026 - Ventas'!$C$5:$C$63,'Catálogo Productos'!B6,'Febrero 2026 - Ventas'!$K$5:$K$63)+SUMIF('Marzo 2026 - Ventas'!$C$5:$C$63,'Catálogo Productos'!B6,'Marzo 2026 - Ventas'!$K$5:$K$63)+SUMIF('Abril 2026 - Ventas'!$C$5:$C$166,'Catálogo Productos'!B6,'Abril 2026 - Ventas'!$K$5:$K$166),"") -> 111.5515 | G9: =IF(OR(NOT('Catálogo Productos'!B6<>""),E9="",E9=0),"",F9/E9) -> 6.1292033 | H9: =IF('Catálogo Productos'!B6<>"",'Catálogo Productos'!H61,"") -> 72 | I9: =IF('Catálogo Productos'!B6<>"",'Catálogo Productos'!L61,"") -> 🟢 OK
A10: =IF('Catálogo Productos'!B7<>"",COUNTA('Catálogo Productos'!$B$4:$B7),"") -> 4 | B10: =IF('Catálogo Productos'!B7<>"",'Catálogo Productos'!B7,"") -> Cuerdas Alice Folk 11-52 | C10: =IF('Catálogo Productos'!B7<>"",'Catálogo Productos'!C7,"") -> Guitarra Acustica | D10: =IF('Catálogo Productos'!B7<>"",COUNTIF('Febrero 2026 - Ventas'!$C$5:$C$63,'Catálogo Productos'!B7)+COUNTIF('Marzo 2026 - Ventas'!$C$5:$C$63,'Catálogo Productos'!B7)+COUNTIF('Abril 2026 - Ventas'!$C$5:$C$166,'Catálogo Productos'!B7),"") -> 9 | E10: =IF('Catálogo Productos'!B7<>"",SUMIF('Febrero 2026 - Ventas'!$C$5:$C$63,'Catálogo Productos'!B7,'Febrero 2026 - Ventas'!$J$5:$J$63)+SUMIF('Marzo 2026 - Ventas'!$C$5:$C$63,'Catálogo Productos'!B7,'Marzo 2026 - Ventas'!$J$5:$J$63)+SUMIF('Abril 2026 - Ventas'!$C$5:$C$166,'Catálogo Productos'!B7,'Abril 2026 - Ventas'!$J$5:$J$166),"") -> 9.1 | F10: =IF('Catálogo Productos'!B7<>"",SUMIF('Febrero 2026 - Ventas'!$C$5:$C$63,'Catálogo Productos'!B7,'Febrero 2026 - Ventas'!$K$5:$K$63)+SUMIF('Marzo 2026 - Ventas'!$C$5:$C$63,'Catálogo Productos'!B7,'Marzo 2026 - Ventas'!$K$5:$K$63)+SUMIF('Abril 2026 - Ventas'!$C$5:$C$166,'Catálogo Productos'!B7,'Abril 2026 - Ventas'!$K$5:$K$166),"") -> 35.4788 | G10: =IF(OR(NOT('Catálogo Productos'!B7<>""),E10="",E10=0),"",F10/E10) -> 3.8987692 | H10: =IF('Catálogo Productos'!B7<>"",'Catálogo Productos'!H62,"") -> 59 | I10: =IF('Catálogo Productos'!B7<>"",'Catálogo Productos'!L62,"") -> 🟢 OK
A11: =IF('Catálogo Productos'!B8<>"",COUNTA('Catálogo Productos'!$B$4:$B8),"") -> 5 | B11: =IF('Catálogo Productos'!B8<>"",'Catálogo Productos'!B8,"") -> Hombrera Violin 3/4 4/4 | C11: =IF('Catálogo Productos'!B8<>"",'Catálogo Productos'!C8,"") -> Violin | D11: =IF('Catálogo Productos'!B8<>"",COUNTIF('Febrero 2026 - Ventas'!$C$5:$C$63,'Catálogo Productos'!B8)+COUNTIF('Marzo 2026 - Ventas'!$C$5:$C$63,'Catálogo Productos'!B8)+COUNTIF('Abril 2026 - Ventas'!$C$5:$C$166,'Catálogo Productos'!B8),"") -> 12 | E11: =IF('Catálogo Productos'!B8<>"",SUMIF('Febrero 2026 - Ventas'!$C$5:$C$63,'Catálogo Productos'!B8,'Febrero 2026 - Ventas'!$J$5:$J$63)+SUMIF('Marzo 2026 - Ventas'!$C$5:$C$63,'Catálogo Productos'!B8,'Marzo 2026 - Ventas'!$J$5:$J$63)+SUMIF('Abril 2026 - Ventas'!$C$5:$C$166,'Catálogo Productos'!B8,'Abril 2026 - Ventas'!$J$5:$J$166),"") -> 15.6 | F11: =IF('Catálogo Productos'!B8<>"",SUMIF('Febrero 2026 - Ventas'!$C$5:$C$63,'Catálogo Productos'!B8,'Febrero 2026 - Ventas'!$K$5:$K$63)+SUMIF('Marzo 2026 - Ventas'!$C$5:$C$63,'Catálogo Productos'!B8,'Marzo 2026 - Ventas'!$K$5:$K$63)+SUMIF('Abril 2026 - Ventas'!$C$5:$C$166,'Catálogo Productos'!B8,'Abril 2026 - Ventas'!$K$5:$K$166),"") -> 101.88 | G11: =IF(OR(NOT('Catálogo Productos'!B8<>""),E11="",E11=0),"",F11/E11) -> 6.5307692 | H11: =IF('Catálogo Productos'!B8<>"",'Catálogo Productos'!H63,"") -> 32 | I11: =IF('Catálogo Productos'!B8<>"",'Catálogo Productos'!L63,"") -> 🟢 OK
A12: =IF('Catálogo Productos'!B9<>"",COUNTA('Catálogo Productos'!$B$4:$B9),"") -> 6 | B12: =IF('Catálogo Productos'!B9<>"",'Catálogo Productos'!B9,"") -> Clavijas Guitarra Clasica Doradas | C12: =IF('Catálogo Productos'!B9<>"",'Catálogo Productos'!C9,"") -> Guitarra Clasica | D12: =IF('Catálogo Productos'!B9<>"",COUNTIF('Febrero 2026 - Ventas'!$C$5:$C$63,'Catálogo Productos'!B9)+COUNTIF('Marzo 2026 - Ventas'!$C$5:$C$63,'Catálogo Productos'!B9)+COUNTIF('Abril 2026 - Ventas'!$C$5:$C$166,'Catálogo Productos'!B9),"") -> 13 | E12: =IF('Catálogo Productos'!B9<>"",SUMIF('Febrero 2026 - Ventas'!$C$5:$C$63,'Catálogo Productos'!B9,'Febrero 2026 - Ventas'!$J$5:$J$63)+SUMIF('Marzo 2026 - Ventas'!$C$5:$C$63,'Catálogo Productos'!B9,'Marzo 2026 - Ventas'!$J$5:$J$63)+SUMIF('Abril 2026 - Ventas'!$C$5:$C$166,'Catálogo Productos'!B9,'Abril 2026 - Ventas'!$J$5:$J$166),"") -> 14.3 | F12: =IF('Catálogo Productos'!B9<>"",SUMIF('Febrero 2026 - Ventas'!$C$5:$C$63,'Catálogo Productos'!B9,'Febrero 2026 - Ventas'!$K$5:$K$63)+SUMIF('Marzo 2026 - Ventas'!$C$5:$C$63,'Catálogo Productos'!B9,'Marzo 2026 - Ventas'!$K$5:$K$63)+SUMIF('Abril 2026 - Ventas'!$C$5:$C$166,'Catálogo Productos'!B9,'Abril 2026 - Ventas'!$K$5:$K$166),"") -> 101.2843 | G12: =IF(OR(NOT('Catálogo Productos'!B9<>""),E12="",E12=0),"",F12/E12) -> 7.0828182 | H12: =IF('Catálogo Productos'!B9<>"",'Catálogo Productos'!H64,"") -> 15 | I12: =IF('Catálogo Productos'!B9<>"",'Catálogo Productos'!L64,"") -> 🟢 OK
A13: =IF('Catálogo Productos'!B10<>"",COUNTA('Catálogo Productos'!$B$4:$B10),"") -> 7 | B13: =IF('Catálogo Productos'!B10<>"",'Catálogo Productos'!B10,"") -> Clavijas Guitarra Clasica Plateadas | C13: =IF('Catálogo Productos'!B10<>"",'Catálogo Productos'!C10,"") -> Guitarra Clasica | D13: =IF('Catálogo Productos'!B10<>"",COUNTIF('Febrero 2026 - Ventas'!$C$5:$C$63,'Catálogo Productos'!B10)+COUNTIF('Marzo 2026 - Ventas'!$C$5:$C$63,'Catálogo Productos'!B10)+COUNTIF('Abril 2026 - Ventas'!$C$5:$C$166,'Catálogo Productos'!B10),"") -> 5 | E13: =IF('Catálogo Productos'!B10<>"",SUMIF('Febrero 2026 - Ventas'!$C$5:$C$63,'Catálogo Productos'!B10,'Febrero 2026 - Ventas'!$J$5:$J$63)+SUMIF('Marzo 2026 - Ventas'!$C$5:$C$63,'Catálogo Productos'!B10,'Marzo 2026 - Ventas'!$J$5:$J$63)+SUMIF('Abril 2026 - Ventas'!$C$5:$C$166,'Catálogo Productos'!B10,'Abril 2026 - Ventas'!$J$5:$J$166),"") -> 3.9 | F13: =IF('Catálogo Productos'!B10<>"",SUMIF('Febrero 2026 - Ventas'!$C$5:$C$63,'Catálogo Productos'!B10,'Febrero 2026 - Ventas'!$K$5:$K$63)+SUMIF('Marzo 2026 - Ventas'!$C$5:$C$63,'Catálogo Productos'!B10,'Marzo 2026 - Ventas'!$K$5:$K$63)+SUMIF('Abril 2026 - Ventas'!$C$5:$C$166,'Catálogo Productos'!B10,'Abril 2026 - Ventas'!$K$5:$K$166),"") -> 51.0933 | G13: =IF(OR(NOT('Catálogo Productos'!B10<>""),E13="",E13=0),"",F13/E13) -> 13.100846 | H13: =IF('Catálogo Productos'!B10<>"",'Catálogo Productos'!H65,"") -> 10 | I13: =IF('Catálogo Productos'!B10<>"",'Catálogo Productos'!L65,"") -> 🟢 OK
A14: =IF('Catálogo Productos'!B11<>"",COUNTA('Catálogo Productos'!$B$4:$B11),"") -> 8 | B14: =IF('Catálogo Productos'!B11<>"",'Catálogo Productos'!B11,"") -> Correa Guitarra/Bajo | C14: =IF('Catálogo Productos'!B11<>"",'Catálogo Productos'!C11,"") -> Correas | D14: =IF('Catálogo Productos'!B11<>"",COUNTIF('Febrero 2026 - Ventas'!$C$5:$C$63,'Catálogo Productos'!B11)+COUNTIF('Marzo 2026 - Ventas'!$C$5:$C$63,'Catálogo Productos'!B11)+COUNTIF('Abril 2026 - Ventas'!$C$5:$C$166,'Catálogo Productos'!B11),"") -> 16 | E14: =IF('Catálogo Productos'!B11<>"",SUMIF('Febrero 2026 - Ventas'!$C$5:$C$63,'Catálogo Productos'!B11,'Febrero 2026 - Ventas'!$J$5:$J$63)+SUMIF('Marzo 2026 - Ventas'!$C$5:$C$63,'Catálogo Productos'!B11,'Marzo 2026 - Ventas'!$J$5:$J$63)+SUMIF('Abril 2026 - Ventas'!$C$5:$C$166,'Catálogo Productos'!B11,'Abril 2026 - Ventas'!$J$5:$J$166),"") -> 19.5 | F14: =IF('Catálogo Productos'!B11<>"",SUMIF('Febrero 2026 - Ventas'!$C$5:$C$63,'Catálogo Productos'!B11,'Febrero 2026 - Ventas'!$K$5:$K$63)+SUMIF('Marzo 2026 - Ventas'!$C$5:$C$63,'Catálogo Productos'!B11,'Marzo 2026 - Ventas'!$K$5:$K$63)+SUMIF('Abril 2026 - Ventas'!$C$5:$C$166,'Catálogo Productos'!B11,'Abril 2026 - Ventas'!$K$5:$K$166),"") -> 58.6776 | G14: =IF(OR(NOT('Catálogo Productos'!B11<>""),E14="",E14=0),"",F14/E14) -> 3.0091077 | H14: =IF('Catálogo Productos'!B11<>"",'Catálogo Productos'!H66,"") -> 21 | I14: =IF('Catálogo Productos'!B11<>"",'Catálogo Productos'!L66,"") -> 🟢 OK
A15: =IF('Catálogo Productos'!B12<>"",COUNTA('Catálogo Productos'!$B$4:$B12),"") -> 9 | B15: =IF('Catálogo Productos'!B12<>"",'Catálogo Productos'!B12,"") -> Base pared Guitarra/Bajo | C15: =IF('Catálogo Productos'!B12<>"",'Catálogo Productos'!C12,"") -> Bases, Stand, Atriles | D15: =IF('Catálogo Productos'!B12<>"",COUNTIF('Febrero 2026 - Ventas'!$C$5:$C$63,'Catálogo Productos'!B12)+COUNTIF('Marzo 2026 - Ventas'!$C$5:$C$63,'Catálogo Productos'!B12)+COUNTIF('Abril 2026 - Ventas'!$C$5:$C$166,'Catálogo Productos'!B12),"") -> 27 | E15: =IF('Catálogo Productos'!B12<>"",SUMIF('Febrero 2026 - Ventas'!$C$5:$C$63,'Catálogo Productos'!B12,'Febrero 2026 - Ventas'!$J$5:$J$63)+SUMIF('Marzo 2026 - Ventas'!$C$5:$C$63,'Catálogo Productos'!B12,'Marzo 2026 - Ventas'!$J$5:$J$63)+SUMIF('Abril 2026 - Ventas'!$C$5:$C$166,'Catálogo Productos'!B12,'Abril 2026 - Ventas'!$J$5:$J$166),"") -> 20.8 | F15: =IF('Catálogo Productos'!B12<>"",SUMIF('Febrero 2026 - Ventas'!$C$5:$C$63,'Catálogo Productos'!B12,'Febrero 2026 - Ventas'!$K$5:$K$63)+SUMIF('Marzo 2026 - Ventas'!$C$5:$C$63,'Catálogo Productos'!B12,'Marzo 2026 - Ventas'!$K$5:$K$63)+SUMIF('Abril 2026 - Ventas'!$C$5:$C$166,'Catálogo Productos'!B12,'Abril 2026 - Ventas'!$K$5:$K$166),"") -> 102.952 | G15: =IF(OR(NOT('Catálogo Productos'!B12<>""),E15="",E15=0),"",F15/E15) -> 4.9496154 | H15: =IF('Catálogo Productos'!B12<>"",'Catálogo Productos'!H67,"") -> 58 | I15: =IF('Catálogo Productos'!B12<>"",'Catálogo Productos'!L67,"") -> 🟢 OK
A16: =IF('Catálogo Productos'!B13<>"",COUNTA('Catálogo Productos'!$B$4:$B13),"") -> 10 | B16: =IF('Catálogo Productos'!B13<>"",'Catálogo Productos'!B13,"") -> Capotraste | C16: =IF('Catálogo Productos'!B13<>"",'Catálogo Productos'!C13,"") -> Capostraste | D16: =IF('Catálogo Productos'!B13<>"",COUNTIF('Febrero 2026 - Ventas'!$C$5:$C$63,'Catálogo Productos'!B13)+COUNTIF('Marzo 2026 - Ventas'!$C$5:$C$63,'Catálogo Productos'!B13)+COUNTIF('Abril 2026 - Ventas'!$C$5:$C$166,'Catálogo Productos'!B13),"") -> 8 | E16: =IF('Catálogo Productos'!B13<>"",SUMIF('Febrero 2026 - Ventas'!$C$5:$C$63,'Catálogo Productos'!B13,'Febrero 2026 - Ventas'!$J$5:$J$63)+SUMIF('Marzo 2026 - Ventas'!$C$5:$C$63,'Catálogo Productos'!B13,'Marzo 2026 - Ventas'!$J$5:$J$63)+SUMIF('Abril 2026 - Ventas'!$C$5:$C$166,'Catálogo Productos'!B13,'Abril 2026 - Ventas'!$J$5:$J$166),"") -> 9.1 | F16: =IF('Catálogo Productos'!B13<>"",SUMIF('Febrero 2026 - Ventas'!$C$5:$C$63,'Catálogo Productos'!B13,'Febrero 2026 - Ventas'!$K$5:$K$63)+SUMIF('Marzo 2026 - Ventas'!$C$5:$C$63,'Catálogo Productos'!B13,'Marzo 2026 - Ventas'!$K$5:$K$63)+SUMIF('Abril 2026 - Ventas'!$C$5:$C$166,'Catálogo Productos'!B13,'Abril 2026 - Ventas'!$K$5:$K$166),"") -> 41.4377 | G16: =IF(OR(NOT('Catálogo Productos'!B13<>""),E16="",E16=0),"",F16/E16) -> 4.5535934 | H16: =IF('Catálogo Productos'!B13<>"",'Catálogo Productos'!H68,"") -> 21 | I16: =IF('Catálogo Productos'!B13<>"",'Catálogo Productos'!L68,"") -> 🟢 OK
A17: =IF('Catálogo Productos'!B14<>"",COUNTA('Catálogo Productos'!$B$4:$B14),"") -> 11 | B17: =IF('Catálogo Productos'!B14<>"",'Catálogo Productos'!B14,"") -> Cuerdas de Violin 4/4 | C17: =IF('Catálogo Productos'!B14<>"",'Catálogo Productos'!C14,"") -> Violin | D17: =IF('Catálogo Productos'!B14<>"",COUNTIF('Febrero 2026 - Ventas'!$C$5:$C$63,'Catálogo Productos'!B14)+COUNTIF('Marzo 2026 - Ventas'!$C$5:$C$63,'Catálogo Productos'!B14)+COUNTIF('Abril 2026 - Ventas'!$C$5:$C$166,'Catálogo Productos'!B14),"") -> 7 | E17: =IF('Catálogo Productos'!B14<>"",SUMIF('Febrero 2026 - Ventas'!$C$5:$C$63,'Catálogo Productos'!B14,'Febrero 2026 - Ventas'!$J$5:$J$63)+SUMIF('Marzo 2026 - Ventas'!$C$5:$C$63,'Catálogo Productos'!B14,'Marzo 2026 - Ventas'!$J$5:$J$63)+SUMIF('Abril 2026 - Ventas'!$C$5:$C$166,'Catálogo Productos'!B14,'Abril 2026 - Ventas'!$J$5:$J$166),"") -> 9.1 | F17: =IF('Catálogo Productos'!B14<>"",SUMIF('Febrero 2026 - Ventas'!$C$5:$C$63,'Catálogo Productos'!B14,'Febrero 2026 - Ventas'!$K$5:$K$63)+SUMIF('Marzo 2026 - Ventas'!$C$5:$C$63,'Catálogo Productos'!B14,'Marzo 2026 - Ventas'!$K$5:$K$63)+SUMIF('Abril 2026 - Ventas'!$C$5:$C$166,'Catálogo Productos'!B14,'Abril 2026 - Ventas'!$K$5:$K$166),"") -> 21.9877 | G17: =IF(OR(NOT('Catálogo Productos'!B14<>""),E17="",E17=0),"",F17/E17) -> 2.4162308 | H17: =IF('Catálogo Productos'!B14<>"",'Catálogo Productos'!H69,"") -> 40 | I17: =IF('Catálogo Productos'!B14<>"",'Catálogo Productos'!L69,"") -> 🟢 OK
A18: =IF('Catálogo Productos'!B15<>"",COUNTA('Catálogo Productos'!$B$4:$B15),"") -> 12 | B18: =IF('Catálogo Productos'!B15<>"",'Catálogo Productos'!B15,"") -> Cable Hebikuo XA03 | C18: =IF('Catálogo Productos'!B15<>"",'Catálogo Productos'!C15,"") -> Cables | D18: =IF('Catálogo Productos'!B15<>"",COUNTIF('Febrero 2026 - Ventas'!$C$5:$C$63,'Catálogo Productos'!B15)+COUNTIF('Marzo 2026 - Ventas'!$C$5:$C$63,'Catálogo Productos'!B15)+COUNTIF('Abril 2026 - Ventas'!$C$5:$C$166,'Catálogo Productos'!B15),"") -> 24 | E18: =IF('Catálogo Productos'!B15<>"",SUMIF('Febrero 2026 - Ventas'!$C$5:$C$63,'Catálogo Productos'!B15,'Febrero 2026 - Ventas'!$J$5:$J$63)+SUMIF('Marzo 2026 - Ventas'!$C$5:$C$63,'Catálogo Productos'!B15,'Marzo 2026 - Ventas'!$J$5:$J$63)+SUMIF('Abril 2026 - Ventas'!$C$5:$C$166,'Catálogo Productos'!B15,'Abril 2026 - Ventas'!$J$5:$J$166),"") -> 23.4 | F18: =IF('Catálogo Productos'!B15<>"",SUMIF('Febrero 2026 - Ventas'!$C$5:$C$63,'Catálogo Productos'!B15,'Febrero 2026 - Ventas'!$K$5:$K$63)+SUMIF('Marzo 2026 - Ventas'!$C$5:$C$63,'Catálogo Productos'!B15,'Marzo 2026 - Ventas'!$K$5:$K$63)+SUMIF('Abril 2026 - Ventas'!$C$5:$C$166,'Catálogo Productos'!B15,'Abril 2026 - Ventas'!$K$5:$K$166),"") -> 190.2 | G18: =IF(OR(NOT('Catálogo Productos'!B15<>""),E18="",E18=0),"",F18/E18) -> 8.1282051 | H18: =IF('Catálogo Productos'!B15<>"",'Catálogo Productos'!H70,"") -> 13 | I18: =IF('Catálogo Productos'!B15<>"",'Catálogo Productos'!L70,"") -> 🟢 OK
... A32: =IF('Catálogo Productos'!B29<>"",COUNTA('Catálogo Productos'!$B$4:$B29),"") -> 26 | B32: =IF('Catálogo Productos'!B29<>"",'Catálogo Productos'!B29,"") -> Ernie Ball Super Slinky | C32: =IF('Catálogo Productos'!B29<>"",'Catálogo Productos'!C29,"") -> Guitarra Electrica | D32: =IF('Catálogo Productos'!B29<>"",COUNTIF('Febrero 2026 - Ventas'!$C$5:$C$63,'Catálogo Productos'!B29)+COUNTIF('Marzo 2026 - Ventas'!$C$5:$C$63,'Catálogo Productos'!B29)+COUNTIF('Abril 2026 - Ventas'!$C$5:$C$166,'Catálogo Productos'!B29),"") -> 0 | E32: =IF('Catálogo Productos'!B29<>"",SUMIF('Febrero 2026 - Ventas'!$C$5:$C$63,'Catálogo Productos'!B29,'Febrero 2026 - Ventas'!$J$5:$J$63)+SUMIF('Marzo 2026 - Ventas'!$C$5:$C$63,'Catálogo Productos'!B29,'Marzo 2026 - Ventas'!$J$5:$J$63)+SUMIF('Abril 2026 - Ventas'!$C$5:$C$166,'Catálogo Productos'!B29,'Abril 2026 - Ventas'!$J$5:$J$166),"") -> 0 | F32: =IF('Catálogo Productos'!B29<>"",SUMIF('Febrero 2026 - Ventas'!$C$5:$C$63,'Catálogo Productos'!B29,'Febrero 2026 - Ventas'!$K$5:$K$63)+SUMIF('Marzo 2026 - Ventas'!$C$5:$C$63,'Catálogo Productos'!B29,'Marzo 2026 - Ventas'!$K$5:$K$63)+SUMIF('Abril 2026 - Ventas'!$C$5:$C$166,'Catálogo Productos'!B29,'Abril 2026 - Ventas'!$K$5:$K$166),"") -> 0 | G32: =IF(OR(NOT('Catálogo Productos'!B29<>""),E32="",E32=0),"",F32/E32) | H32: =IF('Catálogo Productos'!B29<>"",'Catálogo Productos'!H84,"") -> 0 | I32: =IF('Catálogo Productos'!B29<>"",'Catálogo Productos'!L84,"") -> 🔴 Sin stock
A33: =IF('Catálogo Productos'!B30<>"",COUNTA('Catálogo Productos'!$B$4:$B30),"") -> 27 | B33: =IF('Catálogo Productos'!B30<>"",'Catálogo Productos'!B30,"") -> Ernie Ball Regular Slinky | C33: =IF('Catálogo Productos'!B30<>"",'Catálogo Productos'!C30,"") -> Guitarra Electrica | D33: =IF('Catálogo Productos'!B30<>"",COUNTIF('Febrero 2026 - Ventas'!$C$5:$C$63,'Catálogo Productos'!B30)+COUNTIF('Marzo 2026 - Ventas'!$C$5:$C$63,'Catálogo Productos'!B30)+COUNTIF('Abril 2026 - Ventas'!$C$5:$C$166,'Catálogo Productos'!B30),"") -> 0 | E33: =IF('Catálogo Productos'!B30<>"",SUMIF('Febrero 2026 - Ventas'!$C$5:$C$63,'Catálogo Productos'!B30,'Febrero 2026 - Ventas'!$J$5:$J$63)+SUMIF('Marzo 2026 - Ventas'!$C$5:$C$63,'Catálogo Productos'!B30,'Marzo 2026 - Ventas'!$J$5:$J$63)+SUMIF('Abril 2026 - Ventas'!$C$5:$C$166,'Catálogo Productos'!B30,'Abril 2026 - Ventas'!$J$5:$J$166),"") -> 0 | F33: =IF('Catálogo Productos'!B30<>"",SUMIF('Febrero 2026 - Ventas'!$C$5:$C$63,'Catálogo Productos'!B30,'Febrero 2026 - Ventas'!$K$5:$K$63)+SUMIF('Marzo 2026 - Ventas'!$C$5:$C$63,'Catálogo Productos'!B30,'Marzo 2026 - Ventas'!$K$5:$K$63)+SUMIF('Abril 2026 - Ventas'!$C$5:$C$166,'Catálogo Productos'!B30,'Abril 2026 - Ventas'!$K$5:$K$166),"") -> 0 | G33: =IF(OR(NOT('Catálogo Productos'!B30<>""),E33="",E33=0),"",F33/E33) | H33: 6 | I33: =IF('Catálogo Productos'!B30<>"",'Catálogo Productos'!L85,"") -> 🔴 Sin stock
A34: =IF('Catálogo Productos'!B31<>"",COUNTA('Catálogo Productos'!$B$4:$B31),"") -> 28 | B34: =IF('Catálogo Productos'!B31<>"",'Catálogo Productos'!B31,"") -> Puente Violin 4/4 | C34: =IF('Catálogo Productos'!B31<>"",'Catálogo Productos'!C31,"") -> Violin | D34: =IF('Catálogo Productos'!B31<>"",COUNTIF('Febrero 2026 - Ventas'!$C$5:$C$63,'Catálogo Productos'!B31)+COUNTIF('Marzo 2026 - Ventas'!$C$5:$C$63,'Catálogo Productos'!B31)+COUNTIF('Abril 2026 - Ventas'!$C$5:$C$166,'Catálogo Productos'!B31),"") -> 1 | E34: =IF('Catálogo Productos'!B31<>"",SUMIF('Febrero 2026 - Ventas'!$C$5:$C$63,'Catálogo Productos'!B31,'Febrero 2026 - Ventas'!$J$5:$J$63)+SUMIF('Marzo 2026 - Ventas'!$C$5:$C$63,'Catálogo Productos'!B31,'Marzo 2026 - Ventas'!$J$5:$J$63)+SUMIF('Abril 2026 - Ventas'!$C$5:$C$166,'Catálogo Productos'!B31,'Abril 2026 - Ventas'!$J$5:$J$166),"") -> 0 | F34: =IF('Catálogo Productos'!B31<>"",SUMIF('Febrero 2026 - Ventas'!$C$5:$C$63,'Catálogo Productos'!B31,'Febrero 2026 - Ventas'!$K$5:$K$63)+SUMIF('Marzo 2026 - Ventas'!$C$5:$C$63,'Catálogo Productos'!B31,'Marzo 2026 - Ventas'!$K$5:$K$63)+SUMIF('Abril 2026 - Ventas'!$C$5:$C$166,'Catálogo Productos'!B31,'Abril 2026 - Ventas'!$K$5:$K$166),"") -> 4.45 | G34: =IF(OR(NOT('Catálogo Productos'!B31<>""),E34="",E34=0),"",F34/E34) | H34: 12 | I34: =IF('Catálogo Productos'!B31<>"",'Catálogo Productos'!L86,"") -> 🔴 Sin stock
A35: =IF('Catálogo Productos'!B32<>"",COUNTA('Catálogo Productos'!$B$4:$B32),"") -> 29 | B35: =IF('Catálogo Productos'!B32<>"",'Catálogo Productos'!B32,"") -> Puente Violin 3/4 | C35: =IF('Catálogo Productos'!B32<>"",'Catálogo Productos'!C32,"") -> Violin | D35: =IF('Catálogo Productos'!B32<>"",COUNTIF('Marzo 2026 - Ventas'!$C$5:$C$63,'Catálogo Productos'!B32),"") -> 0 | E35: =IF('Catálogo Productos'!B32<>"",SUMIF('Marzo 2026 - Ventas'!$C$5:$C$63,'Catálogo Productos'!B32,'Marzo 2026 - Ventas'!$J$5:$J$63),"") -> 0 | F35: =IF('Catálogo Productos'!B32<>"",SUMIF('Marzo 2026 - Ventas'!$C$5:$C$63,'Catálogo Productos'!B32,'Marzo 2026 - Ventas'!$K$5:$K$63),"") -> 0 | G35: =IF(OR(NOT('Catálogo Productos'!B32<>""),E35="",E35=0),"",F35/E35) | H35: 12 | I35: =IF('Catálogo Productos'!B32<>"",'Catálogo Productos'!L87,"") -> 🔴 Sin stock
A36: =IF('Catálogo Productos'!B33<>"",COUNTA('Catálogo Productos'!$B$4:$B33),"") | B36: =IF('Catálogo Productos'!B33<>"",'Catálogo Productos'!B33,"") | C36: =IF('Catálogo Productos'!B33<>"",'Catálogo Productos'!C33,"") | D36: =IF('Catálogo Productos'!B33<>"",COUNTIF('Marzo 2026 - Ventas'!$C$5:$C$63,'Catálogo Productos'!B33),"") | E36: =IF('Catálogo Productos'!B33<>"",SUMIF('Marzo 2026 - Ventas'!$C$5:$C$63,'Catálogo Productos'!B33,'Marzo 2026 - Ventas'!$J$5:$J$63),"") | F36: =IF('Catálogo Productos'!B33<>"",SUMIF('Marzo 2026 - Ventas'!$C$5:$C$63,'Catálogo Productos'!B33,'Marzo 2026 - Ventas'!$K$5:$K$63),"") | G36: =IF(OR(NOT('Catálogo Productos'!B33<>""),E36="",E36=0),"",F36/E36) | H36: =IF('Catálogo Productos'!B33<>"",'Catálogo Productos'!H88,"") | I36: =IF('Catálogo Productos'!B33<>"",'Catálogo Productos'!L88,"")
A37: =IF('Catálogo Productos'!B34<>"",COUNTA('Catálogo Productos'!$B$4:$B34),"") | B37: =IF('Catálogo Productos'!B34<>"",'Catálogo Productos'!B34,"") | C37: =IF('Catálogo Productos'!B34<>"",'Catálogo Productos'!C34,"") | D37: =IF('Catálogo Productos'!B34<>"",COUNTIF('Marzo 2026 - Ventas'!$C$5:$C$63,'Catálogo Productos'!B34),"") | E37: =IF('Catálogo Productos'!B34<>"",SUMIF('Marzo 2026 - Ventas'!$C$5:$C$63,'Catálogo Productos'!B34,'Marzo 2026 - Ventas'!$J$5:$J$63),"") | F37: =IF('Catálogo Productos'!B34<>"",SUMIF('Marzo 2026 - Ventas'!$C$5:$C$63,'Catálogo Productos'!B34,'Marzo 2026 - Ventas'!$K$5:$K$63),"") | G37: =IF(OR(NOT('Catálogo Productos'!B34<>""),E37="",E37=0),"",F37/E37) | H37: =IF('Catálogo Productos'!B34<>"",'Catálogo Productos'!H89,"") | I37: =IF('Catálogo Productos'!B34<>"",'Catálogo Productos'!L89,"")
A38: =IF('Catálogo Productos'!B35<>"",COUNTA('Catálogo Productos'!$B$4:$B35),"") | B38: =IF('Catálogo Productos'!B35<>"",'Catálogo Productos'!B35,"") | C38: =IF('Catálogo Productos'!B35<>"",'Catálogo Productos'!C35,"") | D38: =IF('Catálogo Productos'!B35<>"",COUNTIF('Marzo 2026 - Ventas'!$C$5:$C$63,'Catálogo Productos'!B35),"") | E38: =IF('Catálogo Productos'!B35<>"",SUMIF('Marzo 2026 - Ventas'!$C$5:$C$63,'Catálogo Productos'!B35,'Marzo 2026 - Ventas'!$J$5:$J$63),"") | F38: =IF('Catálogo Productos'!B35<>"",SUMIF('Marzo 2026 - Ventas'!$C$5:$C$63,'Catálogo Productos'!B35,'Marzo 2026 - Ventas'!$K$5:$K$63),"") | G38: =IF(OR(NOT('Catálogo Productos'!B35<>""),E38="",E38=0),"",F38/E38) | H38: =IF('Catálogo Productos'!B35<>"",'Catálogo Productos'!H90,"") | I38: =IF('Catálogo Productos'!B35<>"",'Catálogo Productos'!L90,"")
A39: =IF('Catálogo Productos'!B36<>"",COUNTA('Catálogo Productos'!$B$4:$B36),"") | B39: =IF('Catálogo Productos'!B36<>"",'Catálogo Productos'!B36,"") | C39: =IF('Catálogo Productos'!B36<>"",'Catálogo Productos'!C36,"") | D39: =IF('Catálogo Productos'!B36<>"",COUNTIF('Marzo 2026 - Ventas'!$C$5:$C$63,'Catálogo Productos'!B36),"") | E39: =IF('Catálogo Productos'!B36<>"",SUMIF('Marzo 2026 - Ventas'!$C$5:$C$63,'Catálogo Productos'!B36,'Marzo 2026 - Ventas'!$J$5:$J$63),"") | F39: =IF('Catálogo Productos'!B36<>"",SUMIF('Marzo 2026 - Ventas'!$C$5:$C$63,'Catálogo Productos'!B36,'Marzo 2026 - Ventas'!$K$5:$K$63),"") | G39: =IF(OR(NOT('Catálogo Productos'!B36<>""),E39="",E39=0),"",F39/E39) | H39: =IF('Catálogo Productos'!B36<>"",'Catálogo Productos'!H91,"") | I39: =IF('Catálogo Productos'!B36<>"",'Catálogo Productos'!L91,"")
A40: =IF('Catálogo Productos'!B37<>"",COUNTA('Catálogo Productos'!$B$4:$B37),"") | B40: =IF('Catálogo Productos'!B37<>"",'Catálogo Productos'!B37,"") | C40: =IF('Catálogo Productos'!B37<>"",'Catálogo Productos'!C37,"") | D40: =IF('Catálogo Productos'!B37<>"",COUNTIF('Marzo 2026 - Ventas'!$C$5:$C$63,'Catálogo Productos'!B37),"") | E40: =IF('Catálogo Productos'!B37<>"",SUMIF('Marzo 2026 - Ventas'!$C$5:$C$63,'Catálogo Productos'!B37,'Marzo 2026 - Ventas'!$J$5:$J$63),"") | F40: =IF('Catálogo Productos'!B37<>"",SUMIF('Marzo 2026 - Ventas'!$C$5:$C$63,'Catálogo Productos'!B37,'Marzo 2026 - Ventas'!$K$5:$K$63),"") | G40: =IF(OR(NOT('Catálogo Productos'!B37<>""),E40="",E40=0),"",F40/E40) | H40: =IF('Catálogo Productos'!B37<>"",'Catálogo Productos'!H92,"") | I40: =IF('Catálogo Productos'!B37<>"",'Catálogo Productos'!L92,"")
A41: =IF('Catálogo Productos'!B38<>"",COUNTA('Catálogo Productos'!$B$4:$B38),"") | B41: =IF('Catálogo Productos'!B38<>"",'Catálogo Productos'!B38,"") | C41: =IF('Catálogo Productos'!B38<>"",'Catálogo Productos'!C38,"") | D41: =IF('Catálogo Productos'!B38<>"",COUNTIF('Marzo 2026 - Ventas'!$C$5:$C$63,'Catálogo Productos'!B38),"") | E41: =IF('Catálogo Productos'!B38<>"",SUMIF('Marzo 2026 - Ventas'!$C$5:$C$63,'Catálogo Productos'!B38,'Marzo 2026 - Ventas'!$J$5:$J$63),"") | F41: =IF('Catálogo Productos'!B38<>"",SUMIF('Marzo 2026 - Ventas'!$C$5:$C$63,'Catálogo Productos'!B38,'Marzo 2026 - Ventas'!$K$5:$K$63),"") | G41: =IF(OR(NOT('Catálogo Productos'!B38<>""),E41="",E41=0),"",F41/E41) | H41: =IF('Catálogo Productos'!B38<>"",'Catálogo Productos'!H93,"") | I41: =IF('Catálogo Productos'!B38<>"",'Catálogo Productos'!L93,"")
A42: =IF('Catálogo Productos'!B39<>"",COUNTA('Catálogo Productos'!$B$4:$B39),"") | B42: =IF('Catálogo Productos'!B39<>"",'Catálogo Productos'!B39,"") | C42: =IF('Catálogo Productos'!B39<>"",'Catálogo Productos'!C39,"") | D42: =IF('Catálogo Productos'!B39<>"",COUNTIF('Marzo 2026 - Ventas'!$C$5:$C$63,'Catálogo Productos'!B39),"") | E42: =IF('Catálogo Productos'!B39<>"",SUMIF('Marzo 2026 - Ventas'!$C$5:$C$63,'Catálogo Productos'!B39,'Marzo 2026 - Ventas'!$J$5:$J$63),"") | F42: =IF('Catálogo Productos'!B39<>"",SUMIF('Marzo 2026 - Ventas'!$C$5:$C$63,'Catálogo Productos'!B39,'Marzo 2026 - Ventas'!$K$5:$K$63),"") | G42: =IF(OR(NOT('Catálogo Productos'!B39<>""),E42="",E42=0),"",F42/E42) | H42: =IF('Catálogo Productos'!B39<>"",'Catálogo Productos'!H94,"") | I42: =IF('Catálogo Productos'!B39<>"",'Catálogo Productos'!L94,"")
A43: =IF('Catálogo Productos'!B40<>"",COUNTA('Catálogo Productos'!$B$4:$B40),"") | B43: =IF('Catálogo Productos'!B40<>"",'Catálogo Productos'!B40,"") | C43: =IF('Catálogo Productos'!B40<>"",'Catálogo Productos'!C40,"") | D43: =IF('Catálogo Productos'!B40<>"",COUNTIF('Marzo 2026 - Ventas'!$C$5:$C$63,'Catálogo Productos'!B40),"") | E43: =IF('Catálogo Productos'!B40<>"",SUMIF('Marzo 2026 - Ventas'!$C$5:$C$63,'Catálogo Productos'!B40,'Marzo 2026 - Ventas'!$J$5:$J$63),"") | F43: =IF('Catálogo Productos'!B40<>"",SUMIF('Marzo 2026 - Ventas'!$C$5:$C$63,'Catálogo Productos'!B40,'Marzo 2026 - Ventas'!$K$5:$K$63),"") | G43: =IF(OR(NOT('Catálogo Productos'!B40<>""),E43="",E43=0),"",F43/E43) | H43: =IF('Catálogo Productos'!B40<>"",'Catálogo Productos'!H95,"") | I43: =IF('Catálogo Productos'!B40<>"",'Catálogo Productos'!L95,"")
A44: =IF('Catálogo Productos'!B41<>"",COUNTA('Catálogo Productos'!$B$4:$B41),"") | B44: =IF('Catálogo Productos'!B41<>"",'Catálogo Productos'!B41,"") | C44: =IF('Catálogo Productos'!B41<>"",'Catálogo Productos'!C41,"") | D44: =IF('Catálogo Productos'!B41<>"",COUNTIF('Marzo 2026 - Ventas'!$C$5:$C$63,'Catálogo Productos'!B41),"") | E44: =IF('Catálogo Productos'!B41<>"",SUMIF('Marzo 2026 - Ventas'!$C$5:$C$63,'Catálogo Productos'!B41,'Marzo 2026 - Ventas'!$J$5:$J$63),"") | F44: =IF('Catálogo Productos'!B41<>"",SUMIF('Marzo 2026 - Ventas'!$C$5:$C$63,'Catálogo Productos'!B41,'Marzo 2026 - Ventas'!$K$5:$K$63),"") | G44: =IF(OR(NOT('Catálogo Productos'!B41<>""),E44="",E44=0),"",F44/E44) | H44: =IF('Catálogo Productos'!B41<>"",'Catálogo Productos'!H96,"") | I44: =IF('Catálogo Productos'!B41<>"",'Catálogo Productos'!L96,"")
A45: =IF('Catálogo Productos'!B42<>"",COUNTA('Catálogo Productos'!$B$4:$B42),"") | B45: =IF('Catálogo Productos'!B42<>"",'Catálogo Productos'!B42,"") | C45: =IF('Catálogo Productos'!B42<>"",'Catálogo Productos'!C42,"") | D45: =IF('Catálogo Productos'!B42<>"",COUNTIF('Marzo 2026 - Ventas'!$C$5:$C$63,'Catálogo Productos'!B42),"") | E45: =IF('Catálogo Productos'!B42<>"",SUMIF('Marzo 2026 - Ventas'!$C$5:$C$63,'Catálogo Productos'!B42,'Marzo 2026 - Ventas'!$J$5:$J$63),"") | F45: =IF('Catálogo Productos'!B42<>"",SUMIF('Marzo 2026 - Ventas'!$C$5:$C$63,'Catálogo Productos'!B42,'Marzo 2026 - Ventas'!$K$5:$K$63),"") | G45: =IF(OR(NOT('Catálogo Productos'!B42<>""),E45="",E45=0),"",F45/E45) | H45: =IF('Catálogo Productos'!B42<>"",'Catálogo Productos'!H97,"") | I45: =IF('Catálogo Productos'!B42<>"",'Catálogo Productos'!L97,"")
A46: =IF('Catálogo Productos'!B43<>"",COUNTA('Catálogo Productos'!$B$4:$B43),"") | B46: =IF('Catálogo Productos'!B43<>"",'Catálogo Productos'!B43,"") | C46: =IF('Catálogo Productos'!B43<>"",'Catálogo Productos'!C43,"") | D46: =IF('Catálogo Productos'!B43<>"",COUNTIF('Marzo 2026 - Ventas'!$C$5:$C$63,'Catálogo Productos'!B43),"") | E46: =IF('Catálogo Productos'!B43<>"",SUMIF('Marzo 2026 - Ventas'!$C$5:$C$63,'Catálogo Productos'!B43,'Marzo 2026 - Ventas'!$J$5:$J$63),"") | F46: =IF('Catálogo Productos'!B43<>"",SUMIF('Marzo 2026 - Ventas'!$C$5:$C$63,'Catálogo Productos'!B43,'Marzo 2026 - Ventas'!$K$5:$K$63),"") | G46: =IF(OR(NOT('Catálogo Productos'!B43<>""),E46="",E46=0),"",F46/E46) | H46: =IF('Catálogo Productos'!B43<>"",'Catálogo Productos'!H98,"") | I46: =IF('Catálogo Productos'!B43<>"",'Catálogo Productos'!L98,"")
A47: =IF('Catálogo Productos'!B44<>"",COUNTA('Catálogo Productos'!$B$4:$B44),"") | B47: =IF('Catálogo Productos'!B44<>"",'Catálogo Productos'!B44,"") | C47: =IF('Catálogo Productos'!B44<>"",'Catálogo Productos'!C44,"") | D47: =IF('Catálogo Productos'!B44<>"",COUNTIF('Marzo 2026 - Ventas'!$C$5:$C$63,'Catálogo Productos'!B44),"") | E47: =IF('Catálogo Productos'!B44<>"",SUMIF('Marzo 2026 - Ventas'!$C$5:$C$63,'Catálogo Productos'!B44,'Marzo 2026 - Ventas'!$J$5:$J$63),"") | F47: =IF('Catálogo Productos'!B44<>"",SUMIF('Marzo 2026 - Ventas'!$C$5:$C$63,'Catálogo Productos'!B44,'Marzo 2026 - Ventas'!$K$5:$K$63),"") | G47: =IF(OR(NOT('Catálogo Productos'!B44<>""),E47="",E47=0),"",F47/E47) | H47: =IF('Catálogo Productos'!B44<>"",'Catálogo Productos'!H99,"") | I47: =IF('Catálogo Productos'!B44<>"",'Catálogo Productos'!L99,"")
... A56: =IF('Catálogo Productos'!B53<>"",COUNTA('Catálogo Productos'!$B$4:$B53),"") | B56: =IF('Catálogo Productos'!B53<>"",'Catálogo Productos'!B53,"") | C56: =IF('Catálogo Productos'!B53<>"",'Catálogo Productos'!C53,"") | D56: =IF('Catálogo Productos'!B53<>"",COUNTIF('Marzo 2026 - Ventas'!$C$5:$C$63,'Catálogo Productos'!B53),"") | E56: =IF('Catálogo Productos'!B53<>"",SUMIF('Marzo 2026 - Ventas'!$C$5:$C$63,'Catálogo Productos'!B53,'Marzo 2026 - Ventas'!$J$5:$J$63),"") | F56: =IF('Catálogo Productos'!B53<>"",SUMIF('Marzo 2026 - Ventas'!$C$5:$C$63,'Catálogo Productos'!B53,'Marzo 2026 - Ventas'!$K$5:$K$63),"") | G56: =IF(OR(NOT('Catálogo Productos'!B53<>""),E56="",E56=0),"",F56/E56) | H56: =IF('Catálogo Productos'!B53<>"",'Catálogo Productos'!H108,"") | I56: =IF('Catálogo Productos'!B53<>"",'Catálogo Productos'!L108,"")
A57: TOTALES | D57: =SUM(D7:D56) -> 246 | E57: =SUM(E7:E56) -> 253.5 | F57: =SUM(F7:F56) -> 1392.9399 | G57: =IF(E57=0,"",F57/E57) -> 5.494832
A59: 💡 Para ordenar: selecciona cualquier celda de la tabla → Datos → Ordenar por la columna que prefieras (Uds, Ganancia, Margen).

Sheet 📦 Rotación & Repos.
A1: 📦 ROTACIÓN DE INVENTARIO & PROYECCIÓN DE REPOSICIÓN
A2: Mes activo: Abril — Días del mes: 31 — Días transcurridos: ver Configuración C11
A3: ℹ️ Promedio Proyectado = ventas del mes en curso × (días del mes ÷ días transcurridos). Actualiza C11 en Configuración cada semana. Al cambiar de mes, actualiza también la hoja referenciada en la fórmula de columna E (actualmente: Abril 2026 - Ventas).
A5: 📊 ANÁLISIS POR PRODUCTO
A6: # | B6: Producto | C6: Categoría | D6: Stock Total | E6: Uds Vendidas (mes activo) | F6: Días del Mes | G6: Días por Unidad (rotación) | H6: Días hasta Agotamiento | I6: Fecha Est. Agotamiento | J6: Estado Rotación | K6: Stock Mínimo | L6: 🚦 Urgencia Reposición | M6: Prom. Mensual Proyectado | N6: Cantidad Sugerida a Pedir | O6: Fecha Límite Hacer Pedido | P6: 🚦 Plan de Reposición | Q6: Meses Cubiertos
A7: =IF('Catálogo Productos'!B4<>"",COUNTA('Catálogo Productos'!$B$4:$B4),"") -> 1 | B7: =IF('Catálogo Productos'!B4<>"",'Catálogo Productos'!B4,"") -> Cuerdas Alice Clasica A106 | C7: =IF('Catálogo Productos'!B4<>"",'Catálogo Productos'!C4,"") -> Guitarra Clasica | D7: 80 | E7: =IF('Catálogo Productos'!B4<>"",COUNTIF('Abril 2026 - Ventas'!$C$5:$C$303,'Catálogo Productos'!B4),"") -> 24 | F7: =IF('Catálogo Productos'!B4<>"",'Configuración'!$C$4,"") -> 31 | G7: =IF(OR(NOT('Catálogo Productos'!B4<>""),E7="",E7=0),IF('Catálogo Productos'!B4<>"","Sin ventas",""),IF(M7=0,"Sin ventas",ROUND(F7/M7,1))) -> 0.4 | H7: =IF(OR(NOT('Catálogo Productos'!B4<>""),D7="",D7=0),IF('Catálogo Productos'!B4<>"",IF(E7=0,"∞ (sin ventas)","🔴 Sin stock"),""),IF(G7="Sin ventas","∞ (sin ventas)",ROUND(D7*G7,0))) -> 32 | I7: =IF(OR(NOT('Catálogo Productos'!B4<>""),H7="",ISNUMBER(SEARCH("∞",TEXT(H7,"@"))),ISNUMBER(SEARCH("🔴",TEXT(H7,"@")))),"",TODAY()+H7) -> 46175 | J7: =IF(NOT('Catálogo Productos'!B4<>""),"",IF(OR(G7="Sin ventas",G7=""),"⚪ Sin ventas este mes",IF(G7<=15,"🔥 Rotación rápida",IF(G7<=30,"✅ Rotación normal","🐢 Rotación lenta")))) -> 🔥 Rotación rápida | K7: =IF('Catálogo Productos'!B4<>"",'Catálogo Productos'!G4,"") -> 40 | L7: =IF(NOT(B7<>""),"",IF(D7=0,"🔴 REPONER YA",IF(OR(M7=0,M7=""),"🟢 Sin prisa",IF(Q7<'Configuración'!$C$9,"🔴 PEDIR AHORA",IF(Q7<('Configuración'!$C$9+'Configuración'!$C$10),"🟡 Reponer pronto","🟢 Sin prisa"))))) -> 🔴 PEDIR AHORA | M7: =IF(B7="","",IF(OR(E7="",E7=0),0,ROUND(E7*('Configuración'!$C$4/'Configuración'!$C$11),1))) -> 74.4 | N7: =IF(B7="","",IF(M7=0,"—",MAX(0,CEILING(M7*('Configuración'!$C$9+'Configuración'!$C$10)-D7,1)))) -> 292 | O7: =IF(B7="","",IF(ISNUMBER(I7),I7-135,"—")) -> 46040 | P7: =IF(B7="","",IF(D7=0,"🔴 PEDIR URGENTE — sin stock",IF(OR(M7=0,M7=""),"⚪ Sin demanda — monitorear",IF(Q7<'Configuración'!$C$9,"🔴 PEDIR AHORA — "&N7&" uds (stock cubre "&Q7&" meses, lead time "&'Configuración'!$C$9&" meses)",IF(Q7<('Configuración'!$C$9+'Configuración'!$C$10),"🟡 VIGILAR — "&N7&" uds (cubre "&Q7&" meses, al límite del lead time)","🟢 OK — stock cubre "&Q7&" meses"))))) -> 🔴 PEDIR AHORA — 292 uds (stock cubre 1,1 meses, lead time 4 meses) | Q7: =IF(B7="","",IF(OR(M7=0,M7=""),999,ROUND(D7/M7,1))) -> 1.1
A8: =IF('Catálogo Productos'!B5<>"",COUNTA('Catálogo Productos'!$B$4:$B5),"") -> 2 | B8: =IF('Catálogo Productos'!B5<>"",'Catálogo Productos'!B5,"") -> Cuerdas Alice Electrica SL | C8: =IF('Catálogo Productos'!B5<>"",'Catálogo Productos'!C5,"") -> Guitarra Electrica | D8: 69 | E8: =IF('Catálogo Productos'!B5<>"",COUNTIF('Abril 2026 - Ventas'!$C$5:$C$303,'Catálogo Productos'!B5),"") -> 17 | F8: =IF('Catálogo Productos'!B5<>"",'Configuración'!$C$4,"") -> 31 | G8: =IF(OR(NOT('Catálogo Productos'!B5<>""),E8="",E8=0),IF('Catálogo Productos'!B5<>"","Sin ventas",""),IF(M8=0,"Sin ventas",ROUND(F8/M8,1))) -> 0.6 | H8: =IF(OR(NOT('Catálogo Productos'!B5<>""),D8="",D8=0),IF('Catálogo Productos'!B5<>"",IF(E8=0,"∞ (sin ventas)","🔴 Sin stock"),""),IF(G8="Sin ventas","∞ (sin ventas)",ROUND(D8*G8,0))) -> 41 | I8: =IF(OR(NOT('Catálogo Productos'!B5<>""),H8="",ISNUMBER(SEARCH("∞",TEXT(H8,"@"))),ISNUMBER(SEARCH("🔴",TEXT(H8,"@")))),"",TODAY()+H8) -> 46184 | J8: =IF(NOT('Catálogo Productos'!B5<>""),"",IF(OR(G8="Sin ventas",G8=""),"⚪ Sin ventas este mes",IF(G8<=15,"🔥 Rotación rápida",IF(G8<=30,"✅ Rotación normal","🐢 Rotación lenta")))) -> 🔥 Rotación rápida | K8: =IF('Catálogo Productos'!B5<>"",'Catálogo Productos'!G5,"") -> 20 | L8: =IF(NOT(B8<>""),"",IF(D8=0,"🔴 REPONER YA",IF(OR(M8=0,M8=""),"🟢 Sin prisa",IF(Q8<'Configuración'!$C$9,"🔴 PEDIR AHORA",IF(Q8<('Configuración'!$C$9+'Configuración'!$C$10),"🟡 Reponer pronto","🟢 Sin prisa"))))) -> 🔴 PEDIR AHORA | M8: =IF(B8="","",IF(OR(E8="",E8=0),0,ROUND(E8*('Configuración'!$C$4/'Configuración'!$C$11),1))) -> 52.7 | N8: =IF(B8="","",IF(M8=0,"—",MAX(0,CEILING(M8*('Configuración'!$C$9+'Configuración'!$C$10)-D8,1)))) -> 195 | O8: =IF(B8="","",IF(ISNUMBER(I8),I8-135,"—")) -> 46049 | P8: =IF(B8="","",IF(D8=0,"🔴 PEDIR URGENTE — sin stock",IF(OR(M8=0,M8=""),"⚪ Sin demanda — monitorear",IF(Q8<'Configuración'!$C$9,"🔴 PEDIR AHORA — "&N8&" uds (stock cubre "&Q8&" meses, lead time "&'Configuración'!$C$9&" meses)",IF(Q8<('Configuración'!$C$9+'Configuración'!$C$10),"🟡 VIGILAR — "&N8&" uds (cubre "&Q8&" meses, al límite del lead time)","🟢 OK — stock cubre "&Q8&" meses"))))) -> 🔴 PEDIR AHORA — 195 uds (stock cubre 1,3 meses, lead time 4 meses) | Q8: =IF(B8="","",IF(OR(M8=0,M8=""),999,ROUND(D8/M8,1))) -> 1.3
A9: =IF('Catálogo Productos'!B6<>"",COUNTA('Catálogo Productos'!$B$4:$B6),"") -> 3 | B9: =IF('Catálogo Productos'!B6<>"",'Catálogo Productos'!B6,"") -> Cuerdas Alice Electrica L | C9: =IF('Catálogo Productos'!B6<>"",'Catálogo Productos'!C6,"") -> Guitarra Electrica | D9: 55 | E9: =IF('Catálogo Productos'!B6<>"",COUNTIF('Abril 2026 - Ventas'!$C$5:$C$303,'Catálogo Productos'!B6),"") -> 10 | F9: =IF('Catálogo Productos'!B6<>"",'Configuración'!$C$4,"") -> 31 | G9: =IF(OR(NOT('Catálogo Productos'!B6<>""),E9="",E9=0),IF('Catálogo Productos'!B6<>"","Sin ventas",""),IF(M9=0,"Sin ventas",ROUND(F9/M9,1))) -> 1 | H9: =IF(OR(NOT('Catálogo Productos'!B6<>""),D9="",D9=0),IF('Catálogo Productos'!B6<>"",IF(E9=0,"∞ (sin ventas)","🔴 Sin stock"),""),IF(G9="Sin ventas","∞ (sin ventas)",ROUND(D9*G9,0))) -> 55 | I9: =IF(OR(NOT('Catálogo Productos'!B6<>""),H9="",ISNUMBER(SEARCH("∞",TEXT(H9,"@"))),ISNUMBER(SEARCH("🔴",TEXT(H9,"@")))),"",TODAY()+H9) -> 46198 | J9: =IF(NOT('Catálogo Productos'!B6<>""),"",IF(OR(G9="Sin ventas",G9=""),"⚪ Sin ventas este mes",IF(G9<=15,"🔥 Rotación rápida",IF(G9<=30,"✅ Rotación normal","🐢 Rotación lenta")))) -> 🔥 Rotación rápida | K9: =IF('Catálogo Productos'!B6<>"",'Catálogo Productos'!G6,"") -> 20 | L9: =IF(NOT(B9<>""),"",IF(D9=0,"🔴 REPONER YA",IF(OR(M9=0,M9=""),"🟢 Sin prisa",IF(Q9<'Configuración'!$C$9,"🔴 PEDIR AHORA",IF(Q9<('Configuración'!$C$9+'Configuración'!$C$10),"🟡 Reponer pronto","🟢 Sin prisa"))))) -> 🔴 PEDIR AHORA | M9: =IF(B9="","",IF(OR(E9="",E9=0),0,ROUND(E9*('Configuración'!$C$4/'Configuración'!$C$11),1))) -> 31 | N9: =IF(B9="","",IF(M9=0,"—",MAX(0,CEILING(M9*('Configuración'!$C$9+'Configuración'!$C$10)-D9,1)))) -> 100 | O9: =IF(B9="","",IF(ISNUMBER(I9),I9-135,"—")) -> 46063 | P9: =IF(B9="","",IF(D9=0,"🔴 PEDIR URGENTE — sin stock",IF(OR(M9=0,M9=""),"⚪ Sin demanda — monitorear",IF(Q9<'Configuración'!$C$9,"🔴 PEDIR AHORA — "&N9&" uds (stock cubre "&Q9&" meses, lead time "&'Configuración'!$C$9&" meses)",IF(Q9<('Configuración'!$C$9+'Configuración'!$C$10),"🟡 VIGILAR — "&N9&" uds (cubre "&Q9&" meses, al límite del lead time)","🟢 OK — stock cubre "&Q9&" meses"))))) -> 🔴 PEDIR AHORA — 100 uds (stock cubre 1,8 meses, lead time 4 meses) | Q9: =IF(B9="","",IF(OR(M9=0,M9=""),999,ROUND(D9/M9,1))) -> 1.8
A10: =IF('Catálogo Productos'!B7<>"",COUNTA('Catálogo Productos'!$B$4:$B7),"") -> 4 | B10: =IF('Catálogo Productos'!B7<>"",'Catálogo Productos'!B7,"") -> Cuerdas Alice Folk 11-52 | C10: =IF('Catálogo Productos'!B7<>"",'Catálogo Productos'!C7,"") -> Guitarra Acustica | D10: =IF('Catálogo Productos'!B7<>"",'Catálogo Productos'!H62,"") -> 59 | E10: =IF('Catálogo Productos'!B7<>"",COUNTIF('Abril 2026 - Ventas'!$C$5:$C$303,'Catálogo Productos'!B7),"") -> 6 | F10: =IF('Catálogo Productos'!B7<>"",'Configuración'!$C$4,"") -> 31 | G10: =IF(OR(NOT('Catálogo Productos'!B7<>""),E10="",E10=0),IF('Catálogo Productos'!B7<>"","Sin ventas",""),IF(M10=0,"Sin ventas",ROUND(F10/M10,1))) -> 1.7 | H10: =IF(OR(NOT('Catálogo Productos'!B7<>""),D10="",D10=0),IF('Catálogo Productos'!B7<>"",IF(E10=0,"∞ (sin ventas)","🔴 Sin stock"),""),IF(G10="Sin ventas","∞ (sin ventas)",ROUND(D10*G10,0))) -> 100 | I10: =IF(OR(NOT('Catálogo Productos'!B7<>""),H10="",ISNUMBER(SEARCH("∞",TEXT(H10,"@"))),ISNUMBER(SEARCH("🔴",TEXT(H10,"@")))),"",TODAY()+H10) -> 46243 | J10: =IF(NOT('Catálogo Productos'!B7<>""),"",IF(OR(G10="Sin ventas",G10=""),"⚪ Sin ventas este mes",IF(G10<=15,"🔥 Rotación rápida",IF(G10<=30,"✅ Rotación normal","🐢 Rotación lenta")))) -> 🔥 Rotación rápida | K10: =IF('Catálogo Productos'!B7<>"",'Catálogo Productos'!G7,"") -> 20 | L10: =IF(NOT(B10<>""),"",IF(D10=0,"🔴 REPONER YA",IF(OR(M10=0,M10=""),"🟢 Sin prisa",IF(Q10<'Configuración'!$C$9,"🔴 PEDIR AHORA",IF(Q10<('Configuración'!$C$9+'Configuración'!$C$10),"🟡 Reponer pronto","🟢 Sin prisa"))))) -> 🔴 PEDIR AHORA | M10: =IF(B10="","",IF(OR(E10="",E10=0),0,ROUND(E10*('Configuración'!$C$4/'Configuración'!$C$11),1))) -> 18.6 | N10: =IF(B10="","",IF(M10=0,"—",MAX(0,CEILING(M10*('Configuración'!$C$9+'Configuración'!$C$10)-D10,1)))) -> 34 | O10: =IF(B10="","",IF(ISNUMBER(I10),I10-135,"—")) -> 46108 | P10: =IF(B10="","",IF(D10=0,"🔴 PEDIR URGENTE — sin stock",IF(OR(M10=0,M10=""),"⚪ Sin demanda — monitorear",IF(Q10<'Configuración'!$C$9,"🔴 PEDIR AHORA — "&N10&" uds (stock cubre "&Q10&" meses, lead time "&'Configuración'!$C$9&" meses)",IF(Q10<('Configuración'!$C$9+'Configuración'!$C$10),"🟡 VIGILAR — "&N10&" uds (cubre "&Q10&" meses, al límite del lead time)","🟢 OK — stock cubre "&Q10&" meses"))))) -> 🔴 PEDIR AHORA — 34 uds (stock cubre 3,2 meses, lead time 4 meses) | Q10: =IF(B10="","",IF(OR(M10=0,M10=""),999,ROUND(D10/M10,1))) -> 3.2
A11: =IF('Catálogo Productos'!B8<>"",COUNTA('Catálogo Productos'!$B$4:$B8),"") -> 5 | B11: =IF('Catálogo Productos'!B8<>"",'Catálogo Productos'!B8,"") -> Hombrera Violin 3/4 4/4 | C11: =IF('Catálogo Productos'!B8<>"",'Catálogo Productos'!C8,"") -> Violin | D11: =IF('Catálogo Productos'!B8<>"",'Catálogo Productos'!H63,"") -> 32 | E11: =IF('Catálogo Productos'!B8<>"",COUNTIF('Abril 2026 - Ventas'!$C$5:$C$303,'Catálogo Productos'!B8),"") -> 9 | F11: =IF('Catálogo Productos'!B8<>"",'Configuración'!$C$4,"") -> 31 | G11: =IF(OR(NOT('Catálogo Productos'!B8<>""),E11="",E11=0),IF('Catálogo Productos'!B8<>"","Sin ventas",""),IF(M11=0,"Sin ventas",ROUND(F11/M11,1))) -> 1.1 | H11: =IF(OR(NOT('Catálogo Productos'!B8<>""),D11="",D11=0),IF('Catálogo Productos'!B8<>"",IF(E11=0,"∞ (sin ventas)","🔴 Sin stock"),""),IF(G11="Sin ventas","∞ (sin ventas)",ROUND(D11*G11,0))) -> 35 | I11: =IF(OR(NOT('Catálogo Productos'!B8<>""),H11="",ISNUMBER(SEARCH("∞",TEXT(H11,"@"))),ISNUMBER(SEARCH("🔴",TEXT(H11,"@")))),"",TODAY()+H11) -> 46178 | J11: =IF(NOT('Catálogo Productos'!B8<>""),"",IF(OR(G11="Sin ventas",G11=""),"⚪ Sin ventas este mes",IF(G11<=15,"🔥 Rotación rápida",IF(G11<=30,"✅ Rotación normal","🐢 Rotación lenta")))) -> 🔥 Rotación rápida | K11: =IF('Catálogo Productos'!B8<>"",'Catálogo Productos'!G8,"") -> 20 | L11: =IF(NOT(B11<>""),"",IF(D11=0,"🔴 REPONER YA",IF(OR(M11=0,M11=""),"🟢 Sin prisa",IF(Q11<'Configuración'!$C$9,"🔴 PEDIR AHORA",IF(Q11<('Configuración'!$C$9+'Configuración'!$C$10),"🟡 Reponer pronto","🟢 Sin prisa"))))) -> 🔴 PEDIR AHORA | M11: =IF(B11="","",IF(OR(E11="",E11=0),0,ROUND(E11*('Configuración'!$C$4/'Configuración'!$C$11),1))) -> 27.9 | N11: =IF(B11="","",IF(M11=0,"—",MAX(0,CEILING(M11*('Configuración'!$C$9+'Configuración'!$C$10)-D11,1)))) -> 108 | O11: =IF(B11="","",IF(ISNUMBER(I11),I11-135,"—")) -> 46043 | P11: =IF(B11="","",IF(D11=0,"🔴 PEDIR URGENTE — sin stock",IF(OR(M11=0,M11=""),"⚪ Sin demanda — monitorear",IF(Q11<'Configuración'!$C$9,"🔴 PEDIR AHORA — "&N11&" uds (stock cubre "&Q11&" meses, lead time "&'Configuración'!$C$9&" meses)",IF(Q11<('Configuración'!$C$9+'Configuración'!$C$10),"🟡 VIGILAR — "&N11&" uds (cubre "&Q11&" meses, al límite del lead time)","🟢 OK — stock cubre "&Q11&" meses"))))) -> 🔴 PEDIR AHORA — 108 uds (stock cubre 1,1 meses, lead time 4 meses) | Q11: =IF(B11="","",IF(OR(M11=0,M11=""),999,ROUND(D11/M11,1))) -> 1.1
A12: =IF('Catálogo Productos'!B9<>"",COUNTA('Catálogo Productos'!$B$4:$B9),"") -> 6 | B12: =IF('Catálogo Productos'!B9<>"",'Catálogo Productos'!B9,"") -> Clavijas Guitarra Clasica Doradas | C12: =IF('Catálogo Productos'!B9<>"",'Catálogo Productos'!C9,"") -> Guitarra Clasica | D12: 14 | E12: =IF('Catálogo Productos'!B9<>"",COUNTIF('Abril 2026 - Ventas'!$C$5:$C$303,'Catálogo Productos'!B9),"") -> 6 | F12: =IF('Catálogo Productos'!B9<>"",'Configuración'!$C$4,"") -> 31 | G12: =IF(OR(NOT('Catálogo Productos'!B9<>""),E12="",E12=0),IF('Catálogo Productos'!B9<>"","Sin ventas",""),IF(M12=0,"Sin ventas",ROUND(F12/M12,1))) -> 1.7 | H12: =IF(OR(NOT('Catálogo Productos'!B9<>""),D12="",D12=0),IF('Catálogo Productos'!B9<>"",IF(E12=0,"∞ (sin ventas)","🔴 Sin stock"),""),IF(G12="Sin ventas","∞ (sin ventas)",ROUND(D12*G12,0))) -> 24 | I12: =IF(OR(NOT('Catálogo Productos'!B9<>""),H12="",ISNUMBER(SEARCH("∞",TEXT(H12,"@"))),ISNUMBER(SEARCH("🔴",TEXT(H12,"@")))),"",TODAY()+H12) -> 46167 | J12: =IF(NOT('Catálogo Productos'!B9<>""),"",IF(OR(G12="Sin ventas",G12=""),"⚪ Sin ventas este mes",IF(G12<=15,"🔥 Rotación rápida",IF(G12<=30,"✅ Rotación normal","🐢 Rotación lenta")))) -> 🔥 Rotación rápida | K12: =IF('Catálogo Productos'!B9<>"",'Catálogo Productos'!G9,"") -> 5 | L12: =IF(NOT(B12<>""),"",IF(D12=0,"🔴 REPONER YA",IF(OR(M12=0,M12=""),"🟢 Sin prisa",IF(Q12<'Configuración'!$C$9,"🔴 PEDIR AHORA",IF(Q12<('Configuración'!$C$9+'Configuración'!$C$10),"🟡 Reponer pronto","🟢 Sin prisa"))))) -> 🔴 PEDIR AHORA | M12: =IF(B12="","",IF(OR(E12="",E12=0),0,ROUND(E12*('Configuración'!$C$4/'Configuración'!$C$11),1))) -> 18.6 | N12: =IF(B12="","",IF(M12=0,"—",MAX(0,CEILING(M12*('Configuración'!$C$9+'Configuración'!$C$10)-D12,1)))) -> 79 | O12: =IF(B12="","",IF(ISNUMBER(I12),I12-135,"—")) -> 46032 | P12: =IF(B12="","",IF(D12=0,"🔴 PEDIR URGENTE — sin stock",IF(OR(M12=0,M12=""),"⚪ Sin demanda — monitorear",IF(Q12<'Configuración'!$C$9,"🔴 PEDIR AHORA — "&N12&" uds (stock cubre "&Q12&" meses, lead time "&'Configuración'!$C$9&" meses)",IF(Q12<('Configuración'!$C$9+'Configuración'!$C$10),"🟡 VIGILAR — "&N12&" uds (cubre "&Q12&" meses, al límite del lead time)","🟢 OK — stock cubre "&Q12&" meses"))))) -> 🔴 PEDIR AHORA — 79 uds (stock cubre 0,8 meses, lead time 4 meses) | Q12: =IF(B12="","",IF(OR(M12=0,M12=""),999,ROUND(D12/M12,1))) -> 0.8
A13: =IF('Catálogo Productos'!B10<>"",COUNTA('Catálogo Productos'!$B$4:$B10),"") -> 7 | B13: =IF('Catálogo Productos'!B10<>"",'Catálogo Productos'!B10,"") -> Clavijas Guitarra Clasica Plateadas | C13: =IF('Catálogo Productos'!B10<>"",'Catálogo Productos'!C10,"") -> Guitarra Clasica | D13: =IF('Catálogo Productos'!B10<>"",'Catálogo Productos'!H65,"") -> 10 | E13: =IF('Catálogo Productos'!B10<>"",COUNTIF('Abril 2026 - Ventas'!$C$5:$C$303,'Catálogo Productos'!B10),"") -> 5 | F13: =IF('Catálogo Productos'!B10<>"",'Configuración'!$C$4,"") -> 31 | G13: =IF(OR(NOT('Catálogo Productos'!B10<>""),E13="",E13=0),IF('Catálogo Productos'!B10<>"","Sin ventas",""),IF(M13=0,"Sin ventas",ROUND(F13/M13,1))) -> 2 | H13: =IF(OR(NOT('Catálogo Productos'!B10<>""),D13="",D13=0),IF('Catálogo Productos'!B10<>"",IF(E13=0,"∞ (sin ventas)","🔴 Sin stock"),""),IF(G13="Sin ventas","∞ (sin ventas)",ROUND(D13*G13,0))) -> 20 | I13: =IF(OR(NOT('Catálogo Productos'!B10<>""),H13="",ISNUMBER(SEARCH("∞",TEXT(H13,"@"))),ISNUMBER(SEARCH("🔴",TEXT(H13,"@")))),"",TODAY()+H13) -> 46163 | J13: =IF(NOT('Catálogo Productos'!B10<>""),"",IF(OR(G13="Sin ventas",G13=""),"⚪ Sin ventas este mes",IF(G13<=15,"🔥 Rotación rápida",IF(G13<=30,"✅ Rotación normal","🐢 Rotación lenta")))) -> 🔥 Rotación rápida | K13: =IF('Catálogo Productos'!B10<>"",'Catálogo Productos'!G10,"") -> 5 | L13: =IF(NOT(B13<>""),"",IF(D13=0,"🔴 REPONER YA",IF(OR(M13=0,M13=""),"🟢 Sin prisa",IF(Q13<'Configuración'!$C$9,"🔴 PEDIR AHORA",IF(Q13<('Configuración'!$C$9+'Configuración'!$C$10),"🟡 Reponer pronto","🟢 Sin prisa"))))) -> 🔴 PEDIR AHORA | M13: =IF(B13="","",IF(OR(E13="",E13=0),0,ROUND(E13*('Configuración'!$C$4/'Configuración'!$C$11),1))) -> 15.5 | N13: =IF(B13="","",IF(M13=0,"—",MAX(0,CEILING(M13*('Configuración'!$C$9+'Configuración'!$C$10)-D13,1)))) -> 68 | O13: =IF(B13="","",IF(ISNUMBER(I13),I13-135,"—")) -> 46028 | P13: =IF(B13="","",IF(D13=0,"🔴 PEDIR URGENTE — sin stock",IF(OR(M13=0,M13=""),"⚪ Sin demanda — monitorear",IF(Q13<'Configuración'!$C$9,"🔴 PEDIR AHORA — "&N13&" uds (stock cubre "&Q13&" meses, lead time "&'Configuración'!$C$9&" meses)",IF(Q13<('Configuración'!$C$9+'Configuración'!$C$10),"🟡 VIGILAR — "&N13&" uds (cubre "&Q13&" meses, al límite del lead time)","🟢 OK — stock cubre "&Q13&" meses"))))) -> 🔴 PEDIR AHORA — 68 uds (stock cubre 0,6 meses, lead time 4 meses) | Q13: =IF(B13="","",IF(OR(M13=0,M13=""),999,ROUND(D13/M13,1))) -> 0.6
A14: =IF('Catálogo Productos'!B11<>"",COUNTA('Catálogo Productos'!$B$4:$B11),"") -> 8 | B14: =IF('Catálogo Productos'!B11<>"",'Catálogo Productos'!B11,"") -> Correa Guitarra/Bajo | C14: =IF('Catálogo Productos'!B11<>"",'Catálogo Productos'!C11,"") -> Correas | D14: =IF('Catálogo Productos'!B11<>"",'Catálogo Productos'!H66,"") -> 21 | E14: =IF('Catálogo Productos'!B11<>"",COUNTIF('Abril 2026 - Ventas'!$C$5:$C$303,'Catálogo Productos'!B11),"") -> 3 | F14: =IF('Catálogo Productos'!B11<>"",'Configuración'!$C$4,"") -> 31 | G14: =IF(OR(NOT('Catálogo Productos'!B11<>""),E14="",E14=0),IF('Catálogo Productos'!B11<>"","Sin ventas",""),IF(M14=0,"Sin ventas",ROUND(F14/M14,1))) -> 3.3 | H14: =IF(OR(NOT('Catálogo Productos'!B11<>""),D14="",D14=0),IF('Catálogo Productos'!B11<>"",IF(E14=0,"∞ (sin ventas)","🔴 Sin stock"),""),IF(G14="Sin ventas","∞ (sin ventas)",ROUND(D14*G14,0))) -> 69 | I14: =IF(OR(NOT('Catálogo Productos'!B11<>""),H14="",ISNUMBER(SEARCH("∞",TEXT(H14,"@"))),ISNUMBER(SEARCH("🔴",TEXT(H14,"@")))),"",TODAY()+H14) -> 46212 | J14: =IF(NOT('Catálogo Productos'!B11<>""),"",IF(OR(G14="Sin ventas",G14=""),"⚪ Sin ventas este mes",IF(G14<=15,"🔥 Rotación rápida",IF(G14<=30,"✅ Rotación normal","🐢 Rotación lenta")))) -> 🔥 Rotación rápida | K14: =IF('Catálogo Productos'!B11<>"",'Catálogo Productos'!G11,"") -> 10 | L14: =IF(NOT(B14<>""),"",IF(D14=0,"🔴 REPONER YA",IF(OR(M14=0,M14=""),"🟢 Sin prisa",IF(Q14<'Configuración'!$C$9,"🔴 PEDIR AHORA",IF(Q14<('Configuración'!$C$9+'Configuración'!$C$10),"🟡 Reponer pronto","🟢 Sin prisa"))))) -> 🔴 PEDIR AHORA | M14: =IF(B14="","",IF(OR(E14="",E14=0),0,ROUND(E14*('Configuración'!$C$4/'Configuración'!$C$11),1))) -> 9.3 | N14: =IF(B14="","",IF(M14=0,"—",MAX(0,CEILING(M14*('Configuración'!$C$9+'Configuración'!$C$10)-D14,1)))) -> 26 | O14: =IF(B14="","",IF(ISNUMBER(I14),I14-135,"—")) -> 46077 | P14: =IF(B14="","",IF(D14=0,"🔴 PEDIR URGENTE — sin stock",IF(OR(M14=0,M14=""),"⚪ Sin demanda — monitorear",IF(Q14<'Configuración'!$C$9,"🔴 PEDIR AHORA — "&N14&" uds (stock cubre "&Q14&" meses, lead time "&'Configuración'!$C$9&" meses)",IF(Q14<('Configuración'!$C$9+'Configuración'!$C$10),"🟡 VIGILAR — "&N14&" uds (cubre "&Q14&" meses, al límite del lead time)","🟢 OK — stock cubre "&Q14&" meses"))))) -> 🔴 PEDIR AHORA — 26 uds (stock cubre 2,3 meses, lead time 4 meses) | Q14: =IF(B14="","",IF(OR(M14=0,M14=""),999,ROUND(D14/M14,1))) -> 2.3
A15: =IF('Catálogo Productos'!B12<>"",COUNTA('Catálogo Productos'!$B$4:$B12),"") -> 9 | B15: =IF('Catálogo Productos'!B12<>"",'Catálogo Productos'!B12,"") -> Base pared Guitarra/Bajo | C15: =IF('Catálogo Productos'!B12<>"",'Catálogo Productos'!C12,"") -> Bases, Stand, Atriles | D15: =IF('Catálogo Productos'!B12<>"",'Catálogo Productos'!H67,"") -> 58 | E15: =IF('Catálogo Productos'!B12<>"",COUNTIF('Abril 2026 - Ventas'!$C$5:$C$303,'Catálogo Productos'!B12),"") -> 23 | F15: =IF('Catálogo Productos'!B12<>"",'Configuración'!$C$4,"") -> 31 | G15: =IF(OR(NOT('Catálogo Productos'!B12<>""),E15="",E15=0),IF('Catálogo Productos'!B12<>"","Sin ventas",""),IF(M15=0,"Sin ventas",ROUND(F15/M15,1))) -> 0.4 | H15: =IF(OR(NOT('Catálogo Productos'!B12<>""),D15="",D15=0),IF('Catálogo Productos'!B12<>"",IF(E15=0,"∞ (sin ventas)","🔴 Sin stock"),""),IF(G15="Sin ventas","∞ (sin ventas)",ROUND(D15*G15,0))) -> 23 | I15: =IF(OR(NOT('Catálogo Productos'!B12<>""),H15="",ISNUMBER(SEARCH("∞",TEXT(H15,"@"))),ISNUMBER(SEARCH("🔴",TEXT(H15,"@")))),"",TODAY()+H15) -> 46166 | J15: =IF(NOT('Catálogo Productos'!B12<>""),"",IF(OR(G15="Sin ventas",G15=""),"⚪ Sin ventas este mes",IF(G15<=15,"🔥 Rotación rápida",IF(G15<=30,"✅ Rotación normal","🐢 Rotación lenta")))) -> 🔥 Rotación rápida | K15: =IF('Catálogo Productos'!B12<>"",'Catálogo Productos'!G12,"") -> 20 | L15: =IF(NOT(B15<>""),"",IF(D15=0,"🔴 REPONER YA",IF(OR(M15=0,M15=""),"🟢 Sin prisa",IF(Q15<'Configuración'!$C$9,"🔴 PEDIR AHORA",IF(Q15<('Configuración'!$C$9+'Configuración'!$C$10),"🟡 Reponer pronto","🟢 Sin prisa"))))) -> 🔴 PEDIR AHORA | M15: =IF(B15="","",IF(OR(E15="",E15=0),0,ROUND(E15*('Configuración'!$C$4/'Configuración'!$C$11),1))) -> 71.3 | N15: =IF(B15="","",IF(M15=0,"—",MAX(0,CEILING(M15*('Configuración'!$C$9+'Configuración'!$C$10)-D15,1)))) -> 299 | O15: =IF(B15="","",IF(ISNUMBER(I15),I15-135,"—")) -> 46031 | P15: =IF(B15="","",IF(D15=0,"🔴 PEDIR URGENTE — sin stock",IF(OR(M15=0,M15=""),"⚪ Sin demanda — monitorear",IF(Q15<'Configuración'!$C$9,"🔴 PEDIR AHORA — "&N15&" uds (stock cubre "&Q15&" meses, lead time "&'Configuración'!$C$9&" meses)",IF(Q15<('Configuración'!$C$9+'Configuración'!$C$10),"🟡 VIGILAR — "&N15&" uds (cubre "&Q15&" meses, al límite del lead time)","🟢 OK — stock cubre "&Q15&" meses"))))) -> 🔴 PEDIR AHORA — 299 uds (stock cubre 0,8 meses, lead time 4 meses) | Q15: =IF(B15="","",IF(OR(M15=0,M15=""),999,ROUND(D15/M15,1))) -> 0.8
A16: =IF('Catálogo Productos'!B13<>"",COUNTA('Catálogo Productos'!$B$4:$B13),"") -> 10 | B16: =IF('Catálogo Productos'!B13<>"",'Catálogo Productos'!B13,"") -> Capotraste | C16: =IF('Catálogo Productos'!B13<>"",'Catálogo Productos'!C13,"") -> Capostraste | D16: =IF('Catálogo Productos'!B13<>"",'Catálogo Productos'!H68,"") -> 21 | E16: =IF('Catálogo Productos'!B13<>"",COUNTIF('Abril 2026 - Ventas'!$C$5:$C$303,'Catálogo Productos'!B13),"") -> 4 | F16: =IF('Catálogo Productos'!B13<>"",'Configuración'!$C$4,"") -> 31 | G16: =IF(OR(NOT('Catálogo Productos'!B13<>""),E16="",E16=0),IF('Catálogo Productos'!B13<>"","Sin ventas",""),IF(M16=0,"Sin ventas",ROUND(F16/M16,1))) -> 2.5 | H16: =IF(OR(NOT('Catálogo Productos'!B13<>""),D16="",D16=0),IF('Catálogo Productos'!B13<>"",IF(E16=0,"∞ (sin ventas)","🔴 Sin stock"),""),IF(G16="Sin ventas","∞ (sin ventas)",ROUND(D16*G16,0))) -> 53 | I16: =IF(OR(NOT('Catálogo Productos'!B13<>""),H16="",ISNUMBER(SEARCH("∞",TEXT(H16,"@"))),ISNUMBER(SEARCH("🔴",TEXT(H16,"@")))),"",TODAY()+H16) -> 46196 | J16: =IF(NOT('Catálogo Productos'!B13<>""),"",IF(OR(G16="Sin ventas",G16=""),"⚪ Sin ventas este mes",IF(G16<=15,"🔥 Rotación rápida",IF(G16<=30,"✅ Rotación normal","🐢 Rotación lenta")))) -> 🔥 Rotación rápida | K16: =IF('Catálogo Productos'!B13<>"",'Catálogo Productos'!G13,"") -> 10 | L16: =IF(NOT(B16<>""),"",IF(D16=0,"🔴 REPONER YA",IF(OR(M16=0,M16=""),"🟢 Sin prisa",IF(Q16<'Configuración'!$C$9,"🔴 PEDIR AHORA",IF(Q16<('Configuración'!$C$9+'Configuración'!$C$10),"🟡 Reponer pronto","🟢 Sin prisa"))))) -> 🔴 PEDIR AHORA | M16: =IF(B16="","",IF(OR(E16="",E16=0),0,ROUND(E16*('Configuración'!$C$4/'Configuración'!$C$11),1))) -> 12.4 | N16: =IF(B16="","",IF(M16=0,"—",MAX(0,CEILING(M16*('Configuración'!$C$9+'Configuración'!$C$10)-D16,1)))) -> 41 | O16: =IF(B16="","",IF(ISNUMBER(I16),I16-135,"—")) -> 46061 | P16: =IF(B16="","",IF(D16=0,"🔴 PEDIR URGENTE — sin stock",IF(OR(M16=0,M16=""),"⚪ Sin demanda — monitorear",IF(Q16<'Configuración'!$C$9,"🔴 PEDIR AHORA — "&N16&" uds (stock cubre "&Q16&" meses, lead time "&'Configuración'!$C$9&" meses)",IF(Q16<('Configuración'!$C$9+'Configuración'!$C$10),"🟡 VIGILAR — "&N16&" uds (cubre "&Q16&" meses, al límite del lead time)","🟢 OK — stock cubre "&Q16&" meses"))))) -> 🔴 PEDIR AHORA — 41 uds (stock cubre 1,7 meses, lead time 4 meses) | Q16: =IF(B16="","",IF(OR(M16=0,M16=""),999,ROUND(D16/M16,1))) -> 1.7
A17: =IF('Catálogo Productos'!B14<>"",COUNTA('Catálogo Productos'!$B$4:$B14),"") -> 11 | B17: =IF('Catálogo Productos'!B14<>"",'Catálogo Productos'!B14,"") -> Cuerdas de Violin 4/4 | C17: =IF('Catálogo Productos'!B14<>"",'Catálogo Productos'!C14,"") -> Violin | D17: =IF('Catálogo Productos'!B14<>"",'Catálogo Productos'!H69,"") -> 40 | E17: =IF('Catálogo Productos'!B14<>"",COUNTIF('Abril 2026 - Ventas'!$C$5:$C$303,'Catálogo Productos'!B14),"") -> 3 | F17: =IF('Catálogo Productos'!B14<>"",'Configuración'!$C$4,"") -> 31 | G17: =IF(OR(NOT('Catálogo Productos'!B14<>""),E17="",E17=0),IF('Catálogo Productos'!B14<>"","Sin ventas",""),IF(M17=0,"Sin ventas",ROUND(F17/M17,1))) -> 3.3 | H17: =IF(OR(NOT('Catálogo Productos'!B14<>""),D17="",D17=0),IF('Catálogo Productos'!B14<>"",IF(E17=0,"∞ (sin ventas)","🔴 Sin stock"),""),IF(G17="Sin ventas","∞ (sin ventas)",ROUND(D17*G17,0))) -> 132 | I17: =IF(OR(NOT('Catálogo Productos'!B14<>""),H17="",ISNUMBER(SEARCH("∞",TEXT(H17,"@"))),ISNUMBER(SEARCH("🔴",TEXT(H17,"@")))),"",TODAY()+H17) -> 46275 | J17: =IF(NOT('Catálogo Productos'!B14<>""),"",IF(OR(G17="Sin ventas",G17=""),"⚪ Sin ventas este mes",IF(G17<=15,"🔥 Rotación rápida",IF(G17<=30,"✅ Rotación normal","🐢 Rotación lenta")))) -> 🔥 Rotación rápida | K17: =IF('Catálogo Productos'!B14<>"",'Catálogo Productos'!G14,"") -> 10 | L17: =IF(NOT(B17<>""),"",IF(D17=0,"🔴 REPONER YA",IF(OR(M17=0,M17=""),"🟢 Sin prisa",IF(Q17<'Configuración'!$C$9,"🔴 PEDIR AHORA",IF(Q17<('Configuración'!$C$9+'Configuración'!$C$10),"🟡 Reponer pronto","🟢 Sin prisa"))))) -> 🟡 Reponer pronto | M17: =IF(B17="","",IF(OR(E17="",E17=0),0,ROUND(E17*('Configuración'!$C$4/'Configuración'!$C$11),1))) -> 9.3 | N17: =IF(B17="","",IF(M17=0,"—",MAX(0,CEILING(M17*('Configuración'!$C$9+'Configuración'!$C$10)-D17,1)))) -> 7 | O17: =IF(B17="","",IF(ISNUMBER(I17),I17-135,"—")) -> 46140 | P17: =IF(B17="","",IF(D17=0,"🔴 PEDIR URGENTE — sin stock",IF(OR(M17=0,M17=""),"⚪ Sin demanda — monitorear",IF(Q17<'Configuración'!$C$9,"🔴 PEDIR AHORA — "&N17&" uds (stock cubre "&Q17&" meses, lead time "&'Configuración'!$C$9&" meses)",IF(Q17<('Configuración'!$C$9+'Configuración'!$C$10),"🟡 VIGILAR — "&N17&" uds (cubre "&Q17&" meses, al límite del lead time)","🟢 OK — stock cubre "&Q17&" meses"))))) -> 🟡 VIGILAR — 7 uds (cubre 4,3 meses, al límite del lead time) | Q17: =IF(B17="","",IF(OR(M17=0,M17=""),999,ROUND(D17/M17,1))) -> 4.3
A18: =IF('Catálogo Productos'!B15<>"",COUNTA('Catálogo Productos'!$B$4:$B15),"") -> 12 | B18: =IF('Catálogo Productos'!B15<>"",'Catálogo Productos'!B15,"") -> Cable Hebikuo XA03 | C18: =IF('Catálogo Productos'!B15<>"",'Catálogo Productos'!C15,"") -> Cables | D18: =IF('Catálogo Productos'!B15<>"",'Catálogo Productos'!H70,"") -> 13 | E18: =IF('Catálogo Productos'!B15<>"",COUNTIF('Abril 2026 - Ventas'!$C$5:$C$303,'Catálogo Productos'!B15),"") -> 13 | F18: =IF('Catálogo Productos'!B15<>"",'Configuración'!$C$4,"") -> 31 | G18: =IF(OR(NOT('Catálogo Productos'!B15<>""),E18="",E18=0),IF('Catálogo Productos'!B15<>"","Sin ventas",""),IF(M18=0,"Sin ventas",ROUND(F18/M18,1))) -> 0.8 | H18: =IF(OR(NOT('Catálogo Productos'!B15<>""),D18="",D18=0),IF('Catálogo Productos'!B15<>"",IF(E18=0,"∞ (sin ventas)","🔴 Sin stock"),""),IF(G18="Sin ventas","∞ (sin ventas)",ROUND(D18*G18,0))) -> 10 | I18: =IF(OR(NOT('Catálogo Productos'!B15<>""),H18="",ISNUMBER(SEARCH("∞",TEXT(H18,"@"))),ISNUMBER(SEARCH("🔴",TEXT(H18,"@")))),"",TODAY()+H18) -> 46153 | J18: =IF(NOT('Catálogo Productos'!B15<>""),"",IF(OR(G18="Sin ventas",G18=""),"⚪ Sin ventas este mes",IF(G18<=15,"🔥 Rotación rápida",IF(G18<=30,"✅ Rotación normal","🐢 Rotación lenta")))) -> 🔥 Rotación rápida | K18: =IF('Catálogo Productos'!B15<>"",'Catálogo Productos'!G15,"") -> 10 | L18: =IF(NOT(B18<>""),"",IF(D18=0,"🔴 REPONER YA",IF(OR(M18=0,M18=""),"🟢 Sin prisa",IF(Q18<'Configuración'!$C$9,"🔴 PEDIR AHORA",IF(Q18<('Configuración'!$C$9+'Configuración'!$C$10),"🟡 Reponer pronto","🟢 Sin prisa"))))) -> 🔴 PEDIR AHORA | M18: =IF(B18="","",IF(OR(E18="",E18=0),0,ROUND(E18*('Configuración'!$C$4/'Configuración'!$C$11),1))) -> 40.3 | N18: =IF(B18="","",IF(M18=0,"—",MAX(0,CEILING(M18*('Configuración'!$C$9+'Configuración'!$C$10)-D18,1)))) -> 189 | O18: =IF(B18="","",IF(ISNUMBER(I18),I18-135,"—")) -> 46018 | P18: =IF(B18="","",IF(D18=0,"🔴 PEDIR URGENTE — sin stock",IF(OR(M18=0,M18=""),"⚪ Sin demanda — monitorear",IF(Q18<'Configuración'!$C$9,"🔴 PEDIR AHORA — "&N18&" uds (stock cubre "&Q18&" meses, lead time "&'Configuración'!$C$9&" meses)",IF(Q18<('Configuración'!$C$9+'Configuración'!$C$10),"🟡 VIGILAR — "&N18&" uds (cubre "&Q18&" meses, al límite del lead time)","🟢 OK — stock cubre "&Q18&" meses"))))) -> 🔴 PEDIR AHORA — 189 uds (stock cubre 0,3 meses, lead time 4 meses) | Q18: =IF(B18="","",IF(OR(M18=0,M18=""),999,ROUND(D18/M18,1))) -> 0.3
A19: =IF('Catálogo Productos'!B16<>"",COUNTA('Catálogo Productos'!$B$4:$B16),"") -> 13 | B19: =IF('Catálogo Productos'!B16<>"",'Catálogo Productos'!B16,"") -> Cejilla/Cejuela | C19: =IF('Catálogo Productos'!B16<>"",'Catálogo Productos'!C16,"") -> Guitarra Clasica | D19: 50 | E19: =IF('Catálogo Productos'!B16<>"",COUNTIF('Abril 2026 - Ventas'!$C$5:$C$303,'Catálogo Productos'!B16),"") -> 3 | F19: =IF('Catálogo Productos'!B16<>"",'Configuración'!$C$4,"") -> 31 | G19: =IF(OR(NOT('Catálogo Productos'!B16<>""),E19="",E19=0),IF('Catálogo Productos'!B16<>"","Sin ventas",""),IF(M19=0,"Sin ventas",ROUND(F19/M19,1))) -> 3.3 | H19: =IF(OR(NOT('Catálogo Productos'!B16<>""),D19="",D19=0),IF('Catálogo Productos'!B16<>"",IF(E19=0,"∞ (sin ventas)","🔴 Sin stock"),""),IF(G19="Sin ventas","∞ (sin ventas)",ROUND(D19*G19,0))) -> 165 | I19: =IF(OR(NOT('Catálogo Productos'!B16<>""),H19="",ISNUMBER(SEARCH("∞",TEXT(H19,"@"))),ISNUMBER(SEARCH("🔴",TEXT(H19,"@")))),"",TODAY()+H19) -> 46308 | J19: =IF(NOT('Catálogo Productos'!B16<>""),"",IF(OR(G19="Sin ventas",G19=""),"⚪ Sin ventas este mes",IF(G19<=15,"🔥 Rotación rápida",IF(G19<=30,"✅ Rotación normal","🐢 Rotación lenta")))) -> 🔥 Rotación rápida | K19: =IF('Catálogo Productos'!B16<>"",'Catálogo Productos'!G16,"") -> 20 | L19: =IF(NOT(B19<>""),"",IF(D19=0,"🔴 REPONER YA",IF(OR(M19=0,M19=""),"🟢 Sin prisa",IF(Q19<'Configuración'!$C$9,"🔴 PEDIR AHORA",IF(Q19<('Configuración'!$C$9+'Configuración'!$C$10),"🟡 Reponer pronto","🟢 Sin prisa"))))) -> 🟢 Sin prisa | M19: =IF(B19="","",IF(OR(E19="",E19=0),0,ROUND(E19*('Configuración'!$C$4/'Configuración'!$C$11),1))) -> 9.3 | N19: =IF(B19="","",IF(M19=0,"—",MAX(0,CEILING(M19*('Configuración'!$C$9+'Configuración'!$C$10)-D19,1)))) -> 0 | O19: =IF(B19="","",IF(ISNUMBER(I19),I19-135,"—")) -> 46173 | P19: =IF(B19="","",IF(D19=0,"🔴 PEDIR URGENTE — sin stock",IF(OR(M19=0,M19=""),"⚪ Sin demanda — monitorear",IF(Q19<'Configuración'!$C$9,"🔴 PEDIR AHORA — "&N19&" uds (stock cubre "&Q19&" meses, lead time "&'Configuración'!$C$9&" meses)",IF(Q19<('Configuración'!$C$9+'Configuración'!$C$10),"🟡 VIGILAR — "&N19&" uds (cubre "&Q19&" meses, al límite del lead time)","🟢 OK — stock cubre "&Q19&" meses"))))) -> 🟢 OK — stock cubre 5,4 meses | Q19: =IF(B19="","",IF(OR(M19=0,M19=""),999,ROUND(D19/M19,1))) -> 5.4
A20: =IF('Catálogo Productos'!B17<>"",COUNTA('Catálogo Productos'!$B$4:$B17),"") -> 14 | B20: =IF('Catálogo Productos'!B17<>"",'Catálogo Productos'!B17,"") -> Pines de Correa | C20: =IF('Catálogo Productos'!B17<>"",'Catálogo Productos'!C17,"") -> Guitarra Acustica | D20: 40 | E20: =IF('Catálogo Productos'!B17<>"",COUNTIF('Abril 2026 - Ventas'!$C$5:$C$303,'Catálogo Productos'!B17),"") -> 5 | F20: =IF('Catálogo Productos'!B17<>"",'Configuración'!$C$4,"") -> 31 | G20: =IF(OR(NOT('Catálogo Productos'!B17<>""),E20="",E20=0),IF('Catálogo Productos'!B17<>"","Sin ventas",""),IF(M20=0,"Sin ventas",ROUND(F20/M20,1))) -> 2 | H20: =IF(OR(NOT('Catálogo Productos'!B17<>""),D20="",D20=0),IF('Catálogo Productos'!B17<>"",IF(E20=0,"∞ (sin ventas)","🔴 Sin stock"),""),IF(G20="Sin ventas","∞ (sin ventas)",ROUND(D20*G20,0))) -> 80 | I20: =IF(OR(NOT('Catálogo Productos'!B17<>""),H20="",ISNUMBER(SEARCH("∞",TEXT(H20,"@"))),ISNUMBER(SEARCH("🔴",TEXT(H20,"@")))),"",TODAY()+H20) -> 46223 | J20: =IF(NOT('Catálogo Productos'!B17<>""),"",IF(OR(G20="Sin ventas",G20=""),"⚪ Sin ventas este mes",IF(G20<=15,"🔥 Rotación rápida",IF(G20<=30,"✅ Rotación normal","🐢 Rotación lenta")))) -> 🔥 Rotación rápida | K20: =IF('Catálogo Productos'!B17<>"",'Catálogo Productos'!G17,"") -> 20 | L20: =IF(NOT(B20<>""),"",IF(D20=0,"🔴 REPONER YA",IF(OR(M20=0,M20=""),"🟢 Sin prisa",IF(Q20<'Configuración'!$C$9,"🔴 PEDIR AHORA",IF(Q20<('Configuración'!$C$9+'Configuración'!$C$10),"🟡 Reponer pronto","🟢 Sin prisa"))))) -> 🔴 PEDIR AHORA | M20: =IF(B20="","",IF(OR(E20="",E20=0),0,ROUND(E20*('Configuración'!$C$4/'Configuración'!$C$11),1))) -> 15.5 | N20: =IF(B20="","",IF(M20=0,"—",MAX(0,CEILING(M20*('Configuración'!$C$9+'Configuración'!$C$10)-D20,1)))) -> 38 | O20: =IF(B20="","",IF(ISNUMBER(I20),I20-135,"—")) -> 46088 | P20: =IF(B20="","",IF(D20=0,"🔴 PEDIR URGENTE — sin stock",IF(OR(M20=0,M20=""),"⚪ Sin demanda — monitorear",IF(Q20<'Configuración'!$C$9,"🔴 PEDIR AHORA — "&N20&" uds (stock cubre "&Q20&" meses, lead time "&'Configuración'!$C$9&" meses)",IF(Q20<('Configuración'!$C$9+'Configuración'!$C$10),"🟡 VIGILAR — "&N20&" uds (cubre "&Q20&" meses, al límite del lead time)","🟢 OK — stock cubre "&Q20&" meses"))))) -> 🔴 PEDIR AHORA — 38 uds (stock cubre 2,6 meses, lead time 4 meses) | Q20: =IF(B20="","",IF(OR(M20=0,M20=""),999,ROUND(D20/M20,1))) -> 2.6
A21: =IF('Catálogo Productos'!B18<>"",COUNTA('Catálogo Productos'!$B$4:$B18),"") -> 15 | B21: =IF('Catálogo Productos'!B18<>"",'Catálogo Productos'!B18,"") -> Cable Pedales | C21: =IF('Catálogo Productos'!B18<>"",'Catálogo Productos'!C18,"") -> Guitarra Electrica | D21: =IF('Catálogo Productos'!B18<>"",'Catálogo Productos'!H73,"") -> 0 | E21: =IF('Catálogo Productos'!B18<>"",COUNTIF('Abril 2026 - Ventas'!$C$5:$C$303,'Catálogo Productos'!B18),"") -> 0 | F21: =IF('Catálogo Productos'!B18<>"",'Configuración'!$C$4,"") -> 31 | G21: =IF(OR(NOT('Catálogo Productos'!B18<>""),E21="",E21=0),IF('Catálogo Productos'!B18<>"","Sin ventas",""),IF(M21=0,"Sin ventas",ROUND(F21/M21,1))) -> Sin ventas | H21: =IF(OR(NOT('Catálogo Productos'!B18<>""),D21="",D21=0),IF('Catálogo Productos'!B18<>"",IF(E21=0,"∞ (sin ventas)","🔴 Sin stock"),""),IF(G21="Sin ventas","∞ (sin ventas)",ROUND(D21*G21,0))) -> ∞ (sin ventas) | I21: =IF(OR(NOT('Catálogo Productos'!B18<>""),H21="",ISNUMBER(SEARCH("∞",TEXT(H21,"@"))),ISNUMBER(SEARCH("🔴",TEXT(H21,"@")))),"",TODAY()+H21) | J21: =IF(NOT('Catálogo Productos'!B18<>""),"",IF(OR(G21="Sin ventas",G21=""),"⚪ Sin ventas este mes",IF(G21<=15,"🔥 Rotación rápida",IF(G21<=30,"✅ Rotación normal","🐢 Rotación lenta")))) -> ⚪ Sin ventas este mes | K21: =IF('Catálogo Productos'!B18<>"",'Catálogo Productos'!G18,"") -> 5 | L21: =IF(NOT(B21<>""),"",IF(D21=0,"🔴 REPONER YA",IF(OR(M21=0,M21=""),"🟢 Sin prisa",IF(Q21<'Configuración'!$C$9,"🔴 PEDIR AHORA",IF(Q21<('Configuración'!$C$9+'Configuración'!$C$10),"🟡 Reponer pronto","🟢 Sin prisa"))))) -> 🔴 REPONER YA | M21: =IF(B21="","",IF(OR(E21="",E21=0),0,ROUND(E21*('Configuración'!$C$4/'Configuración'!$C$11),1))) -> 0 | N21: =IF(B21="","",IF(M21=0,"—",MAX(0,CEILING(M21*('Configuración'!$C$9+'Configuración'!$C$10)-D21,1)))) -> — | O21: =IF(B21="","",IF(ISNUMBER(I21),I21-135,"—")) -> — | P21: =IF(B21="","",IF(D21=0,"🔴 PEDIR URGENTE — sin stock",IF(OR(M21=0,M21=""),"⚪ Sin demanda — monitorear",IF(Q21<'Configuración'!$C$9,"🔴 PEDIR AHORA — "&N21&" uds (stock cubre "&Q21&" meses, lead time "&'Configuración'!$C$9&" meses)",IF(Q21<('Configuración'!$C$9+'Configuración'!$C$10),"🟡 VIGILAR — "&N21&" uds (cubre "&Q21&" meses, al límite del lead time)","🟢 OK — stock cubre "&Q21&" meses"))))) -> 🔴 PEDIR URGENTE — sin stock | Q21: =IF(B21="","",IF(OR(M21=0,M21=""),999,ROUND(D21/M21,1))) -> 999
A22: =IF('Catálogo Productos'!B19<>"",COUNTA('Catálogo Productos'!$B$4:$B19),"") -> 16 | B22: =IF('Catálogo Productos'!B19<>"",'Catálogo Productos'!B19,"") -> Cuerdas Bajo 4C Alice | C22: =IF('Catálogo Productos'!B19<>"",'Catálogo Productos'!C19,"") -> Bajo Electrico | D22: 6 | E22: =IF('Catálogo Productos'!B19<>"",COUNTIF('Abril 2026 - Ventas'!$C$5:$C$303,'Catálogo Productos'!B19),"") -> 12 | F22: =IF('Catálogo Productos'!B19<>"",'Configuración'!$C$4,"") -> 31 | G22: =IF(OR(NOT('Catálogo Productos'!B19<>""),E22="",E22=0),IF('Catálogo Productos'!B19<>"","Sin ventas",""),IF(M22=0,"Sin ventas",ROUND(F22/M22,1))) -> 0.8 | H22: =IF(OR(NOT('Catálogo Productos'!B19<>""),D22="",D22=0),IF('Catálogo Productos'!B19<>"",IF(E22=0,"∞ (sin ventas)","🔴 Sin stock"),""),IF(G22="Sin ventas","∞ (sin ventas)",ROUND(D22*G22,0))) -> 5 | I22: =IF(OR(NOT('Catálogo Productos'!B19<>""),H22="",ISNUMBER(SEARCH("∞",TEXT(H22,"@"))),ISNUMBER(SEARCH("🔴",TEXT(H22,"@")))),"",TODAY()+H22) -> 46148 | J22: =IF(NOT('Catálogo Productos'!B19<>""),"",IF(OR(G22="Sin ventas",G22=""),"⚪ Sin ventas este mes",IF(G22<=15,"🔥 Rotación rápida",IF(G22<=30,"✅ Rotación normal","🐢 Rotación lenta")))) -> 🔥 Rotación rápida | K22: =IF('Catálogo Productos'!B19<>"",'Catálogo Productos'!G19,"") -> 10 | L22: =IF(NOT(B22<>""),"",IF(D22=0,"🔴 REPONER YA",IF(OR(M22=0,M22=""),"🟢 Sin prisa",IF(Q22<'Configuración'!$C$9,"🔴 PEDIR AHORA",IF(Q22<('Configuración'!$C$9+'Configuración'!$C$10),"🟡 Reponer pronto","🟢 Sin prisa"))))) -> 🔴 PEDIR AHORA | M22: =IF(B22="","",IF(OR(E22="",E22=0),0,ROUND(E22*('Configuración'!$C$4/'Configuración'!$C$11),1))) -> 37.2 | N22: =IF(B22="","",IF(M22=0,"—",MAX(0,CEILING(M22*('Configuración'!$C$9+'Configuración'!$C$10)-D22,1)))) -> 180 | O22: =IF(B22="","",IF(ISNUMBER(I22),I22-135,"—")) -> 46013 | P22: =IF(B22="","",IF(D22=0,"🔴 PEDIR URGENTE — sin stock",IF(OR(M22=0,M22=""),"⚪ Sin demanda — monitorear",IF(Q22<'Configuración'!$C$9,"🔴 PEDIR AHORA — "&N22&" uds (stock cubre "&Q22&" meses, lead time "&'Configuración'!$C$9&" meses)",IF(Q22<('Configuración'!$C$9+'Configuración'!$C$10),"🟡 VIGILAR — "&N22&" uds (cubre "&Q22&" meses, al límite del lead time)","🟢 OK — stock cubre "&Q22&" meses"))))) -> 🔴 PEDIR AHORA — 180 uds (stock cubre 0,2 meses, lead time 4 meses) | Q22: =IF(B22="","",IF(OR(M22=0,M22=""),999,ROUND(D22/M22,1))) -> 0.2
A23: =IF('Catálogo Productos'!B20<>"",COUNTA('Catálogo Productos'!$B$4:$B20),"") -> 17 | B23: =IF('Catálogo Productos'!B20<>"",'Catálogo Productos'!B20,"") -> Cuerdas de Viola A90 | C23: =IF('Catálogo Productos'!B20<>"",'Catálogo Productos'!C20,"") -> Viola | D23: =IF('Catálogo Productos'!B20<>"",'Catálogo Productos'!H75,"") -> 16 | E23: =IF('Catálogo Productos'!B20<>"",COUNTIF('Abril 2026 - Ventas'!$C$5:$C$303,'Catálogo Productos'!B20),"") -> 1 | F23: =IF('Catálogo Productos'!B20<>"",'Configuración'!$C$4,"") -> 31 | G23: =IF(OR(NOT('Catálogo Productos'!B20<>""),E23="",E23=0),IF('Catálogo Productos'!B20<>"","Sin ventas",""),IF(M23=0,"Sin ventas",ROUND(F23/M23,1))) -> 10 | H23: =IF(OR(NOT('Catálogo Productos'!B20<>""),D23="",D23=0),IF('Catálogo Productos'!B20<>"",IF(E23=0,"∞ (sin ventas)","🔴 Sin stock"),""),IF(G23="Sin ventas","∞ (sin ventas)",ROUND(D23*G23,0))) -> 160 | I23: =IF(OR(NOT('Catálogo Productos'!B20<>""),H23="",ISNUMBER(SEARCH("∞",TEXT(H23,"@"))),ISNUMBER(SEARCH("🔴",TEXT(H23,"@")))),"",TODAY()+H23) -> 46303 | J23: =IF(NOT('Catálogo Productos'!B20<>""),"",IF(OR(G23="Sin ventas",G23=""),"⚪ Sin ventas este mes",IF(G23<=15,"🔥 Rotación rápida",IF(G23<=30,"✅ Rotación normal","🐢 Rotación lenta")))) -> 🔥 Rotación rápida | K23: =IF('Catálogo Productos'!B20<>"",'Catálogo Productos'!G20,"") -> 5 | L23: =IF(NOT(B23<>""),"",IF(D23=0,"🔴 REPONER YA",IF(OR(M23=0,M23=""),"🟢 Sin prisa",IF(Q23<'Configuración'!$C$9,"🔴 PEDIR AHORA",IF(Q23<('Configuración'!$C$9+'Configuración'!$C$10),"🟡 Reponer pronto","🟢 Sin prisa"))))) -> 🟢 Sin prisa | M23: =IF(B23="","",IF(OR(E23="",E23=0),0,ROUND(E23*('Configuración'!$C$4/'Configuración'!$C$11),1))) -> 3.1 | N23: =IF(B23="","",IF(M23=0,"—",MAX(0,CEILING(M23*('Configuración'!$C$9+'Configuración'!$C$10)-D23,1)))) -> 0 | O23: =IF(B23="","",IF(ISNUMBER(I23),I23-135,"—")) -> 46168 | P23: =IF(B23="","",IF(D23=0,"🔴 PEDIR URGENTE — sin stock",IF(OR(M23=0,M23=""),"⚪ Sin demanda — monitorear",IF(Q23<'Configuración'!$C$9,"🔴 PEDIR AHORA — "&N23&" uds (stock cubre "&Q23&" meses, lead time "&'Configuración'!$C$9&" meses)",IF(Q23<('Configuración'!$C$9+'Configuración'!$C$10),"🟡 VIGILAR — "&N23&" uds (cubre "&Q23&" meses, al límite del lead time)","🟢 OK — stock cubre "&Q23&" meses"))))) -> 🟢 OK — stock cubre 5,2 meses | Q23: =IF(B23="","",IF(OR(M23=0,M23=""),999,ROUND(D23/M23,1))) -> 5.2
A24: =IF('Catálogo Productos'!B21<>"",COUNTA('Catálogo Productos'!$B$4:$B21),"") -> 18 | B24: =IF('Catálogo Productos'!B21<>"",'Catálogo Productos'!B21,"") -> Baqueta Bateria 5A | C24: =IF('Catálogo Productos'!B21<>"",'Catálogo Productos'!C21,"") -> Bateria | D24: =IF('Catálogo Productos'!B21<>"",'Catálogo Productos'!H76,"") -> 23 | E24: =IF('Catálogo Productos'!B21<>"",COUNTIF('Abril 2026 - Ventas'!$C$5:$C$303,'Catálogo Productos'!B21),"") -> 1 | F24: =IF('Catálogo Productos'!B21<>"",'Configuración'!$C$4,"") -> 31 | G24: =IF(OR(NOT('Catálogo Productos'!B21<>""),E24="",E24=0),IF('Catálogo Productos'!B21<>"","Sin ventas",""),IF(M24=0,"Sin ventas",ROUND(F24/M24,1))) -> 10 | H24: =IF(OR(NOT('Catálogo Productos'!B21<>""),D24="",D24=0),IF('Catálogo Productos'!B21<>"",IF(E24=0,"∞ (sin ventas)","🔴 Sin stock"),""),IF(G24="Sin ventas","∞ (sin ventas)",ROUND(D24*G24,0))) -> 230 | I24: =IF(OR(NOT('Catálogo Productos'!B21<>""),H24="",ISNUMBER(SEARCH("∞",TEXT(H24,"@"))),ISNUMBER(SEARCH("🔴",TEXT(H24,"@")))),"",TODAY()+H24) -> 46373 | J24: =IF(NOT('Catálogo Productos'!B21<>""),"",IF(OR(G24="Sin ventas",G24=""),"⚪ Sin ventas este mes",IF(G24<=15,"🔥 Rotación rápida",IF(G24<=30,"✅ Rotación normal","🐢 Rotación lenta")))) -> 🔥 Rotación rápida | K24: =IF('Catálogo Productos'!B21<>"",'Catálogo Productos'!G21,"") -> 5 | L24: =IF(NOT(B24<>""),"",IF(D24=0,"🔴 REPONER YA",IF(OR(M24=0,M24=""),"🟢 Sin prisa",IF(Q24<'Configuración'!$C$9,"🔴 PEDIR AHORA",IF(Q24<('Configuración'!$C$9+'Configuración'!$C$10),"🟡 Reponer pronto","🟢 Sin prisa"))))) -> 🟢 Sin prisa | M24: =IF(B24="","",IF(OR(E24="",E24=0),0,ROUND(E24*('Configuración'!$C$4/'Configuración'!$C$11),1))) -> 3.1 | N24: =IF(B24="","",IF(M24=0,"—",MAX(0,CEILING(M24*('Configuración'!$C$9+'Configuración'!$C$10)-D24,1)))) -> 0 | O24: =IF(B24="","",IF(ISNUMBER(I24),I24-135,"—")) -> 46238 | P24: =IF(B24="","",IF(D24=0,"🔴 PEDIR URGENTE — sin stock",IF(OR(M24=0,M24=""),"⚪ Sin demanda — monitorear",IF(Q24<'Configuración'!$C$9,"🔴 PEDIR AHORA — "&N24&" uds (stock cubre "&Q24&" meses, lead time "&'Configuración'!$C$9&" meses)",IF(Q24<('Configuración'!$C$9+'Configuración'!$C$10),"🟡 VIGILAR — "&N24&" uds (cubre "&Q24&" meses, al límite del lead time)","🟢 OK — stock cubre "&Q24&" meses"))))) -> 🟢 OK — stock cubre 7,4 meses | Q24: =IF(B24="","",IF(OR(M24=0,M24=""),999,ROUND(D24/M24,1))) -> 7.4
A25: =IF('Catálogo Productos'!B22<>"",COUNTA('Catálogo Productos'!$B$4:$B22),"") -> 19 | B25: =IF('Catálogo Productos'!B22<>"",'Catálogo Productos'!B22,"") -> Baqueta Bateria 7A | C25: =IF('Catálogo Productos'!B22<>"",'Catálogo Productos'!C22,"") -> Bateria | D25: =IF('Catálogo Productos'!B22<>"",'Catálogo Productos'!H77,"") -> 24 | E25: =IF('Catálogo Productos'!B22<>"",COUNTIF('Abril 2026 - Ventas'!$C$5:$C$303,'Catálogo Productos'!B22),"") -> 2 | F25: =IF('Catálogo Productos'!B22<>"",'Configuración'!$C$4,"") -> 31 | G25: =IF(OR(NOT('Catálogo Productos'!B22<>""),E25="",E25=0),IF('Catálogo Productos'!B22<>"","Sin ventas",""),IF(M25=0,"Sin ventas",ROUND(F25/M25,1))) -> 5 | H25: =IF(OR(NOT('Catálogo Productos'!B22<>""),D25="",D25=0),IF('Catálogo Productos'!B22<>"",IF(E25=0,"∞ (sin ventas)","🔴 Sin stock"),""),IF(G25="Sin ventas","∞ (sin ventas)",ROUND(D25*G25,0))) -> 120 | I25: =IF(OR(NOT('Catálogo Productos'!B22<>""),H25="",ISNUMBER(SEARCH("∞",TEXT(H25,"@"))),ISNUMBER(SEARCH("🔴",TEXT(H25,"@")))),"",TODAY()+H25) -> 46263 | J25: =IF(NOT('Catálogo Productos'!B22<>""),"",IF(OR(G25="Sin ventas",G25=""),"⚪ Sin ventas este mes",IF(G25<=15,"🔥 Rotación rápida",IF(G25<=30,"✅ Rotación normal","🐢 Rotación lenta")))) -> 🔥 Rotación rápida | K25: =IF('Catálogo Productos'!B22<>"",'Catálogo Productos'!G22,"") -> 5 | L25: =IF(NOT(B25<>""),"",IF(D25=0,"🔴 REPONER YA",IF(OR(M25=0,M25=""),"🟢 Sin prisa",IF(Q25<'Configuración'!$C$9,"🔴 PEDIR AHORA",IF(Q25<('Configuración'!$C$9+'Configuración'!$C$10),"🟡 Reponer pronto","🟢 Sin prisa"))))) -> 🔴 PEDIR AHORA | M25: =IF(B25="","",IF(OR(E25="",E25=0),0,ROUND(E25*('Configuración'!$C$4/'Configuración'!$C$11),1))) -> 6.2 | N25: =IF(B25="","",IF(M25=0,"—",MAX(0,CEILING(M25*('Configuración'!$C$9+'Configuración'!$C$10)-D25,1)))) -> 7 | O25: =IF(B25="","",IF(ISNUMBER(I25),I25-135,"—")) -> 46128 | P25: =IF(B25="","",IF(D25=0,"🔴 PEDIR URGENTE — sin stock",IF(OR(M25=0,M25=""),"⚪ Sin demanda — monitorear",IF(Q25<'Configuración'!$C$9,"🔴 PEDIR AHORA — "&N25&" uds (stock cubre "&Q25&" meses, lead time "&'Configuración'!$C$9&" meses)",IF(Q25<('Configuración'!$C$9+'Configuración'!$C$10),"🟡 VIGILAR — "&N25&" uds (cubre "&Q25&" meses, al límite del lead time)","🟢 OK — stock cubre "&Q25&" meses"))))) -> 🔴 PEDIR AHORA — 7 uds (stock cubre 3,9 meses, lead time 4 meses) | Q25: =IF(B25="","",IF(OR(M25=0,M25=""),999,ROUND(D25/M25,1))) -> 3.9
